Workbook

Sheet Cover
C4: Comparable Valuation Modeling | L4: CONFIDENTIAL
C7: Table of Contents | H7: Model Checks
C9: Dashboard | H9: Blended weights ≠ 100%? | L9: =IF(ABS(Valuation!C51-1)>0.0001,1,0) -> 0
C10: Valuation | H10: Selected low > high on any method? | L10: =IF(Valuation!L22>Valuation!M22,1,0)+IF(Valuation!L23>Valuation!M23,1,0)+IF(Valuation!L24>Valuation!M24,1,0)+IF(Valuation!L25>Valuation!M25,1,0)+IF(Valuation!L26>Valuation!M26,1,0) -> 0
C11: Trading_Comps | H11: Include flags not 0/1 (peers & deals)? | L11: =IF(COUNTIF(Peer_Inputs!Q13:Q20,1)+COUNTIF(Peer_Inputs!Q13:Q20,0)<>8,1,0)+IF(COUNTIF(Precedent_Txns!O8:O14,1)+COUNTIF(Precedent_Txns!O8:O14,0)<>7,1,0) -> 0
C12: Precedent_Txns | H12: Fewer than 4 peers included? | L12: =IF(COUNTIF(Peer_Inputs!Q13:Q20,1)<4,1,0) -> 0
C13: Peer_Inputs | H13: Any peer with EBITDA ≤ 0? | L13: =IF(COUNTIF(Peer_Inputs!G25:I32,"<=0")>0,1,0) -> 0
C14: Nestle_Inputs | H14: DCF base value not tied to DCF Model sheet? | L14: =Nestle_Inputs!F72 -> 0
H15: Range switches outside 1–3? | L15: =IF(OR(Valuation!D16<1,Valuation!D16>3,Valuation!D18<1,Valuation!D18>3),1,0) -> 0
C16: Model Guide
C18: Adjustable Input | D18: (Grey Cell)
C19: Hardcode | D19: (Blue Font)
C20: Formula | D20: (Black Font)
C23: DISCLAIMER & NOTICE OF INTENT
C24: 1. Independent Portfolio Project: This financial model and dashboard were prepared solely by the author, in a personal capacity, to demonstrate
C25: skills in financial modeling and financial statement analysis. They do not reflect the views of any employer.
C26: 2. Public Data Sources: Historical figures are drawn from publicly available sources (Nestlé Investor Relations / Annual Reports). Forecasts and
C27: scenarios (Best / Base / Worst) are the author's own illustrative assumptions, not forecasts issued by Nestlé.
C28: 3. No Affiliation: This project is not affiliated with, authorized by, or endorsed by Nestlé S.A. Nestlé and related names and marks are the
C29: property of their respective owners and are used for identification only.
C30: 4. No Advice: Nothing herein constitutes investment advice, equity research, or a recommendation to buy or sell any security.

Sheet Dashboard
B2: Base Case | Pricing 1-Oct-2026 | Valuation date 30-Jun-2026 | CHF
B4: Current price (CHF) | D4: Analyst Mean target (CHF) | F4: Blended fair value (CHF) | H4: DCF Base Value (CHF) | J4: DCF Exit Multiple (CHF) | L4: Nestlé EV/EBITDA 26F | N4: Peer median EV/EBITDA 26F | P4: Precedent median (All Deals)
B5: =Valuation!D8 -> 74.63 | D5: =H74 -> 88.23 | F5: =Valuation!D52 -> 84.230228 | H5: =$H$80 -> 97.386661 | J5: =G93 -> 82.385576 | L5: =E108 -> 11.715013 | N5: =C109 -> 11.537647 | P5: =Precedent_Txns!L19 -> 14.298297
D6: =TEXT(I95,"+0.0%;-0.0%")&" vs price" -> +18.2% vs price | F6: =TEXT(I96,"+0.0%;-0.0%")&" vs price" -> +12.9% vs price | H6: =TEXT(I92,"+0.0%;-0.0%")&" vs price" -> +30.5% vs price | J6: =TEXT(I93,"+0.0%;-0.0%")&" vs price" -> +10.4% vs price | L6: =TEXT(Trading_Comps!J30,"+0%;-0%")&" vs peer median" -> +2% vs peer median | N6: ="Implied CHF "&TEXT(Valuation!I30,"0.0")&" ("&TEXT(Valuation!J30,"+0.0%;-0.0%")&")" -> Implied CHF 76.1 (+2.0%) | P6: ="Implied CHF "&TEXT(G90,"0.0")&" ("&TEXT(I90,"+0.0%;-0.0%")&")" -> Implied CHF 91.6 (+22.8%)
B8: Valuation Summary | J8: EV / Adj. EBITDA 2026F – Nestlé vs peers
B30: Quality vs Value | J30: Fair Value Bridge
B54: Key Takeaways
B56: ="1. Blended fair value CHF "&TEXT(Valuation!D52,"0.0")&"/sh vs current CHF "&TEXT(Valuation!D8,"0.00")&" ("&TEXT(Valuation!D53,"+0.0%;-0.0%")&") -> "&Valuation!D59&". Implied EV/EBITDA 26F "&TEXT(Valuation!D56,"0.0")&"x." -> 1. Blended fair value CHF 84.2/sh vs current CHF 74.63 (+12.9%) -> FAIRLY VALUED (within ±15%). Implied EV/EBITDA 26F 13.1x.
B57: ="2. Nestlé trades at "&TEXT(Trading_Comps!J17,"0.0")&"x EV/EBITDA 26F vs peer median "&TEXT(Trading_Comps!J22,"0.0")&"x ("&TEXT(Trading_Comps!J30,"+0%;-0%")&") and Tier 1 median "&TEXT(Trading_Comps!J27,"0.0")&"x: after the 2025-26 de-rating its historical quality premium has largely gone, so peer multiples now point to roughly today's price (Tier 1 EV/EBITDA mid CHF "&TEXT(Valuation!I30,"0.0")&"/sh)." -> 2. Nestlé trades at 11.7x EV/EBITDA 26F vs peer median 11.5x (+2%) and Tier 1 median 12.3x: after the 2025-26 de-rating its historical quality premium has largely gone, so peer multiples now point to roughly today's price (Tier 1 EV/EBITDA mid CHF 76.1/sh).
B58: ="3. The DCF (base CHF "&TEXT(Valuation!I35,"0.0")&"/sh perpetuity; "&TEXT(Valuation!I36,"0.0")&" exit) is the most optimistic intrinsic view – it capitalises the 2027-30 margin recovery from 'Fuel for Growth' that the market is not yet paying for." -> 3. The DCF (base CHF 97.4/sh perpetuity; 82.4 exit) is the most optimistic intrinsic view – it capitalises the 2027-30 margin recovery from 'Fuel for Growth' that the market is not yet paying for.
B59: ="4. Precedents (control) imply CHF "&TEXT(Valuation!G33,"0")&"–"&TEXT(Valuation!H33,"0")&"/sh: a theoretical takeout value only – at EV ~CHF "&TEXT(Nestle_Inputs!D54/1000,"0")&"bn Nestlé is effectively un-acquirable, so precedents carry 0% weight." -> 4. Precedents (control) imply CHF 87–96/sh: a theoretical takeout value only – at EV ~CHF 212bn Nestlé is effectively un-acquirable, so precedents carry 0% weight.
B60: 5. Watch-points: Russia placed Nestlé Russia under temporary external administration (17-Sep-2026; c.1% of group sales, potential write-off c.CHF 1bn per analysts); peer prices refreshed to 1-Oct-2026 and peer consensus is approximate
B69: Chart Data
B72: Methodology | E72: Low | F72: High | G72: Delta | H72: Mid / Base | I72: Category
B73: 52-Week Trading Range | E73: =Valuation!G37 -> 70.29 | F73: =Valuation!H37 -> 87.09 | G73: =F73-E73 -> 16.8 | H73: =Valuation!I37 -> 78.69 | I73: Market
B74: Analyst Price Targets | E74: =Valuation!G38 -> 69 | F74: =Valuation!H38 -> 100 | G74: =F74-E74 -> 31 | H74: =Valuation!I38 -> 88.23 | I74: Market
B75: Trading Comps – EV/EBITDA 2026F | E75: =Valuation!G30 -> 72.020413 | F75: =Valuation!H30 -> 80.170195 | G75: =F75-E75 -> 8.1497817 | H75: =Valuation!I30 -> 76.095304 | I75: Trading comps
B76: Trading Comps – EV/EBITDA 2027F | E76: =Valuation!G31 -> 68.700287 | F76: =Valuation!H31 -> 75.818583 | G76: =F76-E76 -> 7.1182965 | H76: =Valuation!I31 -> 72.259435 | I76: Trading comps
B77: Trading Comps – P/E 2026F | E77: =Valuation!G32 -> 70.697802 | F77: =Valuation!H32 -> 82.722763 | G77: =F77-E77 -> 12.024961 | H77: =Valuation!I32 -> 76.710282 | I77: Trading comps
B78: Precedents – EV/LTM EBITDA | E78: =Valuation!G33 -> 87.376175 | F78: =Valuation!H33 -> 95.90652 | G78: =F78-E78 -> 8.5303448 | H78: =Valuation!I33 -> 91.641348 | I78: Precedents
B79: Precedents – Premiums Paid | E79: =Valuation!G34 -> 103.36255 | F79: =Valuation!H34 -> 108.2135 | G79: =F79-E79 -> 4.85095 | H79: =Valuation!I34 -> 105.78803 | I79: Precedents
B80: DCF – Perpetuity Growth | E80: =Valuation!G35 -> 76.327196 | F80: =Valuation!H35 -> 134.66465 | G80: =F80-E80 -> 58.337458 | H80: =Valuation!I35 -> 97.386661 | I80: DCF
B81: DCF – Exit Multiple | E81: =Valuation!G36 -> 77.715302 | F81: =Valuation!H36 -> 87.258217 | G81: =F81-E81 -> 9.5429149 | H81: =Valuation!I36 -> 82.385576 | I81: DCF
B82: Current Share Price | E82: =Valuation!D8-0.4 -> 74.23 | F82: =Valuation!D8+0.4 -> 75.03 | G82: =F82-E82 -> 0.8 | H82: =Valuation!D8 -> 74.63 | I82: Reference
B83: Blended Fair Value | E83: =Valuation!D52-0.4 -> 83.830228 | F83: =Valuation!D52+0.4 -> 84.630228 | G83: =F83-E83 -> 0.8 | H83: =Valuation!D52 -> 84.230228 | I83: Reference
B86: Methodology | E86: Low | F86: High | G86: Mid / Base | H86: Weight | I86: vs price
B87: =Valuation!B30 -> Trading comps – EV/EBITDA 2026F | E87: =Valuation!G30 -> 72.020413 | F87: =Valuation!H30 -> 80.170195 | G87: =Valuation!I30 -> 76.095304 | H87: =Valuation!C42 -> 0.2 | I87: =Valuation!J30 -> 0.019634251
B88: =Valuation!B31 -> Trading comps – EV/EBITDA 2027F | E88: =Valuation!G31 -> 68.700287 | F88: =Valuation!H31 -> 75.818583 | G88: =Valuation!I31 -> 72.259435 | H88: =Valuation!C43 -> 0.1 | I88: =Valuation!J31 -> -0.031764234
B89: =Valuation!B32 -> Trading comps – P/E 2026F | E89: =Valuation!G32 -> 70.697802 | F89: =Valuation!H32 -> 82.722763 | G89: =Valuation!I32 -> 76.710282 | H89: =Valuation!C44 -> 0.2 | I89: =Valuation!J32 -> 0.027874612
B90: =Valuation!B33 -> Precedents – EV/LTM EBITDA | E90: =Valuation!G33 -> 87.376175 | F90: =Valuation!H33 -> 95.90652 | G90: =Valuation!I33 -> 91.641348 | H90: =Valuation!C45 -> 0 | I90: =Valuation!J33 -> 0.22794249
B91: =Valuation!B34 -> Precedents – Premiums paid | E91: =Valuation!G34 -> 103.36255 | F91: =Valuation!H34 -> 108.2135 | G91: =Valuation!I34 -> 105.78803 | H91: =Valuation!C46 -> 0 | I91: =Valuation!J34 -> 0.4175
B92: =Valuation!B35 -> DCF – Perpetuity growth | E92: =Valuation!G35 -> 76.327196 | F92: =Valuation!H35 -> 134.66465 | G92: =Valuation!I35 -> 97.386661 | H92: =Valuation!C47 -> 0.35 | I92: =Valuation!J35 -> 0.30492645
B93: =Valuation!B36 -> DCF – Exit multiple | E93: =Valuation!G36 -> 77.715302 | F93: =Valuation!H36 -> 87.258217 | G93: =Valuation!I36 -> 82.385576 | H93: =Valuation!C48 -> 0.15 | I93: =Valuation!J36 -> 0.10392036
B94: =Valuation!B37 -> 52-week trading range | E94: =Valuation!G37 -> 70.29 | F94: =Valuation!H37 -> 87.09 | G94: =Valuation!I37 -> 78.69 | H94: =Valuation!C49 -> 0 | I94: =Valuation!J37 -> 0.054401715
B95: =Valuation!B38 -> Analyst price targets | E95: =Valuation!G38 -> 69 | F95: =Valuation!H38 -> 100 | G95: =Valuation!I38 -> 88.23 | H95: =Valuation!C50 -> 0 | I95: =Valuation!J38 -> 0.18223235
B96: Blended fair value | G96: =Valuation!D52 -> 84.230228 | H96: =Valuation!C51 -> 1 | I96: =Valuation!D53 -> 0.12863766
B99: Company | C99: EV/EBITDA 26E | D99: EBITDA mgn 26E | E99: Nestlé EV/EBITDA
B100: =Trading_Comps!B8 -> Danone | C100: =Trading_Comps!J8 -> 9.2149408 | D100: =Trading_Comps!H37 -> 0.17915194
B101: =Trading_Comps!B9 -> Unilever | C101: =Trading_Comps!J9 -> 12.453593 | D101: =Trading_Comps!H38 -> 0.23251418
B102: =Trading_Comps!B10 -> PepsiCo | C102: =Trading_Comps!J10 -> 12.054607 | D102: =Trading_Comps!H39 -> 0.18483904
B103: =Trading_Comps!B11 -> Mondelez | C103: =Trading_Comps!J11 -> 12.644077 | D103: =Trading_Comps!H40 -> 0.18434343
B104: =Trading_Comps!B12 -> Coca-Cola | C104: =Trading_Comps!J12 -> 22.705917 | D104: =Trading_Comps!H41 -> 0.33665339
B105: =Trading_Comps!B13 -> Hershey | C105: =Trading_Comps!J13 -> 11.020687 | D105: =Trading_Comps!H42 -> 0.27346939
B106: =Trading_Comps!B14 -> General Mills | C106: =Trading_Comps!J14 -> 9.0433853 | D106: =Trading_Comps!H43 -> 0.19035698
B107: =Trading_Comps!B15 -> Kraft Heinz | C107: =Trading_Comps!J15 -> 8.5318037 | D107: =Trading_Comps!H44 -> 0.22153209
B108: Nestlé | C108: =Trading_Comps!J17 -> 11.715013 | D108: =Trading_Comps!H45 -> 0.2016 | E108: =Trading_Comps!J17 -> 11.715013
B109: Peer median | C109: =Trading_Comps!J22 -> 11.537647
C112: Contribution
B113: DCF – Perpetuity | C113: =Valuation!E47 -> 34.085331
B114: DCF – Exit multiple | C114: =Valuation!E48 -> 12.357836
B115: Comps – EV/EBITDA 26F | C115: =Valuation!E42 -> 15.219061
B116: Comps – EV/EBITDA 27F | C116: =Valuation!E43 -> 7.2259435
B117: Comps – P/E 26F | C117: =Valuation!E44 -> 15.342056
B118: Blended fair value | C118: =Valuation!D52 -> 84.230228
B119: Current price | C119: =Dashboard!H82 -> 74.63

Sheet Valuation
O1: Basis of Assumption / Source
B3: Valuation – Implied Nestle Value per Share by Methodology
B5: All figures in CHF millions unless stated
B7: Key inputs | C7: Unit | D7: Value
B8: Current share price | C8: CHF/sh | D8: =Nestle_Inputs!D41 -> 74.63
B9: Diluted shares | C9: mm | D9: =Nestle_Inputs!D42 -> 2573
B10: EV → Equity adjustment | D10: =Nestle_Inputs!D52 -> -20386.48
B11: Adj. EBITDA 2025A (LTM proxy) | D11: =Nestle_Inputs!F22 -> 18022 | O11: FY2025A adjusted EBITDA used as LTM (see Nestle_Inputs). Precedent multiples are on LTM EBITDA, so they must be applied to an LTM figure, not a forecast.
B12: Adj. EBITDA 2026E | D12: =Nestle_Inputs!G22 -> 18131.39
B13: Adj. EBITDA 2027E | D13: =Nestle_Inputs!H22 -> 18174.785
B14: Adj. net profit excl. associates 2026E | D14: =Nestle_Inputs!G28 -> 9833.2191
B15: L'Oréal stake at market | D15: =Nestle_Inputs!D51 -> 37092.52
B16: Trading comps range basis | C16: switch | D16: 2 | O16: Default = 2 (Tier 1 IQR): Danone, Unilever, PepsiCo and Mondelez are the only peers with Nestlé-like global scale, category breadth and EM exposure. Switch to 1 to use all 8 peers, or 3 to type your own low/high in the Manual columns below.
B18: Precedents range basis | C18: switch | D18: 2 | O18: Default = 2 (Large-cap deals only, EV > USD 20bn): closest to Nestlé's scale; small brand deals (Sovos, Hostess) carry scarcity/growth premia that do not transfer. Switch to 1 for all 7 deals or 3 for the manual range.
B21: Multiple range selection | C21: Nestlé metric | D21: All: 25th | E21: All: Median | F21: All: 75th | G21: Subset: 25th | H21: Subset: Median | I21: Subset: 75th | J21: Manual low | K21: Manual high | L21: Selected low | M21: Selected high
B22: Trading comps – EV/EBITDA 2026E | C22: =D12 -> 18131.39 | D22: =Trading_Comps!J23 -> 9.1720519 | E22: =Trading_Comps!J22 -> 11.537647 | F22: =Trading_Comps!J20 -> 12.501214 | G22: =Trading_Comps!J28 -> 11.34469 | H22: =Trading_Comps!J27 -> 12.2541 | I22: =Trading_Comps!J26 -> 12.501214 | J22: 11 | K22: 13 | L22: =CHOOSE($D$16,D22,G22,J22) -> 11.34469 | M22: =CHOOSE($D$16,F22,I22,K22) -> 12.501214 | O22: Subset columns = Tier 1 for trading comps, Large-cap for precedents. Manual defaults (blue) reflect a 'Nestlé premium' view: ~Tier 1 median to +1.5x, justified by scale and historic premium – use when you want to express a view rather than the pure statistics.
B23: Trading comps – EV/EBITDA 2027E | C23: =D13 -> 18174.785 | D23: =Trading_Comps!K23 -> 8.9223139 | E23: =Trading_Comps!K22 -> 10.924391 | F23: =Trading_Comps!K20 -> 11.855309 | G23: =Trading_Comps!K28 -> 10.847574 | H23: =Trading_Comps!K27 -> 11.684844 | I23: =Trading_Comps!K26 -> 11.855309 | J23: 10.5 | K23: 12.5 | L23: =CHOOSE($D$16,D23,G23,J23) -> 10.847574 | M23: =CHOOSE($D$16,F23,I23,K23) -> 11.855309
B24: Trading comps – P/E 2026E (ex-L'Oréal) | C24: =D14 -> 9833.2191 | D24: =Trading_Comps!P23 -> 13.378607 | E24: =Trading_Comps!P22 -> 16.191275 | F24: =Trading_Comps!P20 -> 19.119945 | G24: =Trading_Comps!P28 -> 14.726909 | H24: =Trading_Comps!P27 -> 16.191275 | I24: =Trading_Comps!P26 -> 17.873409 | J24: 15 | K24: 18 | L24: =CHOOSE($D$16,D24,G24,J24) -> 14.726909 | M24: =CHOOSE($D$16,F24,I24,K24) -> 17.873409 | O24: P/E applied to Nestlé's adjusted net profit EXCLUDING associates; the L'Oréal stake is then added at market value (sum-of-the-parts) – avoids pricing L'Oréal earnings at a food multiple.
B25: Precedents – EV/LTM EBITDA | C25: =D11 -> 18022 | D25: =Precedent_Txns!L20 -> 13.410181 | E25: =Precedent_Txns!L19 -> 14.298297 | F25: =Precedent_Txns!L17 -> 16.637591 | G25: =Precedent_Txns!L25 -> 13.605892 | H25: =Precedent_Txns!L24 -> 14.04995 | I25: =Precedent_Txns!L23 -> 14.823769 | J25: 13 | K25: 16 | L25: =CHOOSE($D$18,D25,G25,J25) -> 13.605892 | M25: =CHOOSE($D$18,F25,I25,K25) -> 14.823769
B26: Precedents – Premium paid (to current price) | C26: =D8 -> 74.63 | D26: =Precedent_Txns!N20 -> 0.3475 | E26: =Precedent_Txns!N19 -> 0.42 | F26: =Precedent_Txns!N17 -> 0.455 | G26: =Precedent_Txns!N25 -> 0.385 | H26: =Precedent_Txns!N24 -> 0.44 | I26: =Precedent_Txns!N23 -> 0.45 | J26: 0.3 | K26: 0.45 | L26: =CHOOSE($D$18,D26,G26,J26) -> 0.385 | M26: =CHOOSE($D$18,F26,I26,K26) -> 0.45 | O26: Premium applied to the current share price as the 'unaffected' price (no bid speculation in Nestlé's price today).
B29: Implied valuation | C29: EV low | D29: EV high | E29: Equity low | F29: Equity high | G29: Per share low | H29: Per share high | I29: Mid / Base | J29: Up / (down) vs price | K29: Implied EV/EBITDA 26E (mid) | L29: Basis
B30: Trading comps – EV/EBITDA 2026F | C30: =L22*C22 -> 205695 | D30: =M22*C22 -> 226664.39 | E30: =C30+$D$10 -> 185308.52 | F30: =D30+$D$10 -> 206277.91 | G30: =E30/$D$9 -> 72.020413 | H30: =F30/$D$9 -> 80.170195 | I30: =AVERAGE(G30:H30) -> 76.095304 | J30: =I30/$D$8-1 -> 0.019634251 | K30: =(I30*$D$9-$D$10)/$D$12 -> 11.922952 | L30: Minority | O30: Mechanics: Implied EV = selected multiple x Nestlé metric -> + EV/Equity adjustment (Nestle_Inputs) -> / diluted shares. 'Mid / Base' = average of low & high for multiples; = DCF base case for DCF rows (the DCF range is not symmetric).
B31: Trading comps – EV/EBITDA 2027F | C31: =L23*C23 -> 197152.32 | D31: =M23*C23 -> 215467.7 | E31: =C31+$D$10 -> 176765.84 | F31: =D31+$D$10 -> 195081.22 | G31: =E31/$D$9 -> 68.700287 | H31: =F31/$D$9 -> 75.818583 | I31: =AVERAGE(G31:H31) -> 72.259435 | J31: =I31/$D$8-1 -> -0.031764234 | K31: =(I31*$D$9-$D$10)/$D$12 -> 11.37861 | L31: Minority
B32: Trading comps – P/E 2026F | C32: =E32-$D$10 -> 202291.92 | D32: =F32-$D$10 -> 233232.15 | E32: =L24*C24+$D$15 -> 181905.44 | F32: =M24*C24+$D$15 -> 212845.67 | G32: =E32/$D$9 -> 70.697802 | H32: =F32/$D$9 -> 82.722763 | I32: =AVERAGE(G32:H32) -> 76.710282 | J32: =I32/$D$8-1 -> 0.027874612 | K32: =(I32*$D$9-$D$10)/$D$12 -> 12.010223 | L32: Minority
B33: Precedents – EV/LTM EBITDA | C33: =L25*C25 -> 245205.38 | D33: =M25*C25 -> 267153.96 | E33: =C33+$D$10 -> 224818.9 | F33: =D33+$D$10 -> 246767.48 | G33: =E33/$D$9 -> 87.376175 | H33: =F33/$D$9 -> 95.90652 | I33: =AVERAGE(G33:H33) -> 91.641348 | J33: =I33/$D$8-1 -> 0.22794249 | K33: =(I33*$D$9-$D$10)/$D$12 -> 14.129069 | L33: Control | O33: Control-basis values: include a takeover premium and buyer synergies -> not directly comparable with the minority (trading) share price.
B34: Precedents – Premiums paid | C34: =E34-$D$10 -> 286338.32 | D34: =F34-$D$10 -> 298819.82 | E34: =C26*(1+L26)*$D$9 -> 265951.84 | F34: =C26*(1+M26)*$D$9 -> 278433.34 | G34: =E34/$D$9 -> 103.36255 | H34: =F34/$D$9 -> 108.2135 | I34: =AVERAGE(G34:H34) -> 105.78803 | J34: =I34/$D$8-1 -> 0.4175 | K34: =(I34*$D$9-$D$10)/$D$12 -> 16.136604 | L34: Control
B35: DCF – Perpetuity growth | C35: =Nestle_Inputs!D67 -> 216776.36 | D35: =Nestle_Inputs!F67 -> 366878.64 | E35: =C35+$D$10 -> 196389.88 | F35: =D35+$D$10 -> 346492.16 | G35: =E35/$D$9 -> 76.327196 | H35: =F35/$D$9 -> 134.66465 | I35: =(Nestle_Inputs!E67+$D$10)/$D$9 -> 97.386661 | J35: =I35/$D$8-1 -> 0.30492645 | K35: =(I35*$D$9-$D$10)/$D$12 -> 14.944379 | L35: Intrinsic | O35: From the DCF model (full equity bridge). Low/High = WACC ±0.5% and g ±0.5% (perpetuity) / exit multiple ±0.5x.
B36: DCF – Exit multiple | C36: =Nestle_Inputs!D68 -> 220347.95 | D36: =Nestle_Inputs!F68 -> 244901.87 | E36: =C36+$D$10 -> 199961.47 | F36: =D36+$D$10 -> 224515.39 | G36: =E36/$D$9 -> 77.715302 | H36: =F36/$D$9 -> 87.258217 | I36: =(Nestle_Inputs!E68+$D$10)/$D$9 -> 82.385576 | J36: =I36/$D$8-1 -> 0.10392036 | K36: =(I36*$D$9-$D$10)/$D$12 -> 12.815596 | L36: Intrinsic
B37: 52-week trading range | G37: =Nestle_Inputs!D56 -> 70.29 | H37: =Nestle_Inputs!D57 -> 87.09 | I37: =AVERAGE(G37:H37) -> 78.69 | J37: =I37/$D$8-1 -> 0.054401715 | K37: =(I37*$D$9-$D$10)/$D$12 -> 12.291162 | L37: Market ref. | O37: Market references: not valuation methods, but they show where the market / sell-side currently is. Mid for 52-week = simple average; analyst mid = consensus mean target.
B38: Analyst price targets | G38: =Nestle_Inputs!D58 -> 69 | H38: =Nestle_Inputs!D59 -> 100 | I38: =Nestle_Inputs!D60 -> 88.23 | J38: =I38/$D$8-1 -> 0.18223235 | K38: =(I38*$D$9-$D$10)/$D$12 -> 13.64497 | L38: Market ref.
B41: Blended valuation (fair value, minority basis) | C41: Weight | D41: Mid / Base (CHF/sh) | E41: Contribution | F41: Basis
B42: =B30 -> Trading comps – EV/EBITDA 2026F | C42: 0.2 | D42: =I30 -> 76.095304 | E42: =C42*D42 -> 15.219061 | F42: =L30 -> Minority | O42: Weights are a judgement call. Default: DCF 50% (35% perpetuity + 15% exit – intrinsic, reflects our explicit 2026-30 plan), trading comps 50% (market cross-check). Precedents & premiums = 0% because they are CONTROL values and a takeover of Nestlé is not a realistic scenario; 52-week & analyst targets = 0% because they are market references, not methods. Change weights freely – the total must equal 100% (see Cover check).
B43: =B31 -> Trading comps – EV/EBITDA 2027F | C43: 0.1 | D43: =I31 -> 72.259435 | E43: =C43*D43 -> 7.2259435 | F43: =L31 -> Minority
B44: =B32 -> Trading comps – P/E 2026F | C44: 0.2 | D44: =I32 -> 76.710282 | E44: =C44*D44 -> 15.342056 | F44: =L32 -> Minority
B45: =B33 -> Precedents – EV/LTM EBITDA | C45: 0 | D45: =I33 -> 91.641348 | E45: =C45*D45 -> 0 | F45: =L33 -> Control
B46: =B34 -> Precedents – Premiums paid | C46: 0 | D46: =I34 -> 105.78803 | E46: =C46*D46 -> 0 | F46: =L34 -> Control
B47: =B35 -> DCF – Perpetuity growth | C47: 0.35 | D47: =I35 -> 97.386661 | E47: =C47*D47 -> 34.085331 | F47: =L35 -> Intrinsic
B48: =B36 -> DCF – Exit multiple | C48: 0.15 | D48: =I36 -> 82.385576 | E48: =C48*D48 -> 12.357836 | F48: =L36 -> Intrinsic
B49: =B37 -> 52-week trading range | C49: 0 | D49: =I37 -> 78.69 | E49: =C49*D49 -> 0 | F49: =L37 -> Market ref.
B50: =B38 -> Analyst price targets | C50: 0 | D50: =I38 -> 88.23 | E50: =C50*D50 -> 0 | F50: =L38 -> Market ref.
B51: Total weight | C51: =SUM(C42:C50) -> 1
B52: Blended fair value per share | D52: =IF(C51=0,0,SUMPRODUCT(C42:C50,D42:D50)/C51) -> 84.230228 | O52: Blended fair value = weighted average of the mid/base values (weights normalised to 100%).
B53: Upside / (downside) vs current price | D53: =D52/$D$8-1 -> 0.12863766
B54: Implied equity value | D54: =D52*$D$9 -> 216724.38
B55: Implied enterprise value | D55: =D54-$D$10 -> 237110.86
B56: Implied EV / adj. EBITDA 2026E | D56: =D55/$D$12 -> 13.077368
B57: Implied P/E 2026E (ex-L'Oréal) | D57: =(D54-$D$15)/$D$14 -> 18.267859
B58: Control value reference (precedents EV/EBITDA mid) | D58: =I33 -> 91.641348
B59: Valuation signal | D59: =IF(D53>0.15,"UNDERVALUED (>15% upside)",IF(D53<-0.15,"OVERVALUED (>15% downside)","FAIRLY VALUED (within ±15%)")) -> FAIRLY VALUED (within ±15%) | O59: Signal thresholds ±15% – a typical buy-/sell-side materiality band for a low-volatility large-cap staple.

Sheet Trading_Comps
S1: Basis of Assumption / Source
B3: Trading Comparables – Valuation Multiples & Operating Benchmarking
B6: Company | C6: Tier | D6: Market cap (CHF mm) | E6: EV (CHF mm) | F6: EV / Sales | I6: EV / EBITDA | L6: EV / EBIT | O6: P / E
F7: 2025A | G7: 2026F | H7: 2027F | I7: 2025A | J7: 2026F | K7: 2027F | L7: 2025A | M7: 2026F | N7: 2027F | O7: 2025A | P7: 2026F | Q7: 2027F
B8: =Peer_Inputs!B13 -> Danone | C8: =Peer_Inputs!D13 -> 1 | D8: =Peer_Inputs!O13 -> 34521.368 | E8: =Peer_Inputs!P13 -> 43449.368 | F8: =IF(Peer_Inputs!D25>0,Peer_Inputs!$M13/Peer_Inputs!D25,"n.m.") -> 1.7019945 | G8: =IF(Peer_Inputs!E25>0,Peer_Inputs!$M13/Peer_Inputs!E25,"n.m.") -> 1.6508746 | H8: =IF(Peer_Inputs!F25>0,Peer_Inputs!$M13/Peer_Inputs!F25,"n.m.") -> 1.5918143 | I8: =IF(Peer_Inputs!G25>0,Peer_Inputs!$M13/Peer_Inputs!G25,"n.m.") -> 9.6230175 | J8: =IF(Peer_Inputs!H25>0,Peer_Inputs!$M13/Peer_Inputs!H25,"n.m.") -> 9.2149408 | K8: =IF(Peer_Inputs!I25>0,Peer_Inputs!$M13/Peer_Inputs!I25,"n.m.") -> 8.7819079 | L8: =IF(Peer_Inputs!J25>0,Peer_Inputs!$M13/Peer_Inputs!J25,"n.m.") -> 12.609919 | M8: =IF(Peer_Inputs!K25>0,Peer_Inputs!$M13/Peer_Inputs!K25,"n.m.") -> 11.964085 | N8: =IF(Peer_Inputs!L25>0,Peer_Inputs!$M13/Peer_Inputs!L25,"n.m.") -> 11.284964 | O8: =IF(Peer_Inputs!M25>0,Peer_Inputs!$G13/Peer_Inputs!M25,"n.m.") -> 15.144737 | P8: =IF(Peer_Inputs!N25>0,Peer_Inputs!$G13/Peer_Inputs!N25,"n.m.") -> 14.31592 | Q8: =IF(Peer_Inputs!O25>0,Peer_Inputs!$G13/Peer_Inputs!O25,"n.m.") -> 13.321759
B9: =Peer_Inputs!B14 -> Unilever | C9: =Peer_Inputs!D14 -> 1 | D9: =Peer_Inputs!O14 -> 105256.66 | E9: =Peer_Inputs!P14 -> 142456.66 | F9: =IF(Peer_Inputs!D26>0,Peer_Inputs!$M14/Peer_Inputs!D26,"n.m.") -> 2.9571274 | G9: =IF(Peer_Inputs!E26>0,Peer_Inputs!$M14/Peer_Inputs!E26,"n.m.") -> 2.8956371 | H9: =IF(Peer_Inputs!F26>0,Peer_Inputs!$M14/Peer_Inputs!F26,"n.m.") -> 2.800351 | I9: =IF(Peer_Inputs!G26>0,Peer_Inputs!$M14/Peer_Inputs!G26,"n.m.") -> 12.818343 | J9: =IF(Peer_Inputs!H26>0,Peer_Inputs!$M14/Peer_Inputs!H26,"n.m.") -> 12.453593 | K9: =IF(Peer_Inputs!I26>0,Peer_Inputs!$M14/Peer_Inputs!I26,"n.m.") -> 11.92056 | L9: =IF(Peer_Inputs!J26>0,Peer_Inputs!$M14/Peer_Inputs!J26,"n.m.") -> 14.658297 | M9: =IF(Peer_Inputs!K26>0,Peer_Inputs!$M14/Peer_Inputs!K26,"n.m.") -> 14.249228 | N9: =IF(Peer_Inputs!L26>0,Peer_Inputs!$M14/Peer_Inputs!L26,"n.m.") -> 13.615929 | O9: =IF(Peer_Inputs!M26>0,Peer_Inputs!$G14/Peer_Inputs!M26,"n.m.") -> 18.457143 | P9: =IF(Peer_Inputs!N26>0,Peer_Inputs!$G14/Peer_Inputs!N26,"n.m.") -> 17.518644 | Q9: =IF(Peer_Inputs!O26>0,Peer_Inputs!$G14/Peer_Inputs!O26,"n.m.") -> 16.406349
B10: =Peer_Inputs!B15 -> PepsiCo | C10: =Peer_Inputs!D15 -> 1 | D10: =Peer_Inputs!O15 -> 135936.88 | E10: =Peer_Inputs!P15 -> 169511.88 | F10: =IF(Peer_Inputs!D27>0,Peer_Inputs!$M15/Peer_Inputs!D27,"n.m.") -> 2.2851118 | G10: =IF(Peer_Inputs!E27>0,Peer_Inputs!$M15/Peer_Inputs!E27,"n.m.") -> 2.228162 | H10: =IF(Peer_Inputs!F27>0,Peer_Inputs!$M15/Peer_Inputs!F27,"n.m.") -> 2.1565025 | I10: =IF(Peer_Inputs!G27>0,Peer_Inputs!$M15/Peer_Inputs!G27,"n.m.") -> 12.475116 | J10: =IF(Peer_Inputs!H27>0,Peer_Inputs!$M15/Peer_Inputs!H27,"n.m.") -> 12.054607 | K10: =IF(Peer_Inputs!I27>0,Peer_Inputs!$M15/Peer_Inputs!I27,"n.m.") -> 11.536129 | L10: =IF(Peer_Inputs!J27>0,Peer_Inputs!$M15/Peer_Inputs!J27,"n.m.") -> 15.548696 | M10: =IF(Peer_Inputs!K27>0,Peer_Inputs!$M15/Peer_Inputs!K27,"n.m.") -> 15.005035 | N10: =IF(Peer_Inputs!L27>0,Peer_Inputs!$M15/Peer_Inputs!L27,"n.m.") -> 14.3048 | O10: =IF(Peer_Inputs!M27>0,Peer_Inputs!$G15/Peer_Inputs!M27,"n.m.") -> 15.506173 | P10: =IF(Peer_Inputs!N27>0,Peer_Inputs!$G15/Peer_Inputs!N27,"n.m.") -> 14.863905 | Q10: =IF(Peer_Inputs!O27>0,Peer_Inputs!$G15/Peer_Inputs!O27,"n.m.") -> 14.03352
B11: =Peer_Inputs!B16 -> Mondelez | C11: =Peer_Inputs!D16 -> 1 | D11: =Peer_Inputs!O16 -> 58224.39 | E11: =Peer_Inputs!P16 -> 72918.39 | F11: =IF(Peer_Inputs!D28>0,Peer_Inputs!$M16/Peer_Inputs!D28,"n.m.") -> 2.3974483 | G11: =IF(Peer_Inputs!E28>0,Peer_Inputs!$M16/Peer_Inputs!E28,"n.m.") -> 2.3308525 | H11: =IF(Peer_Inputs!F28>0,Peer_Inputs!$M16/Peer_Inputs!F28,"n.m.") -> 2.2512624 | I11: =IF(Peer_Inputs!G28>0,Peer_Inputs!$M16/Peer_Inputs!G28,"n.m.") -> 12.909337 | J11: =IF(Peer_Inputs!H28>0,Peer_Inputs!$M16/Peer_Inputs!H28,"n.m.") -> 12.644077 | K11: =IF(Peer_Inputs!I28>0,Peer_Inputs!$M16/Peer_Inputs!I28,"n.m.") -> 11.833559 | L11: =IF(Peer_Inputs!J28>0,Peer_Inputs!$M16/Peer_Inputs!J28,"n.m.") -> 15.512901 | M11: =IF(Peer_Inputs!K28>0,Peer_Inputs!$M16/Peer_Inputs!K28,"n.m.") -> 15.256489 | N11: =IF(Peer_Inputs!L28>0,Peer_Inputs!$M16/Peer_Inputs!L28,"n.m.") -> 14.200271 | O11: =IF(Peer_Inputs!M28>0,Peer_Inputs!$G16/Peer_Inputs!M28,"n.m.") -> 19.579661 | P11: =IF(Peer_Inputs!N28>0,Peer_Inputs!$G16/Peer_Inputs!N28,"n.m.") -> 18.937705 | Q11: =IF(Peer_Inputs!O28>0,Peer_Inputs!$G16/Peer_Inputs!O28,"n.m.") -> 17.241791
B12: =Peer_Inputs!B17 -> Coca-Cola | C12: =Peer_Inputs!D17 -> 2 | D12: =Peer_Inputs!O17 -> 292481.7 | E12: =Peer_Inputs!P17 -> 303146.7 | F12: =IF(Peer_Inputs!D29>0,Peer_Inputs!$M17/Peer_Inputs!D29,"n.m.") -> 8.0110647 | G12: =IF(Peer_Inputs!E29>0,Peer_Inputs!$M17/Peer_Inputs!E29,"n.m.") -> 7.6440239 | H12: =IF(Peer_Inputs!F29>0,Peer_Inputs!$M17/Peer_Inputs!F29,"n.m.") -> 7.2676136 | I12: =IF(Peer_Inputs!G29>0,Peer_Inputs!$M17/Peer_Inputs!G29,"n.m.") -> 23.983125 | J12: =IF(Peer_Inputs!H29>0,Peer_Inputs!$M17/Peer_Inputs!H29,"n.m.") -> 22.705917 | K12: =IF(Peer_Inputs!I29>0,Peer_Inputs!$M17/Peer_Inputs!I29,"n.m.") -> 21.43743 | L12: =IF(Peer_Inputs!J29>0,Peer_Inputs!$M17/Peer_Inputs!J29,"n.m.") -> 25.753691 | M12: =IF(Peer_Inputs!K29>0,Peer_Inputs!$M17/Peer_Inputs!K29,"n.m.") -> 24.286709 | N12: =IF(Peer_Inputs!L29>0,Peer_Inputs!$M17/Peer_Inputs!L29,"n.m.") -> 22.909254 | O12: =IF(Peer_Inputs!M29>0,Peer_Inputs!$G17/Peer_Inputs!M29,"n.m.") -> 28.7 | P12: =IF(Peer_Inputs!N29>0,Peer_Inputs!$G17/Peer_Inputs!N29,"n.m.") -> 26.73913 | Q12: =IF(Peer_Inputs!O29>0,Peer_Inputs!$G17/Peer_Inputs!O29,"n.m.") -> 24.956522
B13: =Peer_Inputs!B18 -> Hershey | C13: =Peer_Inputs!D18 -> 2 | D13: =Peer_Inputs!O18 -> 25295.247 | E13: =Peer_Inputs!P18 -> 29166.247 | F13: =IF(Peer_Inputs!D30>0,Peer_Inputs!$M18/Peer_Inputs!D30,"n.m.") -> 3.1690386 | G13: =IF(Peer_Inputs!E30>0,Peer_Inputs!$M18/Peer_Inputs!E30,"n.m.") -> 3.0138204 | H13: =IF(Peer_Inputs!F30>0,Peer_Inputs!$M18/Peer_Inputs!F30,"n.m.") -> 2.9070315 | I13: =IF(Peer_Inputs!G30>0,Peer_Inputs!$M18/Peer_Inputs!G30,"n.m.") -> 13.573272 | J13: =IF(Peer_Inputs!H30>0,Peer_Inputs!$M18/Peer_Inputs!H30,"n.m.") -> 11.020687 | K13: =IF(Peer_Inputs!I30>0,Peer_Inputs!$M18/Peer_Inputs!I30,"n.m.") -> 10.312654 | L13: =IF(Peer_Inputs!J30>0,Peer_Inputs!$M18/Peer_Inputs!J30,"n.m.") -> 16.408578 | M13: =IF(Peer_Inputs!K30>0,Peer_Inputs!$M18/Peer_Inputs!K30,"n.m.") -> 12.908846 | N13: =IF(Peer_Inputs!L30>0,Peer_Inputs!$M18/Peer_Inputs!L30,"n.m.") -> 12.025831 | O13: =IF(Peer_Inputs!M30>0,Peer_Inputs!$G18/Peer_Inputs!M30,"n.m.") -> 26.114754 | P13: =IF(Peer_Inputs!N30>0,Peer_Inputs!$G18/Peer_Inputs!N30,"n.m.") -> 19.666667 | Q13: =IF(Peer_Inputs!O30>0,Peer_Inputs!$G18/Peer_Inputs!O30,"n.m.") -> 17.898876
B14: =Peer_Inputs!B19 -> General Mills | C14: =Peer_Inputs!D19 -> 2 | D14: =Peer_Inputs!O19 -> 13385.326 | E14: =Peer_Inputs!P19 -> 24445.326 | F14: =IF(Peer_Inputs!D31>0,Peer_Inputs!$M19/Peer_Inputs!D31,"n.m.") -> 1.6541034 | G14: =IF(Peer_Inputs!E31>0,Peer_Inputs!$M19/Peer_Inputs!E31,"n.m.") -> 1.7214715 | H14: =IF(Peer_Inputs!F31>0,Peer_Inputs!$M19/Peer_Inputs!F31,"n.m.") -> 1.7166963 | I14: =IF(Peer_Inputs!G31>0,Peer_Inputs!$M19/Peer_Inputs!G31,"n.m.") -> 8.3424264 | J14: =IF(Peer_Inputs!H31>0,Peer_Inputs!$M19/Peer_Inputs!H31,"n.m.") -> 9.0433853 | K14: =IF(Peer_Inputs!I31>0,Peer_Inputs!$M19/Peer_Inputs!I31,"n.m.") -> 8.9691159 | L14: =IF(Peer_Inputs!J31>0,Peer_Inputs!$M19/Peer_Inputs!J31,"n.m.") -> 9.794814 | M14: =IF(Peer_Inputs!K31>0,Peer_Inputs!$M19/Peer_Inputs!K31,"n.m.") -> 10.775432 | N14: =IF(Peer_Inputs!L31>0,Peer_Inputs!$M19/Peer_Inputs!L31,"n.m.") -> 10.691661 | O14: =IF(Peer_Inputs!M31>0,Peer_Inputs!$G19/Peer_Inputs!M31,"n.m.") -> 8.4735786 | P14: =IF(Peer_Inputs!N31>0,Peer_Inputs!$G19/Peer_Inputs!N31,"n.m.") -> 9.8737334 | Q14: =IF(Peer_Inputs!O31>0,Peer_Inputs!$G19/Peer_Inputs!O31,"n.m.") -> 9.7421174
B15: =Peer_Inputs!B20 -> Kraft Heinz | C15: =Peer_Inputs!D20 -> 2 | D15: =Peer_Inputs!O20 -> 20773.169 | E15: =Peer_Inputs!P20 -> 36059.668 | F15: =IF(Peer_Inputs!D32>0,Peer_Inputs!$M20/Peer_Inputs!D32,"n.m.") -> 1.8300517 | G15: =IF(Peer_Inputs!E32>0,Peer_Inputs!$M20/Peer_Inputs!E32,"n.m.") -> 1.8900683 | H15: =IF(Peer_Inputs!F32>0,Peer_Inputs!$M20/Peer_Inputs!F32,"n.m.") -> 1.8979272 | I15: =IF(Peer_Inputs!G32>0,Peer_Inputs!$M20/Peer_Inputs!G32,"n.m.") -> 7.7364661 | J15: =IF(Peer_Inputs!H32>0,Peer_Inputs!$M20/Peer_Inputs!H32,"n.m.") -> 8.5318037 | K15: =IF(Peer_Inputs!I32>0,Peer_Inputs!$M20/Peer_Inputs!I32,"n.m.") -> 8.6122925 | L15: =IF(Peer_Inputs!J32>0,Peer_Inputs!$M20/Peer_Inputs!J32,"n.m.") -> 9.2212424 | M15: =IF(Peer_Inputs!K32>0,Peer_Inputs!$M20/Peer_Inputs!K32,"n.m.") -> 10.373898 | N15: =IF(Peer_Inputs!L32>0,Peer_Inputs!$M20/Peer_Inputs!L32,"n.m.") -> 10.493138 | O15: =IF(Peer_Inputs!M32>0,Peer_Inputs!$G20/Peer_Inputs!M32,"n.m.") -> 8.6007752 | P15: =IF(Peer_Inputs!N32>0,Peer_Inputs!$G20/Peer_Inputs!N32,"n.m.") -> 10.566667 | Q15: =IF(Peer_Inputs!O32>0,Peer_Inputs!$G20/Peer_Inputs!O32,"n.m.") -> 10.32093
B17: Nestlé (at market) | C17: – | D17: =Nestle_Inputs!D43 -> 192022.99 | E17: =Nestle_Inputs!D54 -> 212409.47 | F17: =$E17/Nestle_Inputs!F9 -> 2.3735554 | G17: =$E17/Nestle_Inputs!G9 -> 2.3617466 | H17: =$E17/Nestle_Inputs!H9 -> 2.326844 | I17: =$E17/Nestle_Inputs!F22 -> 11.786121 | J17: =$E17/Nestle_Inputs!G22 -> 11.715013 | K17: =$E17/Nestle_Inputs!H22 -> 11.687042 | L17: =$E17/Nestle_Inputs!F20 -> 14.761934 | M17: =$E17/Nestle_Inputs!G20 -> 14.463546 | N17: =$E17/Nestle_Inputs!H20 -> 14.462111 | O17: =(Nestle_Inputs!$D$43-Nestle_Inputs!$D$51)/Nestle_Inputs!F28 -> 16.298726 | P17: =(Nestle_Inputs!$D$43-Nestle_Inputs!$D$51)/Nestle_Inputs!G28 -> 15.755824 | Q17: =(Nestle_Inputs!$D$43-Nestle_Inputs!$D$51)/Nestle_Inputs!H28 -> 15.740666 | S17: Nestlé EV/EBITDA uses ADJUSTED EBITDA (underlying) and an EV that excludes the L'Oréal stake (valued at market). Nestlé P/E is shown EX-L'Oréal: (market cap – L'Oréal stake) / adjusted net profit excl. associates – the like-for-like figure for the P/E method in Valuation.
B19: All peers – Maximum | F19: =IFERROR(MAX(F66:F73),"n.a.") -> 8.0110647 | G19: =IFERROR(MAX(G66:G73),"n.a.") -> 7.6440239 | H19: =IFERROR(MAX(H66:H73),"n.a.") -> 7.2676136 | I19: =IFERROR(MAX(I66:I73),"n.a.") -> 23.983125 | J19: =IFERROR(MAX(J66:J73),"n.a.") -> 22.705917 | K19: =IFERROR(MAX(K66:K73),"n.a.") -> 21.43743 | L19: =IFERROR(MAX(L66:L73),"n.a.") -> 25.753691 | M19: =IFERROR(MAX(M66:M73),"n.a.") -> 24.286709 | ... Q19: =IFERROR(MAX(Q66:Q73),"n.a.") -> 24.956522 | S19: Statistics use Excel QUARTILE (inclusive). The interquartile range (25th–75th) is the default valuation range because it strips out the tails (e.g. Coca-Cola at ~23x EV/EBITDA) without discretionary exclusions. Mean shown for completeness but is distorted by outliers – rely on the median.
B20: All peers – 75th percentile | F20: =IFERROR(QUARTILE(F66:F73,3),"n.a.") -> 3.0101052 | G20: =IFERROR(QUARTILE(G66:G73,3),"n.a.") -> 2.9251829 | H20: =IFERROR(QUARTILE(H66:H73,3),"n.a.") -> 2.8270211 | I20: =IFERROR(QUARTILE(I66:I73,3),"n.a.") -> 13.075321 | J20: =IFERROR(QUARTILE(J66:J73,3),"n.a.") -> 12.501214 | K20: =IFERROR(QUARTILE(K66:K73,3),"n.a.") -> 11.855309 | L20: =IFERROR(QUARTILE(L66:L73,3),"n.a.") -> 15.763666 | M20: =IFERROR(QUARTILE(M66:M73,3),"n.a.") -> 15.067899 | ... Q20: =IFERROR(QUARTILE(Q66:Q73,3),"n.a.") -> 17.406062
B21: All peers – Mean | F21: =IFERROR(AVERAGE(F66:F73),"n.a.") -> 3.0007426 | G21: =IFERROR(AVERAGE(G66:G73),"n.a.") -> 2.9218638 | H21: =IFERROR(AVERAGE(H66:H73),"n.a.") -> 2.8236499 | I21: =IFERROR(AVERAGE(I66:I73),"n.a.") -> 12.682638 | J21: =IFERROR(AVERAGE(J66:J73),"n.a.") -> 12.208626 | K21: =IFERROR(AVERAGE(K66:K73),"n.a.") -> 11.675456 | L21: =IFERROR(AVERAGE(L66:L73),"n.a.") -> 14.938517 | M21: =IFERROR(AVERAGE(M66:M73),"n.a.") -> 14.352465 | ... Q21: =IFERROR(AVERAGE(Q66:Q73),"n.a.") -> 15.490233
B22: All peers – Median | F22: =IFERROR(MEDIAN(F66:F73),"n.a.") -> 2.3412801 | G22: =IFERROR(MEDIAN(G66:G73),"n.a.") -> 2.2795073 | H22: =IFERROR(MEDIAN(H66:H73),"n.a.") -> 2.2038825 | I22: =IFERROR(MEDIAN(I66:I73),"n.a.") -> 12.64673 | J22: =IFERROR(MEDIAN(J66:J73),"n.a.") -> 11.537647 | K22: =IFERROR(MEDIAN(K66:K73),"n.a.") -> 10.924391 | L22: =IFERROR(MEDIAN(L66:L73),"n.a.") -> 15.085599 | M22: =IFERROR(MEDIAN(M66:M73),"n.a.") -> 13.579037 | ... Q22: =IFERROR(MEDIAN(Q66:Q73),"n.a.") -> 15.219934
B23: All peers – 25th percentile | F23: =IFERROR(QUARTILE(F66:F73,1),"n.a.") -> 1.7980374 | G23: =IFERROR(QUARTILE(G66:G73,1),"n.a.") -> 1.8479191 | H23: =IFERROR(QUARTILE(H66:H73,1),"n.a.") -> 1.8526195 | I23: =IFERROR(QUARTILE(I66:I73,1),"n.a.") -> 9.3028697 | J23: =IFERROR(QUARTILE(J66:J73,1),"n.a.") -> 9.1720519 | K23: =IFERROR(QUARTILE(K66:K73,1),"n.a.") -> 8.9223139 | L23: =IFERROR(QUARTILE(L66:L73,1),"n.a.") -> 11.906143 | M23: =IFERROR(QUARTILE(M66:M73,1),"n.a.") -> 11.666921 | ... Q23: =IFERROR(QUARTILE(Q66:Q73,1),"n.a.") -> 12.571552
B24: All peers – Minimum | F24: =IFERROR(MIN(F66:F73),"n.a.") -> 1.6541034 | G24: =IFERROR(MIN(G66:G73),"n.a.") -> 1.6508746 | H24: =IFERROR(MIN(H66:H73),"n.a.") -> 1.5918143 | I24: =IFERROR(MIN(I66:I73),"n.a.") -> 7.7364661 | J24: =IFERROR(MIN(J66:J73),"n.a.") -> 8.5318037 | K24: =IFERROR(MIN(K66:K73),"n.a.") -> 8.6122925 | L24: =IFERROR(MIN(L66:L73),"n.a.") -> 9.2212424 | M24: =IFERROR(MIN(M66:M73),"n.a.") -> 10.373898 | ... Q24: =IFERROR(MIN(Q66:Q73),"n.a.") -> 9.7421174
B26: Tier 1 – 75th percentile | F26: =IFERROR(QUARTILE(F77:F84,3),"n.a.") -> 2.5373681 | G26: =IFERROR(QUARTILE(G77:G84,3),"n.a.") -> 2.4720487 | H26: =IFERROR(QUARTILE(H77:H84,3),"n.a.") -> 2.3885346 | I26: =IFERROR(QUARTILE(I77:I84,3),"n.a.") -> 12.841092 | J26: =IFERROR(QUARTILE(J77:J84,3),"n.a.") -> 12.501214 | K26: =IFERROR(QUARTILE(K77:K84,3),"n.a.") -> 11.855309 | L26: =IFERROR(QUARTILE(L77:L84,3),"n.a.") -> 15.52185 | M26: =IFERROR(QUARTILE(M77:M84,3),"n.a.") -> 15.067899 | ... Q26: =IFERROR(QUARTILE(Q77:Q84,3),"n.a.") -> 16.61521 | S26: Tier 1 statistics = the closest comparables (global scale, diversified portfolio, EM exposure). Valuation sheet lets you pick All-peer IQR, Tier 1 IQR or a manual range.
B27: Tier 1 – Median | F27: =IFERROR(QUARTILE(F77:F84,2),"n.a.") -> 2.3412801 | G27: =IFERROR(QUARTILE(G77:G84,2),"n.a.") -> 2.2795073 | H27: =IFERROR(QUARTILE(H77:H84,2),"n.a.") -> 2.2038825 | I27: =IFERROR(QUARTILE(I77:I84,2),"n.a.") -> 12.64673 | J27: =IFERROR(QUARTILE(J77:J84,2),"n.a.") -> 12.2541 | K27: =IFERROR(QUARTILE(K77:K84,2),"n.a.") -> 11.684844 | L27: =IFERROR(QUARTILE(L77:L84,2),"n.a.") -> 15.085599 | M27: =IFERROR(QUARTILE(M77:M84,2),"n.a.") -> 14.627131 | ... Q27: =IFERROR(QUARTILE(Q77:Q84,2),"n.a.") -> 15.219934
B28: Tier 1 – 25th percentile | F28: =IFERROR(QUARTILE(F77:F84,1),"n.a.") -> 2.1393325 | G28: =IFERROR(QUARTILE(G77:G84,1),"n.a.") -> 2.0838401 | H28: =IFERROR(QUARTILE(H77:H84,1),"n.a.") -> 2.0153305 | I28: =IFERROR(QUARTILE(I77:I84,1),"n.a.") -> 11.762092 | J28: =IFERROR(QUARTILE(J77:J84,1),"n.a.") -> 11.34469 | K28: =IFERROR(QUARTILE(K77:K84,1),"n.a.") -> 10.847574 | L28: =IFERROR(QUARTILE(L77:L84,1),"n.a.") -> 14.146202 | M28: =IFERROR(QUARTILE(M77:M84,1),"n.a.") -> 13.677942 | ... Q28: =IFERROR(QUARTILE(Q77:Q84,1),"n.a.") -> 13.855579
B29: Tier 2 – Median | F29: =IFERROR(MEDIAN(F88:F95),"n.a.") -> 2.4995452 | G29: =IFERROR(MEDIAN(G88:G95),"n.a.") -> 2.4519444 | H29: =IFERROR(MEDIAN(H88:H95),"n.a.") -> 2.4024794 | I29: =IFERROR(MEDIAN(I88:I95),"n.a.") -> 10.957849 | J29: =IFERROR(MEDIAN(J88:J95),"n.a.") -> 10.032036 | K29: =IFERROR(MEDIAN(K88:K95),"n.a.") -> 9.6408848 | L29: =IFERROR(MEDIAN(L88:L95),"n.a.") -> 13.101696 | M29: =IFERROR(MEDIAN(M88:M95),"n.a.") -> 11.842139 | ... Q29: =IFERROR(MEDIAN(Q88:Q95),"n.a.") -> 14.109903
B30: Nestlé premium / (discount) vs all-peer median | F30: =IFERROR(F17/F22-1,"n.a.") -> 0.013785324 | G30: =IFERROR(G17/G22-1,"n.a.") -> 0.036077699 | H30: =IFERROR(H17/H22-1,"n.a.") -> 0.055793131 | I30: =IFERROR(I17/I22-1,"n.a.") -> -0.068049911 | J30: =IFERROR(J17/J22-1,"n.a.") -> 0.015372838 | K30: =IFERROR(K17/K22-1,"n.a.") -> 0.069811715 | L30: =IFERROR(L17/L22-1,"n.a.") -> -0.021455206 | M30: =IFERROR(M17/M22-1,"n.a.") -> 0.065137843 | ... Q30: =IFERROR(Q17/Q22-1,"n.a.") -> 0.034213807 | S30: At 1-Oct-2026 prices Nestlé trades broadly in line with the all-peer median and slightly BELOW the Tier 1 median on EV/EBITDA and P/E. Its historical premium (scale, pricing power, #1 positions in coffee, pet care and infant nutrition, lower earnings volatility) has largely been priced out after the 2025-26 restructuring, CEO change and soft volumes. The key judgment: whether the 'Fuel for Growth' margin recovery justifies re-establishing part of that premium (DCF view) or not (pure comps view).
B31: Nestlé premium / (discount) vs Tier 1 median | F31: =IFERROR(F17/F27-1,"n.a.") -> 0.013785324 | G31: =IFERROR(G17/G27-1,"n.a.") -> 0.036077699 | H31: =IFERROR(H17/H27-1,"n.a.") -> 0.055793131 | I31: =IFERROR(I17/I27-1,"n.a.") -> -0.068049911 | J31: =IFERROR(J17/J27-1,"n.a.") -> -0.043992385 | K31: =IFERROR(K17/K27-1,"n.a.") -> 0.00018809157 | L31: =IFERROR(L17/L27-1,"n.a.") -> -0.021455206 | M31: =IFERROR(M17/M27-1,"n.a.") -> -0.011183685 | ... Q31: =IFERROR(Q17/Q27-1,"n.a.") -> 0.034213807
E35: Sales Growth | G35: EBITDA Margin | J35: EBIT Margin | K35: EPS Growth
B36: Operating benchmarking | C36: Tier | D36: Sales 2026F (CHF mm) | E36: 2026F | F36: 2027F | G36: 2025A | H36: 2026F | I36: 2027F | J36: 2026F | K36: 2026F | L36: 2027F | M36: Net debt / EBITDA 2025A
B37: =Peer_Inputs!B13 -> Danone | C37: =Peer_Inputs!D13 -> 1 | D37: =Peer_Inputs!E25*Peer_Inputs!N13 -> 26319 | E37: =Peer_Inputs!E25/Peer_Inputs!D25-1 -> 0.030965392 | F37: =Peer_Inputs!F25/Peer_Inputs!E25-1 -> 0.037102473 | G37: =Peer_Inputs!G25/Peer_Inputs!D25 -> 0.17686703 | H37: =Peer_Inputs!H25/Peer_Inputs!E25 -> 0.17915194 | I37: =Peer_Inputs!I25/Peer_Inputs!F25 -> 0.18126065 | J37: =Peer_Inputs!K25/Peer_Inputs!E25 -> 0.13798587 | K37: =Peer_Inputs!N25/Peer_Inputs!M25-1 -> 0.057894737 | L37: =Peer_Inputs!O25/Peer_Inputs!N25-1 -> 0.074626866 | M37: =Peer_Inputs!J13/Peer_Inputs!G25 -> 2.0185376 | S37: Benchmarking explains WHERE in the range Nestlé should sit: Nestlé is the largest by sales (~CHF 90bn), has an adjusted EBITDA margin around/above the peer median and moderate leverage, but its 2026E top-line growth (Base Case, CHF-reported, FX & divestment drag) is below most peers. Net: supports a multiple at or modestly above the Tier 1 median, not the top of the range.
B38: =Peer_Inputs!B14 -> Unilever | C38: =Peer_Inputs!D14 -> 1 | D38: =Peer_Inputs!E26*Peer_Inputs!N14 -> 49197 | E38: =Peer_Inputs!E26/Peer_Inputs!D26-1 -> 0.021235521 | F38: =Peer_Inputs!F26/Peer_Inputs!E26-1 -> 0.034026465 | G38: =Peer_Inputs!G26/Peer_Inputs!D26 -> 0.23069498 | H38: =Peer_Inputs!H26/Peer_Inputs!E26 -> 0.23251418 | I38: =Peer_Inputs!I26/Peer_Inputs!F26 -> 0.23491773 | J38: =Peer_Inputs!K26/Peer_Inputs!E26 -> 0.20321361 | K38: =Peer_Inputs!N26/Peer_Inputs!M26-1 -> 0.053571429 | L38: =Peer_Inputs!O26/Peer_Inputs!N26-1 -> 0.06779661 | M38: =Peer_Inputs!J14/Peer_Inputs!G26 -> 1.8828452
B39: =Peer_Inputs!B15 -> PepsiCo | C39: =Peer_Inputs!D15 -> 1 | D39: =Peer_Inputs!E27*Peer_Inputs!N15 -> 76077 | E39: =Peer_Inputs!E27/Peer_Inputs!D27-1 -> 0.025559105 | F39: =Peer_Inputs!F27/Peer_Inputs!E27-1 -> 0.033229491 | G39: =Peer_Inputs!G27/Peer_Inputs!D27 -> 0.18317359 | H39: =Peer_Inputs!H27/Peer_Inputs!E27 -> 0.18483904 | I39: =Peer_Inputs!I27/Peer_Inputs!F27 -> 0.18693467 | J39: =Peer_Inputs!K27/Peer_Inputs!E27 -> 0.14849429 | K39: =Peer_Inputs!N27/Peer_Inputs!M27-1 -> 0.043209877 | L39: =Peer_Inputs!O27/Peer_Inputs!N27-1 -> 0.059171598 | M39: =Peer_Inputs!J15/Peer_Inputs!G27 -> 2.5290698
B40: =Peer_Inputs!B16 -> Mondelez | C40: =Peer_Inputs!D16 -> 1 | D40: =Peer_Inputs!E28*Peer_Inputs!N16 -> 31284 | E40: =Peer_Inputs!E28/Peer_Inputs!D28-1 -> 0.028571429 | F40: =Peer_Inputs!F28/Peer_Inputs!E28-1 -> 0.035353535 | G40: =Peer_Inputs!G28/Peer_Inputs!D28 -> 0.18571429 | H40: =Peer_Inputs!H28/Peer_Inputs!E28 -> 0.18434343 | I40: =Peer_Inputs!I28/Peer_Inputs!F28 -> 0.1902439 | J40: =Peer_Inputs!K28/Peer_Inputs!E28 -> 0.15277778 | K40: =Peer_Inputs!N28/Peer_Inputs!M28-1 -> 0.033898305 | L40: =Peer_Inputs!O28/Peer_Inputs!N28-1 -> 0.098360656 | M40: =Peer_Inputs!J16/Peer_Inputs!G28 -> 2.7272727
B41: =Peer_Inputs!B17 -> Coca-Cola | C41: =Peer_Inputs!D17 -> 2 | D41: =Peer_Inputs!E29*Peer_Inputs!N17 -> 39658 | E41: =Peer_Inputs!E29/Peer_Inputs!D29-1 -> 0.048016701 | F41: =Peer_Inputs!F29/Peer_Inputs!E29-1 -> 0.051792829 | G41: =Peer_Inputs!G29/Peer_Inputs!D29 -> 0.33402923 | H41: =Peer_Inputs!H29/Peer_Inputs!E29 -> 0.33665339 | I41: =Peer_Inputs!I29/Peer_Inputs!F29 -> 0.33901515 | J41: =Peer_Inputs!K29/Peer_Inputs!E29 -> 0.31474104 | K41: =Peer_Inputs!N29/Peer_Inputs!M29-1 -> 0.073333333 | L41: =Peer_Inputs!O29/Peer_Inputs!N29-1 -> 0.071428571 | M41: =Peer_Inputs!J17/Peer_Inputs!G29 -> 1.9375
B42: =Peer_Inputs!B18 -> Hershey | C42: =Peer_Inputs!D18 -> 2 | D42: =Peer_Inputs!E30*Peer_Inputs!N18 -> 9677.5 | E42: =Peer_Inputs!E30/Peer_Inputs!D30-1 -> 0.051502146 | F42: =Peer_Inputs!F30/Peer_Inputs!E30-1 -> 0.036734694 | G42: =Peer_Inputs!G30/Peer_Inputs!D30 -> 0.23347639 | H42: =Peer_Inputs!H30/Peer_Inputs!E30 -> 0.27346939 | I42: =Peer_Inputs!I30/Peer_Inputs!F30 -> 0.28188976 | J42: =Peer_Inputs!K30/Peer_Inputs!E30 -> 0.23346939 | K42: =Peer_Inputs!N30/Peer_Inputs!M30-1 -> 0.32786885 | L42: =Peer_Inputs!O30/Peer_Inputs!N30-1 -> 0.098765432 | M42: =Peer_Inputs!J18/Peer_Inputs!G30 -> 1.8014706
B43: =Peer_Inputs!B19 -> General Mills | C43: =Peer_Inputs!D19 -> 2 | D43: =Peer_Inputs!E31*Peer_Inputs!N19 -> 14200.25 | E43: =Peer_Inputs!E31/Peer_Inputs!D31-1 -> -0.039134018 | F43: =Peer_Inputs!F31/Peer_Inputs!E31-1 -> 0.0027816412 | G43: =Peer_Inputs!G31/Peer_Inputs!D31 -> 0.19827605 | H43: =Peer_Inputs!H31/Peer_Inputs!E31 -> 0.19035698 | I43: =Peer_Inputs!I31/Peer_Inputs!F31 -> 0.19140083 | J43: =Peer_Inputs!K31/Peer_Inputs!E31 -> 0.15975892 | K43: =Peer_Inputs!N31/Peer_Inputs!M31-1 -> -0.14180602 | L43: =Peer_Inputs!O31/Peer_Inputs!N31-1 -> 0.013510003 | M43: =Peer_Inputs!J19/Peer_Inputs!G31 -> 3.8283532
B44: =Peer_Inputs!B20 -> Kraft Heinz | C44: =Peer_Inputs!D20 -> 2 | D44: =Peer_Inputs!E32*Peer_Inputs!N20 -> 19078.5 | E44: =Peer_Inputs!E32/Peer_Inputs!D32-1 -> -0.031753669 | F44: =Peer_Inputs!F32/Peer_Inputs!E32-1 -> -0.0041407867 | G44: =Peer_Inputs!G32/Peer_Inputs!D32 -> 0.23654879 | H44: =Peer_Inputs!H32/Peer_Inputs!E32 -> 0.22153209 | I44: =Peer_Inputs!I32/Peer_Inputs!F32 -> 0.22037422 | J44: =Peer_Inputs!K32/Peer_Inputs!E32 -> 0.18219462 | K44: =Peer_Inputs!N32/Peer_Inputs!M32-1 -> -0.18604651 | L44: =Peer_Inputs!O32/Peer_Inputs!N32-1 -> 0.023809524 | M44: =Peer_Inputs!J20/Peer_Inputs!G32 -> 3.2542373
B45: Nestlé (Base Case) | C45: – | D45: =Nestle_Inputs!G9 -> 89937.45 | E45: =Nestle_Inputs!G10 -> 0.005 | F45: =Nestle_Inputs!H10 -> 0.014999999 | G45: =Nestle_Inputs!F23 -> 0.20138563 | H45: =Nestle_Inputs!G23 -> 0.2016 | I45: =Nestle_Inputs!H23 -> 0.19909606 | J45: =Nestle_Inputs!G24 -> 0.1632896 | K45: =Nestle_Inputs!G34 -> 0.033978773 | L45: =Nestle_Inputs!H34 -> 0.0051369751 | M45: =Nestle_Inputs!D44/Nestle_Inputs!F22 -> 3.1264011 | S45: Nestlé growth is CHF-reported (strong-CHF translation drag ~3pts) while most peers report in USD/EUR – on an organic basis the gap is narrower. Nestlé's net debt/EBITDA uses adjusted 2025A EBITDA.
B46: Peer median | D46: =MEDIAN(D37:D44) -> 28801.5 | E46: =MEDIAN(E37:E44) -> 0.027065267 | F46: =MEDIAN(F37:F44) -> 0.03469 | G46: =MEDIAN(G37:G44) -> 0.21448552 | H46: =MEDIAN(H37:H44) -> 0.20594453 | I46: =MEDIAN(I37:I44) -> 0.20588753 | J46: =MEDIAN(J37:J44) -> 0.17097677 | K46: =MEDIAN(K37:K44) -> 0.048390653 | ... M46: =MEDIAN(M37:M44) -> 2.2738037
B47: Peer mean | D47: =AVERAGE(D37:D44) -> 33186.406 | E47: =AVERAGE(E37:E44) -> 0.016870326 | F47: =AVERAGE(F37:F44) -> 0.028360043 | G47: =AVERAGE(G37:G44) -> 0.22234754 | H47: =AVERAGE(H37:H44) -> 0.22535756 | I47: =AVERAGE(I37:I44) -> 0.22825462 | J47: =AVERAGE(J37:J44) -> 0.19157944 | K47: =AVERAGE(K37:K44) -> 0.0327405 | ... M47: =AVERAGE(M37:M44) -> 2.4974108
B50: Regression cross-check: EV/EBITDA 2026F (y) vs Adj. EBITDA margin 2026F (x) – included peers
B51: Slope | F51: =SLOPE(J66:J73,D66:D73) -> 63.607464 | S51: A simple 'value vs quality' regression: do higher-margin peers command higher multiples? Read the R-squared before relying on it – with 8 peers one point (Coca-Cola: highest margin AND highest multiple) drives most of the fit. Toggle KO off in Peer_Inputs to see how fragile it is. Used as a sanity check only, not in the blended value.
B52: Intercept | F52: =INTERCEPT(J66:J73,D66:D73) -> -2.1257963
B53: R-squared | F53: =RSQ(J66:J73,D66:D73) -> 0.60113132
B54: Nestlé adj. EBITDA margin 2026F | F54: =H45 -> 0.2016
B55: Regression-implied Nestlé EV/EBITDA 2026F | F55: =F52+F51*F54 -> 10.697469
B56: Nestlé actual EV/EBITDA 2026F (at market) | F56: =J17 -> 11.715013
B61: Helper (feeds statistics above)
F64: EV / Sales | I64: EV / EBITDA | L64: EV / EBIT | O64: P / E
B65: All included peers | D65: EBITDA margin 26E | F65: 2025A | G65: 2026F | H65: 2027F | I65: 2025A | J65: 2026F | K65: 2027F | L65: 2025A | M65: 2026F | N65: 2027F | O65: 2025A | P65: 2026F | Q65: 2027F
B66: =B8 -> Danone | D66: =IF(Peer_Inputs!$Q13=1,H37,"") -> 0.17915194 | F66: =IF(AND(Peer_Inputs!$Q13=1,ISNUMBER(F8)),F8,"") -> 1.7019945 | G66: =IF(AND(Peer_Inputs!$Q13=1,ISNUMBER(G8)),G8,"") -> 1.6508746 | H66: =IF(AND(Peer_Inputs!$Q13=1,ISNUMBER(H8)),H8,"") -> 1.5918143 | I66: =IF(AND(Peer_Inputs!$Q13=1,ISNUMBER(I8)),I8,"") -> 9.6230175 | J66: =IF(AND(Peer_Inputs!$Q13=1,ISNUMBER(J8)),J8,"") -> 9.2149408 | K66: =IF(AND(Peer_Inputs!$Q13=1,ISNUMBER(K8)),K8,"") -> 8.7819079 | L66: =IF(AND(Peer_Inputs!$Q13=1,ISNUMBER(L8)),L8,"") -> 12.609919 | M66: =IF(AND(Peer_Inputs!$Q13=1,ISNUMBER(M8)),M8,"") -> 11.964085 | ... Q66: =IF(AND(Peer_Inputs!$Q13=1,ISNUMBER(Q8)),Q8,"") -> 13.321759
B67: =B9 -> Unilever | D67: =IF(Peer_Inputs!$Q14=1,H38,"") -> 0.23251418 | F67: =IF(AND(Peer_Inputs!$Q14=1,ISNUMBER(F9)),F9,"") -> 2.9571274 | G67: =IF(AND(Peer_Inputs!$Q14=1,ISNUMBER(G9)),G9,"") -> 2.8956371 | H67: =IF(AND(Peer_Inputs!$Q14=1,ISNUMBER(H9)),H9,"") -> 2.800351 | I67: =IF(AND(Peer_Inputs!$Q14=1,ISNUMBER(I9)),I9,"") -> 12.818343 | J67: =IF(AND(Peer_Inputs!$Q14=1,ISNUMBER(J9)),J9,"") -> 12.453593 | K67: =IF(AND(Peer_Inputs!$Q14=1,ISNUMBER(K9)),K9,"") -> 11.92056 | L67: =IF(AND(Peer_Inputs!$Q14=1,ISNUMBER(L9)),L9,"") -> 14.658297 | M67: =IF(AND(Peer_Inputs!$Q14=1,ISNUMBER(M9)),M9,"") -> 14.249228 | ... Q67: =IF(AND(Peer_Inputs!$Q14=1,ISNUMBER(Q9)),Q9,"") -> 16.406349
B68: =B10 -> PepsiCo | D68: =IF(Peer_Inputs!$Q15=1,H39,"") -> 0.18483904 | F68: =IF(AND(Peer_Inputs!$Q15=1,ISNUMBER(F10)),F10,"") -> 2.2851118 | G68: =IF(AND(Peer_Inputs!$Q15=1,ISNUMBER(G10)),G10,"") -> 2.228162 | H68: =IF(AND(Peer_Inputs!$Q15=1,ISNUMBER(H10)),H10,"") -> 2.1565025 | I68: =IF(AND(Peer_Inputs!$Q15=1,ISNUMBER(I10)),I10,"") -> 12.475116 | J68: =IF(AND(Peer_Inputs!$Q15=1,ISNUMBER(J10)),J10,"") -> 12.054607 | K68: =IF(AND(Peer_Inputs!$Q15=1,ISNUMBER(K10)),K10,"") -> 11.536129 | L68: =IF(AND(Peer_Inputs!$Q15=1,ISNUMBER(L10)),L10,"") -> 15.548696 | M68: =IF(AND(Peer_Inputs!$Q15=1,ISNUMBER(M10)),M10,"") -> 15.005035 | ... Q68: =IF(AND(Peer_Inputs!$Q15=1,ISNUMBER(Q10)),Q10,"") -> 14.03352
B69: =B11 -> Mondelez | D69: =IF(Peer_Inputs!$Q16=1,H40,"") -> 0.18434343 | F69: =IF(AND(Peer_Inputs!$Q16=1,ISNUMBER(F11)),F11,"") -> 2.3974483 | G69: =IF(AND(Peer_Inputs!$Q16=1,ISNUMBER(G11)),G11,"") -> 2.3308525 | H69: =IF(AND(Peer_Inputs!$Q16=1,ISNUMBER(H11)),H11,"") -> 2.2512624 | I69: =IF(AND(Peer_Inputs!$Q16=1,ISNUMBER(I11)),I11,"") -> 12.909337 | J69: =IF(AND(Peer_Inputs!$Q16=1,ISNUMBER(J11)),J11,"") -> 12.644077 | K69: =IF(AND(Peer_Inputs!$Q16=1,ISNUMBER(K11)),K11,"") -> 11.833559 | L69: =IF(AND(Peer_Inputs!$Q16=1,ISNUMBER(L11)),L11,"") -> 15.512901 | M69: =IF(AND(Peer_Inputs!$Q16=1,ISNUMBER(M11)),M11,"") -> 15.256489 | ... Q69: =IF(AND(Peer_Inputs!$Q16=1,ISNUMBER(Q11)),Q11,"") -> 17.241791
B70: =B12 -> Coca-Cola | D70: =IF(Peer_Inputs!$Q17=1,H41,"") -> 0.33665339 | F70: =IF(AND(Peer_Inputs!$Q17=1,ISNUMBER(F12)),F12,"") -> 8.0110647 | G70: =IF(AND(Peer_Inputs!$Q17=1,ISNUMBER(G12)),G12,"") -> 7.6440239 | H70: =IF(AND(Peer_Inputs!$Q17=1,ISNUMBER(H12)),H12,"") -> 7.2676136 | I70: =IF(AND(Peer_Inputs!$Q17=1,ISNUMBER(I12)),I12,"") -> 23.983125 | J70: =IF(AND(Peer_Inputs!$Q17=1,ISNUMBER(J12)),J12,"") -> 22.705917 | K70: =IF(AND(Peer_Inputs!$Q17=1,ISNUMBER(K12)),K12,"") -> 21.43743 | L70: =IF(AND(Peer_Inputs!$Q17=1,ISNUMBER(L12)),L12,"") -> 25.753691 | M70: =IF(AND(Peer_Inputs!$Q17=1,ISNUMBER(M12)),M12,"") -> 24.286709 | ... Q70: =IF(AND(Peer_Inputs!$Q17=1,ISNUMBER(Q12)),Q12,"") -> 24.956522
B71: =B13 -> Hershey | D71: =IF(Peer_Inputs!$Q18=1,H42,"") -> 0.27346939 | F71: =IF(AND(Peer_Inputs!$Q18=1,ISNUMBER(F13)),F13,"") -> 3.1690386 | G71: =IF(AND(Peer_Inputs!$Q18=1,ISNUMBER(G13)),G13,"") -> 3.0138204 | H71: =IF(AND(Peer_Inputs!$Q18=1,ISNUMBER(H13)),H13,"") -> 2.9070315 | I71: =IF(AND(Peer_Inputs!$Q18=1,ISNUMBER(I13)),I13,"") -> 13.573272 | J71: =IF(AND(Peer_Inputs!$Q18=1,ISNUMBER(J13)),J13,"") -> 11.020687 | K71: =IF(AND(Peer_Inputs!$Q18=1,ISNUMBER(K13)),K13,"") -> 10.312654 | L71: =IF(AND(Peer_Inputs!$Q18=1,ISNUMBER(L13)),L13,"") -> 16.408578 | M71: =IF(AND(Peer_Inputs!$Q18=1,ISNUMBER(M13)),M13,"") -> 12.908846 | ... Q71: =IF(AND(Peer_Inputs!$Q18=1,ISNUMBER(Q13)),Q13,"") -> 17.898876
B72: =B14 -> General Mills | D72: =IF(Peer_Inputs!$Q19=1,H43,"") -> 0.19035698 | F72: =IF(AND(Peer_Inputs!$Q19=1,ISNUMBER(F14)),F14,"") -> 1.6541034 | G72: =IF(AND(Peer_Inputs!$Q19=1,ISNUMBER(G14)),G14,"") -> 1.7214715 | H72: =IF(AND(Peer_Inputs!$Q19=1,ISNUMBER(H14)),H14,"") -> 1.7166963 | I72: =IF(AND(Peer_Inputs!$Q19=1,ISNUMBER(I14)),I14,"") -> 8.3424264 | J72: =IF(AND(Peer_Inputs!$Q19=1,ISNUMBER(J14)),J14,"") -> 9.0433853 | K72: =IF(AND(Peer_Inputs!$Q19=1,ISNUMBER(K14)),K14,"") -> 8.9691159 | L72: =IF(AND(Peer_Inputs!$Q19=1,ISNUMBER(L14)),L14,"") -> 9.794814 | M72: =IF(AND(Peer_Inputs!$Q19=1,ISNUMBER(M14)),M14,"") -> 10.775432 | ... Q72: =IF(AND(Peer_Inputs!$Q19=1,ISNUMBER(Q14)),Q14,"") -> 9.7421174
B73: =B15 -> Kraft Heinz | D73: =IF(Peer_Inputs!$Q20=1,H44,"") -> 0.22153209 | F73: =IF(AND(Peer_Inputs!$Q20=1,ISNUMBER(F15)),F15,"") -> 1.8300517 | G73: =IF(AND(Peer_Inputs!$Q20=1,ISNUMBER(G15)),G15,"") -> 1.8900683 | H73: =IF(AND(Peer_Inputs!$Q20=1,ISNUMBER(H15)),H15,"") -> 1.8979272 | I73: =IF(AND(Peer_Inputs!$Q20=1,ISNUMBER(I15)),I15,"") -> 7.7364661 | J73: =IF(AND(Peer_Inputs!$Q20=1,ISNUMBER(J15)),J15,"") -> 8.5318037 | K73: =IF(AND(Peer_Inputs!$Q20=1,ISNUMBER(K15)),K15,"") -> 8.6122925 | L73: =IF(AND(Peer_Inputs!$Q20=1,ISNUMBER(L15)),L15,"") -> 9.2212424 | M73: =IF(AND(Peer_Inputs!$Q20=1,ISNUMBER(M15)),M15,"") -> 10.373898 | ... Q73: =IF(AND(Peer_Inputs!$Q20=1,ISNUMBER(Q15)),Q15,"") -> 10.32093
B76: Tier 1 included peers
B77: =B8 -> Danone | F77: =IF(AND(AND(Peer_Inputs!$Q13=1,Peer_Inputs!$D13=1),ISNUMBER(F8)),F8,"") -> 1.7019945 | G77: =IF(AND(AND(Peer_Inputs!$Q13=1,Peer_Inputs!$D13=1),ISNUMBER(G8)),G8,"") -> 1.6508746 | H77: =IF(AND(AND(Peer_Inputs!$Q13=1,Peer_Inputs!$D13=1),ISNUMBER(H8)),H8,"") -> 1.5918143 | I77: =IF(AND(AND(Peer_Inputs!$Q13=1,Peer_Inputs!$D13=1),ISNUMBER(I8)),I8,"") -> 9.6230175 | J77: =IF(AND(AND(Peer_Inputs!$Q13=1,Peer_Inputs!$D13=1),ISNUMBER(J8)),J8,"") -> 9.2149408 | K77: =IF(AND(AND(Peer_Inputs!$Q13=1,Peer_Inputs!$D13=1),ISNUMBER(K8)),K8,"") -> 8.7819079 | L77: =IF(AND(AND(Peer_Inputs!$Q13=1,Peer_Inputs!$D13=1),ISNUMBER(L8)),L8,"") -> 12.609919 | M77: =IF(AND(AND(Peer_Inputs!$Q13=1,Peer_Inputs!$D13=1),ISNUMBER(M8)),M8,"") -> 11.964085 | ... Q77: =IF(AND(AND(Peer_Inputs!$Q13=1,Peer_Inputs!$D13=1),ISNUMBER(Q8)),Q8,"") -> 13.321759
B78: =B9 -> Unilever | F78: =IF(AND(AND(Peer_Inputs!$Q14=1,Peer_Inputs!$D14=1),ISNUMBER(F9)),F9,"") -> 2.9571274 | G78: =IF(AND(AND(Peer_Inputs!$Q14=1,Peer_Inputs!$D14=1),ISNUMBER(G9)),G9,"") -> 2.8956371 | H78: =IF(AND(AND(Peer_Inputs!$Q14=1,Peer_Inputs!$D14=1),ISNUMBER(H9)),H9,"") -> 2.800351 | I78: =IF(AND(AND(Peer_Inputs!$Q14=1,Peer_Inputs!$D14=1),ISNUMBER(I9)),I9,"") -> 12.818343 | J78: =IF(AND(AND(Peer_Inputs!$Q14=1,Peer_Inputs!$D14=1),ISNUMBER(J9)),J9,"") -> 12.453593 | K78: =IF(AND(AND(Peer_Inputs!$Q14=1,Peer_Inputs!$D14=1),ISNUMBER(K9)),K9,"") -> 11.92056 | L78: =IF(AND(AND(Peer_Inputs!$Q14=1,Peer_Inputs!$D14=1),ISNUMBER(L9)),L9,"") -> 14.658297 | M78: =IF(AND(AND(Peer_Inputs!$Q14=1,Peer_Inputs!$D14=1),ISNUMBER(M9)),M9,"") -> 14.249228 | ... Q78: =IF(AND(AND(Peer_Inputs!$Q14=1,Peer_Inputs!$D14=1),ISNUMBER(Q9)),Q9,"") -> 16.406349
B79: =B10 -> PepsiCo | F79: =IF(AND(AND(Peer_Inputs!$Q15=1,Peer_Inputs!$D15=1),ISNUMBER(F10)),F10,"") -> 2.2851118 | G79: =IF(AND(AND(Peer_Inputs!$Q15=1,Peer_Inputs!$D15=1),ISNUMBER(G10)),G10,"") -> 2.228162 | H79: =IF(AND(AND(Peer_Inputs!$Q15=1,Peer_Inputs!$D15=1),ISNUMBER(H10)),H10,"") -> 2.1565025 | I79: =IF(AND(AND(Peer_Inputs!$Q15=1,Peer_Inputs!$D15=1),ISNUMBER(I10)),I10,"") -> 12.475116 | J79: =IF(AND(AND(Peer_Inputs!$Q15=1,Peer_Inputs!$D15=1),ISNUMBER(J10)),J10,"") -> 12.054607 | K79: =IF(AND(AND(Peer_Inputs!$Q15=1,Peer_Inputs!$D15=1),ISNUMBER(K10)),K10,"") -> 11.536129 | L79: =IF(AND(AND(Peer_Inputs!$Q15=1,Peer_Inputs!$D15=1),ISNUMBER(L10)),L10,"") -> 15.548696 | M79: =IF(AND(AND(Peer_Inputs!$Q15=1,Peer_Inputs!$D15=1),ISNUMBER(M10)),M10,"") -> 15.005035 | ... Q79: =IF(AND(AND(Peer_Inputs!$Q15=1,Peer_Inputs!$D15=1),ISNUMBER(Q10)),Q10,"") -> 14.03352
B80: =B11 -> Mondelez | F80: =IF(AND(AND(Peer_Inputs!$Q16=1,Peer_Inputs!$D16=1),ISNUMBER(F11)),F11,"") -> 2.3974483 | G80: =IF(AND(AND(Peer_Inputs!$Q16=1,Peer_Inputs!$D16=1),ISNUMBER(G11)),G11,"") -> 2.3308525 | H80: =IF(AND(AND(Peer_Inputs!$Q16=1,Peer_Inputs!$D16=1),ISNUMBER(H11)),H11,"") -> 2.2512624 | I80: =IF(AND(AND(Peer_Inputs!$Q16=1,Peer_Inputs!$D16=1),ISNUMBER(I11)),I11,"") -> 12.909337 | J80: =IF(AND(AND(Peer_Inputs!$Q16=1,Peer_Inputs!$D16=1),ISNUMBER(J11)),J11,"") -> 12.644077 | K80: =IF(AND(AND(Peer_Inputs!$Q16=1,Peer_Inputs!$D16=1),ISNUMBER(K11)),K11,"") -> 11.833559 | L80: =IF(AND(AND(Peer_Inputs!$Q16=1,Peer_Inputs!$D16=1),ISNUMBER(L11)),L11,"") -> 15.512901 | M80: =IF(AND(AND(Peer_Inputs!$Q16=1,Peer_Inputs!$D16=1),ISNUMBER(M11)),M11,"") -> 15.256489 | ... Q80: =IF(AND(AND(Peer_Inputs!$Q16=1,Peer_Inputs!$D16=1),ISNUMBER(Q11)),Q11,"") -> 17.241791
B81: =B12 -> Coca-Cola | F81: =IF(AND(AND(Peer_Inputs!$Q17=1,Peer_Inputs!$D17=1),ISNUMBER(F12)),F12,"") | G81: =IF(AND(AND(Peer_Inputs!$Q17=1,Peer_Inputs!$D17=1),ISNUMBER(G12)),G12,"") | H81: =IF(AND(AND(Peer_Inputs!$Q17=1,Peer_Inputs!$D17=1),ISNUMBER(H12)),H12,"") | I81: =IF(AND(AND(Peer_Inputs!$Q17=1,Peer_Inputs!$D17=1),ISNUMBER(I12)),I12,"") | J81: =IF(AND(AND(Peer_Inputs!$Q17=1,Peer_Inputs!$D17=1),ISNUMBER(J12)),J12,"") | K81: =IF(AND(AND(Peer_Inputs!$Q17=1,Peer_Inputs!$D17=1),ISNUMBER(K12)),K12,"") | L81: =IF(AND(AND(Peer_Inputs!$Q17=1,Peer_Inputs!$D17=1),ISNUMBER(L12)),L12,"") | M81: =IF(AND(AND(Peer_Inputs!$Q17=1,Peer_Inputs!$D17=1),ISNUMBER(M12)),M12,"") | ... Q81: =IF(AND(AND(Peer_Inputs!$Q17=1,Peer_Inputs!$D17=1),ISNUMBER(Q12)),Q12,"")
B82: =B13 -> Hershey | F82: =IF(AND(AND(Peer_Inputs!$Q18=1,Peer_Inputs!$D18=1),ISNUMBER(F13)),F13,"") | G82: =IF(AND(AND(Peer_Inputs!$Q18=1,Peer_Inputs!$D18=1),ISNUMBER(G13)),G13,"") | H82: =IF(AND(AND(Peer_Inputs!$Q18=1,Peer_Inputs!$D18=1),ISNUMBER(H13)),H13,"") | I82: =IF(AND(AND(Peer_Inputs!$Q18=1,Peer_Inputs!$D18=1),ISNUMBER(I13)),I13,"") | J82: =IF(AND(AND(Peer_Inputs!$Q18=1,Peer_Inputs!$D18=1),ISNUMBER(J13)),J13,"") | K82: =IF(AND(AND(Peer_Inputs!$Q18=1,Peer_Inputs!$D18=1),ISNUMBER(K13)),K13,"") | L82: =IF(AND(AND(Peer_Inputs!$Q18=1,Peer_Inputs!$D18=1),ISNUMBER(L13)),L13,"") | M82: =IF(AND(AND(Peer_Inputs!$Q18=1,Peer_Inputs!$D18=1),ISNUMBER(M13)),M13,"") | ... Q82: =IF(AND(AND(Peer_Inputs!$Q18=1,Peer_Inputs!$D18=1),ISNUMBER(Q13)),Q13,"")
B83: =B14 -> General Mills | F83: =IF(AND(AND(Peer_Inputs!$Q19=1,Peer_Inputs!$D19=1),ISNUMBER(F14)),F14,"") | G83: =IF(AND(AND(Peer_Inputs!$Q19=1,Peer_Inputs!$D19=1),ISNUMBER(G14)),G14,"") | H83: =IF(AND(AND(Peer_Inputs!$Q19=1,Peer_Inputs!$D19=1),ISNUMBER(H14)),H14,"") | I83: =IF(AND(AND(Peer_Inputs!$Q19=1,Peer_Inputs!$D19=1),ISNUMBER(I14)),I14,"") | J83: =IF(AND(AND(Peer_Inputs!$Q19=1,Peer_Inputs!$D19=1),ISNUMBER(J14)),J14,"") | K83: =IF(AND(AND(Peer_Inputs!$Q19=1,Peer_Inputs!$D19=1),ISNUMBER(K14)),K14,"") | L83: =IF(AND(AND(Peer_Inputs!$Q19=1,Peer_Inputs!$D19=1),ISNUMBER(L14)),L14,"") | M83: =IF(AND(AND(Peer_Inputs!$Q19=1,Peer_Inputs!$D19=1),ISNUMBER(M14)),M14,"") | ... Q83: =IF(AND(AND(Peer_Inputs!$Q19=1,Peer_Inputs!$D19=1),ISNUMBER(Q14)),Q14,"")
B84: =B15 -> Kraft Heinz | F84: =IF(AND(AND(Peer_Inputs!$Q20=1,Peer_Inputs!$D20=1),ISNUMBER(F15)),F15,"") | G84: =IF(AND(AND(Peer_Inputs!$Q20=1,Peer_Inputs!$D20=1),ISNUMBER(G15)),G15,"") | H84: =IF(AND(AND(Peer_Inputs!$Q20=1,Peer_Inputs!$D20=1),ISNUMBER(H15)),H15,"") | I84: =IF(AND(AND(Peer_Inputs!$Q20=1,Peer_Inputs!$D20=1),ISNUMBER(I15)),I15,"") | J84: =IF(AND(AND(Peer_Inputs!$Q20=1,Peer_Inputs!$D20=1),ISNUMBER(J15)),J15,"") | K84: =IF(AND(AND(Peer_Inputs!$Q20=1,Peer_Inputs!$D20=1),ISNUMBER(K15)),K15,"") | L84: =IF(AND(AND(Peer_Inputs!$Q20=1,Peer_Inputs!$D20=1),ISNUMBER(L15)),L15,"") | M84: =IF(AND(AND(Peer_Inputs!$Q20=1,Peer_Inputs!$D20=1),ISNUMBER(M15)),M15,"") | ... Q84: =IF(AND(AND(Peer_Inputs!$Q20=1,Peer_Inputs!$D20=1),ISNUMBER(Q15)),Q15,"")
B87: Tier 2 included peers
B88: =B8 -> Danone | F88: =IF(AND(AND(Peer_Inputs!$Q13=1,Peer_Inputs!$D13=2),ISNUMBER(F8)),F8,"") | G88: =IF(AND(AND(Peer_Inputs!$Q13=1,Peer_Inputs!$D13=2),ISNUMBER(G8)),G8,"") | H88: =IF(AND(AND(Peer_Inputs!$Q13=1,Peer_Inputs!$D13=2),ISNUMBER(H8)),H8,"") | I88: =IF(AND(AND(Peer_Inputs!$Q13=1,Peer_Inputs!$D13=2),ISNUMBER(I8)),I8,"") | J88: =IF(AND(AND(Peer_Inputs!$Q13=1,Peer_Inputs!$D13=2),ISNUMBER(J8)),J8,"") | K88: =IF(AND(AND(Peer_Inputs!$Q13=1,Peer_Inputs!$D13=2),ISNUMBER(K8)),K8,"") | L88: =IF(AND(AND(Peer_Inputs!$Q13=1,Peer_Inputs!$D13=2),ISNUMBER(L8)),L8,"") | M88: =IF(AND(AND(Peer_Inputs!$Q13=1,Peer_Inputs!$D13=2),ISNUMBER(M8)),M8,"") | ... Q88: =IF(AND(AND(Peer_Inputs!$Q13=1,Peer_Inputs!$D13=2),ISNUMBER(Q8)),Q8,"")
B89: =B9 -> Unilever | F89: =IF(AND(AND(Peer_Inputs!$Q14=1,Peer_Inputs!$D14=2),ISNUMBER(F9)),F9,"") | G89: =IF(AND(AND(Peer_Inputs!$Q14=1,Peer_Inputs!$D14=2),ISNUMBER(G9)),G9,"") | H89: =IF(AND(AND(Peer_Inputs!$Q14=1,Peer_Inputs!$D14=2),ISNUMBER(H9)),H9,"") | I89: =IF(AND(AND(Peer_Inputs!$Q14=1,Peer_Inputs!$D14=2),ISNUMBER(I9)),I9,"") | J89: =IF(AND(AND(Peer_Inputs!$Q14=1,Peer_Inputs!$D14=2),ISNUMBER(J9)),J9,"") | K89: =IF(AND(AND(Peer_Inputs!$Q14=1,Peer_Inputs!$D14=2),ISNUMBER(K9)),K9,"") | L89: =IF(AND(AND(Peer_Inputs!$Q14=1,Peer_Inputs!$D14=2),ISNUMBER(L9)),L9,"") | M89: =IF(AND(AND(Peer_Inputs!$Q14=1,Peer_Inputs!$D14=2),ISNUMBER(M9)),M9,"") | ... Q89: =IF(AND(AND(Peer_Inputs!$Q14=1,Peer_Inputs!$D14=2),ISNUMBER(Q9)),Q9,"")
B90: =B10 -> PepsiCo | F90: =IF(AND(AND(Peer_Inputs!$Q15=1,Peer_Inputs!$D15=2),ISNUMBER(F10)),F10,"") | G90: =IF(AND(AND(Peer_Inputs!$Q15=1,Peer_Inputs!$D15=2),ISNUMBER(G10)),G10,"") | H90: =IF(AND(AND(Peer_Inputs!$Q15=1,Peer_Inputs!$D15=2),ISNUMBER(H10)),H10,"") | I90: =IF(AND(AND(Peer_Inputs!$Q15=1,Peer_Inputs!$D15=2),ISNUMBER(I10)),I10,"") | J90: =IF(AND(AND(Peer_Inputs!$Q15=1,Peer_Inputs!$D15=2),ISNUMBER(J10)),J10,"") | K90: =IF(AND(AND(Peer_Inputs!$Q15=1,Peer_Inputs!$D15=2),ISNUMBER(K10)),K10,"") | L90: =IF(AND(AND(Peer_Inputs!$Q15=1,Peer_Inputs!$D15=2),ISNUMBER(L10)),L10,"") | M90: =IF(AND(AND(Peer_Inputs!$Q15=1,Peer_Inputs!$D15=2),ISNUMBER(M10)),M10,"") | ... Q90: =IF(AND(AND(Peer_Inputs!$Q15=1,Peer_Inputs!$D15=2),ISNUMBER(Q10)),Q10,"")
B91: =B11 -> Mondelez | F91: =IF(AND(AND(Peer_Inputs!$Q16=1,Peer_Inputs!$D16=2),ISNUMBER(F11)),F11,"") | G91: =IF(AND(AND(Peer_Inputs!$Q16=1,Peer_Inputs!$D16=2),ISNUMBER(G11)),G11,"") | H91: =IF(AND(AND(Peer_Inputs!$Q16=1,Peer_Inputs!$D16=2),ISNUMBER(H11)),H11,"") | I91: =IF(AND(AND(Peer_Inputs!$Q16=1,Peer_Inputs!$D16=2),ISNUMBER(I11)),I11,"") | J91: =IF(AND(AND(Peer_Inputs!$Q16=1,Peer_Inputs!$D16=2),ISNUMBER(J11)),J11,"") | K91: =IF(AND(AND(Peer_Inputs!$Q16=1,Peer_Inputs!$D16=2),ISNUMBER(K11)),K11,"") | L91: =IF(AND(AND(Peer_Inputs!$Q16=1,Peer_Inputs!$D16=2),ISNUMBER(L11)),L11,"") | M91: =IF(AND(AND(Peer_Inputs!$Q16=1,Peer_Inputs!$D16=2),ISNUMBER(M11)),M11,"") | ... Q91: =IF(AND(AND(Peer_Inputs!$Q16=1,Peer_Inputs!$D16=2),ISNUMBER(Q11)),Q11,"")
B92: =B12 -> Coca-Cola | F92: =IF(AND(AND(Peer_Inputs!$Q17=1,Peer_Inputs!$D17=2),ISNUMBER(F12)),F12,"") -> 8.0110647 | G92: =IF(AND(AND(Peer_Inputs!$Q17=1,Peer_Inputs!$D17=2),ISNUMBER(G12)),G12,"") -> 7.6440239 | H92: =IF(AND(AND(Peer_Inputs!$Q17=1,Peer_Inputs!$D17=2),ISNUMBER(H12)),H12,"") -> 7.2676136 | I92: =IF(AND(AND(Peer_Inputs!$Q17=1,Peer_Inputs!$D17=2),ISNUMBER(I12)),I12,"") -> 23.983125 | J92: =IF(AND(AND(Peer_Inputs!$Q17=1,Peer_Inputs!$D17=2),ISNUMBER(J12)),J12,"") -> 22.705917 | K92: =IF(AND(AND(Peer_Inputs!$Q17=1,Peer_Inputs!$D17=2),ISNUMBER(K12)),K12,"") -> 21.43743 | L92: =IF(AND(AND(Peer_Inputs!$Q17=1,Peer_Inputs!$D17=2),ISNUMBER(L12)),L12,"") -> 25.753691 | M92: =IF(AND(AND(Peer_Inputs!$Q17=1,Peer_Inputs!$D17=2),ISNUMBER(M12)),M12,"") -> 24.286709 | ... Q92: =IF(AND(AND(Peer_Inputs!$Q17=1,Peer_Inputs!$D17=2),ISNUMBER(Q12)),Q12,"") -> 24.956522
B93: =B13 -> Hershey | F93: =IF(AND(AND(Peer_Inputs!$Q18=1,Peer_Inputs!$D18=2),ISNUMBER(F13)),F13,"") -> 3.1690386 | G93: =IF(AND(AND(Peer_Inputs!$Q18=1,Peer_Inputs!$D18=2),ISNUMBER(G13)),G13,"") -> 3.0138204 | H93: =IF(AND(AND(Peer_Inputs!$Q18=1,Peer_Inputs!$D18=2),ISNUMBER(H13)),H13,"") -> 2.9070315 | I93: =IF(AND(AND(Peer_Inputs!$Q18=1,Peer_Inputs!$D18=2),ISNUMBER(I13)),I13,"") -> 13.573272 | J93: =IF(AND(AND(Peer_Inputs!$Q18=1,Peer_Inputs!$D18=2),ISNUMBER(J13)),J13,"") -> 11.020687 | K93: =IF(AND(AND(Peer_Inputs!$Q18=1,Peer_Inputs!$D18=2),ISNUMBER(K13)),K13,"") -> 10.312654 | L93: =IF(AND(AND(Peer_Inputs!$Q18=1,Peer_Inputs!$D18=2),ISNUMBER(L13)),L13,"") -> 16.408578 | M93: =IF(AND(AND(Peer_Inputs!$Q18=1,Peer_Inputs!$D18=2),ISNUMBER(M13)),M13,"") -> 12.908846 | ... Q93: =IF(AND(AND(Peer_Inputs!$Q18=1,Peer_Inputs!$D18=2),ISNUMBER(Q13)),Q13,"") -> 17.898876
B94: =B14 -> General Mills | F94: =IF(AND(AND(Peer_Inputs!$Q19=1,Peer_Inputs!$D19=2),ISNUMBER(F14)),F14,"") -> 1.6541034 | G94: =IF(AND(AND(Peer_Inputs!$Q19=1,Peer_Inputs!$D19=2),ISNUMBER(G14)),G14,"") -> 1.7214715 | H94: =IF(AND(AND(Peer_Inputs!$Q19=1,Peer_Inputs!$D19=2),ISNUMBER(H14)),H14,"") -> 1.7166963 | I94: =IF(AND(AND(Peer_Inputs!$Q19=1,Peer_Inputs!$D19=2),ISNUMBER(I14)),I14,"") -> 8.3424264 | J94: =IF(AND(AND(Peer_Inputs!$Q19=1,Peer_Inputs!$D19=2),ISNUMBER(J14)),J14,"") -> 9.0433853 | K94: =IF(AND(AND(Peer_Inputs!$Q19=1,Peer_Inputs!$D19=2),ISNUMBER(K14)),K14,"") -> 8.9691159 | L94: =IF(AND(AND(Peer_Inputs!$Q19=1,Peer_Inputs!$D19=2),ISNUMBER(L14)),L14,"") -> 9.794814 | M94: =IF(AND(AND(Peer_Inputs!$Q19=1,Peer_Inputs!$D19=2),ISNUMBER(M14)),M14,"") -> 10.775432 | ... Q94: =IF(AND(AND(Peer_Inputs!$Q19=1,Peer_Inputs!$D19=2),ISNUMBER(Q14)),Q14,"") -> 9.7421174
B95: =B15 -> Kraft Heinz | F95: =IF(AND(AND(Peer_Inputs!$Q20=1,Peer_Inputs!$D20=2),ISNUMBER(F15)),F15,"") -> 1.8300517 | G95: =IF(AND(AND(Peer_Inputs!$Q20=1,Peer_Inputs!$D20=2),ISNUMBER(G15)),G15,"") -> 1.8900683 | H95: =IF(AND(AND(Peer_Inputs!$Q20=1,Peer_Inputs!$D20=2),ISNUMBER(H15)),H15,"") -> 1.8979272 | I95: =IF(AND(AND(Peer_Inputs!$Q20=1,Peer_Inputs!$D20=2),ISNUMBER(I15)),I15,"") -> 7.7364661 | J95: =IF(AND(AND(Peer_Inputs!$Q20=1,Peer_Inputs!$D20=2),ISNUMBER(J15)),J15,"") -> 8.5318037 | K95: =IF(AND(AND(Peer_Inputs!$Q20=1,Peer_Inputs!$D20=2),ISNUMBER(K15)),K15,"") -> 8.6122925 | L95: =IF(AND(AND(Peer_Inputs!$Q20=1,Peer_Inputs!$D20=2),ISNUMBER(L15)),L15,"") -> 9.2212424 | M95: =IF(AND(AND(Peer_Inputs!$Q20=1,Peer_Inputs!$D20=2),ISNUMBER(M15)),M15,"") -> 10.373898 | ... Q95: =IF(AND(AND(Peer_Inputs!$Q20=1,Peer_Inputs!$D20=2),ISNUMBER(Q15)),Q15,"") -> 10.32093

Sheet Precedent_Txns
Q1: Basis of Assumption / Source
B3: Precedent Transactions – Global Food, Beverage & Consumer Staples (2023–2026)
B5: USD millions. LTM = last twelve months before announcement. Multiples are headline (pre-synergy) as disclosed by the parties.
B7: Announced | C7: Target | D7: Acquirer | E7: Target business | F7: Size class | G7: Deal type | H7: Enterprise value | I7: LTM sales | J7: LTM EBITDA | K7: EV / LTM Sales | L7: EV / LTM EBITDA | M7: EBITDA margin | N7: Premium paid | O7: Include (1/0)
B8: 46112 | C8: Unilever Foods (Knorr, Hellmann's) | D8: McCormick | E8: Cooking aids & condiments | F8: Large-cap | G8: Carve-out / RMT | H8: 44800 | I8: 12444 | J8: 3246 | K8: =IF(AND(ISNUMBER(I8),I8>0),H8/I8,"n.a.") -> 3.6001286 | L8: =IF(AND(ISNUMBER(J8),J8>0),H8/J8,"n.a.") -> 13.801602 | M8: =IF(AND(ISNUMBER(J8),ISNUMBER(I8)),J8/I8,"n.a.") -> 0.2608486 | N8: n.a. | O8: 1 | Q8: EV USD 44.8bn = 3.6x sales / 13.8x FY2025 underlying EBITDA (~EUR 2.8bn) per Unilever & McCormick releases (31-Mar-2026). Reverse Morris Trust: Unilever receives USD 15.7bn cash + 65% of combined equity. Sales/EBITDA backed out from the disclosed multiples. No premium (carve-out). Most relevant datapoint: a Nestlé-style global food portfolio.
B9: 45964 | C9: Kenvue | D9: Kimberly-Clark | E9: Consumer health (HPC) | F9: Large-cap | G9: Public, cash+stock | H9: 48700 | I9: 15100 | J9: 3406 | K9: =IF(AND(ISNUMBER(I9),I9>0),H9/I9,"n.a.") -> 3.2251656 | L9: =IF(AND(ISNUMBER(J9),J9>0),H9/J9,"n.a.") -> 14.298297 | M9: =IF(AND(ISNUMBER(J9),ISNUMBER(I9)),J9/I9,"n.a.") -> 0.22556291 | N9: 0.46 | O9: 1 | Q9: EV USD 48.7bn, ~14.3x LTM adj. EBITDA (8.8x incl. synergies); 46% premium to unaffected close. Adjacent staples category (not food) – keep for large-cap control benchmark.
B10: 45894 | C10: JDE Peet's | D10: Keurig Dr Pepper | E10: Coffee | F10: Large-cap | G10: Public, cash | H10: 22900 | I10: 10300 | J10: 1759 | K10: =IF(AND(ISNUMBER(I10),I10>0),H10/I10,"n.a.") -> 2.223301 | L10: =IF(AND(ISNUMBER(J10),J10>0),H10/J10,"n.a.") -> 13.018761 | M10: =IF(AND(ISNUMBER(J10),ISNUMBER(I10)),J10/I10,"n.a.") -> 0.1707767 | N10: 0.33 | O10: 1 | Q10: EV ~USD 22.9bn at ~13.0x LTM EBITDA (EUR 31.85/sh cash). Coffee = Nestlé's largest category (Nescafé, Nespresso) -> highly relevant. Premium ~33% vs 90-day VWAP (approx.).
B11: 45848 | C11: WK Kellogg Co | D11: Ferrero | E11: Breakfast cereal | F11: Mid-cap | G11: Public, cash | H11: 3100 | I11: 2650 | J11: 290 | K11: =IF(AND(ISNUMBER(I11),I11>0),H11/I11,"n.a.") -> 1.1698113 | L11: =IF(AND(ISNUMBER(J11),J11>0),H11/J11,"n.a.") -> 10.689655 | M11: =IF(AND(ISNUMBER(J11),ISNUMBER(I11)),J11/I11,"n.a.") -> 0.10943396 | N11: 0.4 | O11: 1 | Q11: EV ~USD 3.1bn (USD 23/sh); ~10.7x LTM adj. EBITDA; ~40% premium to 30-day VWAP (31% to last close). Low-growth US cereal -> low end of range.
B12: 45518 | C12: Kellanova | D12: Mars | E12: Snacks (Pringles, Cheez-It) | F12: Large-cap | G12: Public, cash | H12: 35900 | I12: 12950 | J12: 2189 | K12: =IF(AND(ISNUMBER(I12),I12>0),H12/I12,"n.a.") -> 2.7722008 | L12: =IF(AND(ISNUMBER(J12),J12>0),H12/J12,"n.a.") -> 16.400183 | M12: =IF(AND(ISNUMBER(J12),ISNUMBER(I12)),J12/I12,"n.a.") -> 0.16903475 | N12: 0.44 | O12: 1 | Q12: EV USD 35.9bn (USD 83.50/sh) = ~16.4x LTM adj. EBITDA; 44% premium to 30-day VWAP. Closed Dec-2025 after EU review. Scarce global snacking asset -> top of large-cap range.
B13: 45180 | C13: Hostess Brands | D13: J.M. Smucker | E13: Sweet baked goods | F13: Mid-cap | G13: Public, cash+stock | H13: 5600 | I13: 1380 | J13: 320 | K13: =IF(AND(ISNUMBER(I13),I13>0),H13/I13,"n.a.") -> 4.057971 | L13: =IF(AND(ISNUMBER(J13),J13>0),H13/J13,"n.a.") -> 17.5 | M13: =IF(AND(ISNUMBER(J13),ISNUMBER(I13)),J13/I13,"n.a.") -> 0.23188406 | N13: 0.54 | O13: 1 | Q13: EV USD 5.6bn (USD 34.25/sh) ~17.5x LTM adj. EBITDA pre-synergy; ~54% premium. Peak-cycle 2023 pricing; later impaired by Smucker -> treat as high-end outlier.
B14: 45145 | C14: Sovos Brands (Rao's) | D14: Campbell Soup | E14: Premium sauces | F14: Mid-cap | G14: Public, cash | H14: 2700 | I14: 900 | J14: 160 | K14: =IF(AND(ISNUMBER(I14),I14>0),H14/I14,"n.a.") -> 3 | L14: =IF(AND(ISNUMBER(J14),J14>0),H14/J14,"n.a.") -> 16.875 | M14: =IF(AND(ISNUMBER(J14),ISNUMBER(I14)),J14/I14,"n.a.") -> 0.17777778 | N14: 0.28 | O14: 1 | Q14: EV USD 2.7bn (USD 23/sh) ~17x LTM adj. EBITDA pre-synergy (high-growth premium brand); 28% premium.
C16: All deals – Maximum | K16: =IFERROR(MAX(K32:K38),"n.a.") -> 4.057971 | L16: =IFERROR(MAX(L32:L38),"n.a.") -> 17.5 | M16: =IFERROR(MAX(M32:M38),"n.a.") -> 0.2608486 | N16: =IFERROR(MAX(N32:N38),"n.a.") -> 0.54 | Q16: Precedent multiples embed a CONTROL PREMIUM (and often synergies the buyer expects), so they value Nestlé as if 100% were acquired. Read them as a 'takeout / control value' reference, not a fair trading value. Median EV/LTM EBITDA across the set ~14x vs peer trading median ~11x -> the gap is effectively the control premium.
C17: All deals – 75th percentile | K17: =IFERROR(QUARTILE(K32:K38,3),"n.a.") -> 3.4126471 | L17: =IFERROR(QUARTILE(L32:L38,3),"n.a.") -> 16.637591 | M17: =IFERROR(QUARTILE(M32:M38,3),"n.a.") -> 0.22872349 | N17: =IFERROR(QUARTILE(N32:N38,3),"n.a.") -> 0.455
C18: All deals – Mean | K18: =IFERROR(AVERAGE(K32:K38),"n.a.") -> 2.8640826 | L18: =IFERROR(AVERAGE(L32:L38),"n.a.") -> 14.654785 | M18: =IFERROR(AVERAGE(M32:M38),"n.a.") -> 0.19218839 | N18: =IFERROR(AVERAGE(N32:N38),"n.a.") -> 0.40833333
C19: All deals – Median | K19: =IFERROR(MEDIAN(K32:K38),"n.a.") -> 3 | L19: =IFERROR(MEDIAN(L32:L38),"n.a.") -> 14.298297 | M19: =IFERROR(MEDIAN(M32:M38),"n.a.") -> 0.17777778 | N19: =IFERROR(MEDIAN(N32:N38),"n.a.") -> 0.42
C20: All deals – 25th percentile | K20: =IFERROR(QUARTILE(K32:K38,1),"n.a.") -> 2.4977509 | L20: =IFERROR(QUARTILE(L32:L38,1),"n.a.") -> 13.410181 | M20: =IFERROR(QUARTILE(M32:M38,1),"n.a.") -> 0.16990572 | N20: =IFERROR(QUARTILE(N32:N38,1),"n.a.") -> 0.3475
C21: All deals – Minimum | K21: =IFERROR(MIN(K32:K38),"n.a.") -> 1.1698113 | L21: =IFERROR(MIN(L32:L38),"n.a.") -> 10.689655 | M21: =IFERROR(MIN(M32:M38),"n.a.") -> 0.10943396 | N21: =IFERROR(MIN(N32:N38),"n.a.") -> 0.28
C23: Large-cap – 75th percentile | K23: =IFERROR(QUARTILE(K42:K48,3),"n.a.") -> 3.3189063 | L23: =IFERROR(QUARTILE(L42:L48,3),"n.a.") -> 14.823769 | M23: =IFERROR(QUARTILE(M42:M48,3),"n.a.") -> 0.23438434 | N23: =IFERROR(QUARTILE(N42:N48,3),"n.a.") -> 0.45 | Q23: Large-cap (EV > USD 20bn) subset is the more relevant benchmark for Nestlé's scale – smaller brand deals (Sovos, Hostess) carry scarcity/growth premia that do not transfer to a CHF ~220bn EV conglomerate.
C24: Large-cap – Median | K24: =IFERROR(QUARTILE(K42:K48,2),"n.a.") -> 2.9986832 | L24: =IFERROR(QUARTILE(L42:L48,2),"n.a.") -> 14.04995 | M24: =IFERROR(QUARTILE(M42:M48,2),"n.a.") -> 0.19816981 | N24: =IFERROR(QUARTILE(N42:N48,2),"n.a.") -> 0.44
C25: Large-cap – 25th percentile | K25: =IFERROR(QUARTILE(K42:K48,1),"n.a.") -> 2.6349758 | L25: =IFERROR(QUARTILE(L42:L48,1),"n.a.") -> 13.605892 | M25: =IFERROR(QUARTILE(M42:M48,1),"n.a.") -> 0.17034121 | N25: =IFERROR(QUARTILE(N42:N48,1),"n.a.") -> 0.385
Q26: Reality check: with an EV of ~CHF 220bn Nestlé is effectively un-acquirable (it would be the largest food deal ever by >4x). Precedents therefore get ZERO weight in the blended value (see Valuation) and are shown on the football field for context only. Sources: company press releases / merger proxies; Iconic 'CPG valuation multiples 2026' (Kellanova 16.4x, Kenvue 14.3x, JDE Peet's 13.02x). Figures approximate – verify vs. proxy statements.
B30: Helper (feeds statistics)
B31: All included deals
C32: =C8 -> Unilever Foods (Knorr, Hellmann's) | K32: =IF(AND($O8=1,ISNUMBER(K8)),K8,"") -> 3.6001286 | L32: =IF(AND($O8=1,ISNUMBER(L8)),L8,"") -> 13.801602 | M32: =IF(AND($O8=1,ISNUMBER(M8)),M8,"") -> 0.2608486 | N32: =IF(AND($O8=1,ISNUMBER(N8)),N8,"")
C33: =C9 -> Kenvue | K33: =IF(AND($O9=1,ISNUMBER(K9)),K9,"") -> 3.2251656 | L33: =IF(AND($O9=1,ISNUMBER(L9)),L9,"") -> 14.298297 | M33: =IF(AND($O9=1,ISNUMBER(M9)),M9,"") -> 0.22556291 | N33: =IF(AND($O9=1,ISNUMBER(N9)),N9,"") -> 0.46
C34: =C10 -> JDE Peet's | K34: =IF(AND($O10=1,ISNUMBER(K10)),K10,"") -> 2.223301 | L34: =IF(AND($O10=1,ISNUMBER(L10)),L10,"") -> 13.018761 | M34: =IF(AND($O10=1,ISNUMBER(M10)),M10,"") -> 0.1707767 | N34: =IF(AND($O10=1,ISNUMBER(N10)),N10,"") -> 0.33
C35: =C11 -> WK Kellogg Co | K35: =IF(AND($O11=1,ISNUMBER(K11)),K11,"") -> 1.1698113 | L35: =IF(AND($O11=1,ISNUMBER(L11)),L11,"") -> 10.689655 | M35: =IF(AND($O11=1,ISNUMBER(M11)),M11,"") -> 0.10943396 | N35: =IF(AND($O11=1,ISNUMBER(N11)),N11,"") -> 0.4
C36: =C12 -> Kellanova | K36: =IF(AND($O12=1,ISNUMBER(K12)),K12,"") -> 2.7722008 | L36: =IF(AND($O12=1,ISNUMBER(L12)),L12,"") -> 16.400183 | M36: =IF(AND($O12=1,ISNUMBER(M12)),M12,"") -> 0.16903475 | N36: =IF(AND($O12=1,ISNUMBER(N12)),N12,"") -> 0.44
C37: =C13 -> Hostess Brands | K37: =IF(AND($O13=1,ISNUMBER(K13)),K13,"") -> 4.057971 | L37: =IF(AND($O13=1,ISNUMBER(L13)),L13,"") -> 17.5 | M37: =IF(AND($O13=1,ISNUMBER(M13)),M13,"") -> 0.23188406 | N37: =IF(AND($O13=1,ISNUMBER(N13)),N13,"") -> 0.54
C38: =C14 -> Sovos Brands (Rao's) | K38: =IF(AND($O14=1,ISNUMBER(K14)),K14,"") -> 3 | L38: =IF(AND($O14=1,ISNUMBER(L14)),L14,"") -> 16.875 | M38: =IF(AND($O14=1,ISNUMBER(M14)),M14,"") -> 0.17777778 | N38: =IF(AND($O14=1,ISNUMBER(N14)),N14,"") -> 0.28
B41: Large-cap included deals
C42: =C8 -> Unilever Foods (Knorr, Hellmann's) | K42: =IF(AND(AND($O8=1,$F8="Large-cap"),ISNUMBER(K8)),K8,"") -> 3.6001286 | L42: =IF(AND(AND($O8=1,$F8="Large-cap"),ISNUMBER(L8)),L8,"") -> 13.801602 | M42: =IF(AND(AND($O8=1,$F8="Large-cap"),ISNUMBER(M8)),M8,"") -> 0.2608486 | N42: =IF(AND(AND($O8=1,$F8="Large-cap"),ISNUMBER(N8)),N8,"")
C43: =C9 -> Kenvue | K43: =IF(AND(AND($O9=1,$F9="Large-cap"),ISNUMBER(K9)),K9,"") -> 3.2251656 | L43: =IF(AND(AND($O9=1,$F9="Large-cap"),ISNUMBER(L9)),L9,"") -> 14.298297 | M43: =IF(AND(AND($O9=1,$F9="Large-cap"),ISNUMBER(M9)),M9,"") -> 0.22556291 | N43: =IF(AND(AND($O9=1,$F9="Large-cap"),ISNUMBER(N9)),N9,"") -> 0.46
C44: =C10 -> JDE Peet's | K44: =IF(AND(AND($O10=1,$F10="Large-cap"),ISNUMBER(K10)),K10,"") -> 2.223301 | L44: =IF(AND(AND($O10=1,$F10="Large-cap"),ISNUMBER(L10)),L10,"") -> 13.018761 | M44: =IF(AND(AND($O10=1,$F10="Large-cap"),ISNUMBER(M10)),M10,"") -> 0.1707767 | N44: =IF(AND(AND($O10=1,$F10="Large-cap"),ISNUMBER(N10)),N10,"") -> 0.33
C45: =C11 -> WK Kellogg Co | K45: =IF(AND(AND($O11=1,$F11="Large-cap"),ISNUMBER(K11)),K11,"") | L45: =IF(AND(AND($O11=1,$F11="Large-cap"),ISNUMBER(L11)),L11,"") | M45: =IF(AND(AND($O11=1,$F11="Large-cap"),ISNUMBER(M11)),M11,"") | N45: =IF(AND(AND($O11=1,$F11="Large-cap"),ISNUMBER(N11)),N11,"")
C46: =C12 -> Kellanova | K46: =IF(AND(AND($O12=1,$F12="Large-cap"),ISNUMBER(K12)),K12,"") -> 2.7722008 | L46: =IF(AND(AND($O12=1,$F12="Large-cap"),ISNUMBER(L12)),L12,"") -> 16.400183 | M46: =IF(AND(AND($O12=1,$F12="Large-cap"),ISNUMBER(M12)),M12,"") -> 0.16903475 | N46: =IF(AND(AND($O12=1,$F12="Large-cap"),ISNUMBER(N12)),N12,"") -> 0.44
C47: =C13 -> Hostess Brands | K47: =IF(AND(AND($O13=1,$F13="Large-cap"),ISNUMBER(K13)),K13,"") | L47: =IF(AND(AND($O13=1,$F13="Large-cap"),ISNUMBER(L13)),L13,"") | M47: =IF(AND(AND($O13=1,$F13="Large-cap"),ISNUMBER(M13)),M13,"") | N47: =IF(AND(AND($O13=1,$F13="Large-cap"),ISNUMBER(N13)),N13,"")
C48: =C14 -> Sovos Brands (Rao's) | K48: =IF(AND(AND($O14=1,$F14="Large-cap"),ISNUMBER(K14)),K14,"") | L48: =IF(AND(AND($O14=1,$F14="Large-cap"),ISNUMBER(L14)),L14,"") | M48: =IF(AND(AND($O14=1,$F14="Large-cap"),ISNUMBER(M14)),M14,"") | N48: =IF(AND(AND($O14=1,$F14="Large-cap"),ISNUMBER(N14)),N14,"")

Sheet Peer_Inputs
S1: Basis of Assumption / Source
B3: Peer Inputs – Market Data, Consensus Estimates & Calendarisation
B6: FX table | C6: Code | D6: CHF per 1
B7: Swiss franc | C7: CHF | D7: 1 | S7: FX rates identical to the DCF WACC peer table (USD/CHF 0.79, EUR/CHF 0.93) so all three models are consistent. FX only affects size columns (CHF market cap / EV); multiples are currency-neutral because EV and the metric are in the same currency.
B8: US dollar | C8: USD | D8: 0.79 | S8: Pricing date: 1-Oct-2026 (same as Nestlé and the DCF Model).
B9: Euro | C9: EUR | D9: 0.93
B11: Company | C11: Ticker | D11: Tier | E11: Curr | F11: FYE | G11: Share price | H11: Diluted shares (mm) | I11: Market cap | J11: Net debt | K11: NCI & other debt-like | L11: Less: equity investments | M11: Enterprise value | N11: FX to CHF | O11: Market cap (CHF mm) | P11: EV (CHF mm) | Q11: Include in stats
B12: Table A – Market data (local currency mm)
B13: Danone | C13: BN FP | D13: 1 | E13: EUR | F13: Dec | G13: 57.55 | H13: 645 | I13: =G13*H13 -> 37119.75 | J13: 9800 | K13: 600 | L13: 800 | M13: =I13+J13+K13-L13 -> 46719.75 | N13: =INDEX($D$7:$D$9,MATCH(E13,$C$7:$C$9,0)) -> 0.93 | O13: =I13*N13 -> 34521.368 | P13: =M13*N13 -> 43449.368 | Q13: 1 | S13: Tier 1 = global, diversified food & beverage/HPC leaders with Nestlé-like scale, brand breadth and EM exposure (Danone, Unilever, PepsiCo, Mondelez). Tier 2 = category specialists / US-centric packaged food (Coca-Cola, Hershey, General Mills, Kraft Heinz). Peer set = DCF WACC peers + 3 US packaged-food names to widen the sample. Danone EUR 57.55 (1-Oct-2026 close; down from EUR 60.7 on 23-Sep).
B14: Unilever | C14: ULVR LN | D14: 1 | E14: EUR | F14: Dec | G14: 51.68 | H14: 2190 | I14: =G14*H14 -> 113179.2 | J14: 22500 | K14: 18000 | L14: 500 | M14: =I14+J14+K14-L14 -> 153179.2 | N14: =INDEX($D$7:$D$9,MATCH(E14,$C$7:$C$9,0)) -> 0.93 | O14: =I14*N14 -> 105256.66 | P14: =M14*N14 -> 142456.66 | Q14: 1 | S14: Unilever: LSE close 4,494p on 1-Oct-2026 converted at c.1.15 EUR/GBP = EUR 51.68; 2,190m shares in issue after the 2026 buyback (market cap c.GBP 98bn / EUR 113bn). NCI shown at a MARKET-value proxy (~EUR 18bn = 38% minority in listed Hindustan Unilever) rather than book (~EUR 2.6bn): EBITDA consolidates 100% of HUL, so EV must carry the minority at market. Financials = continuing ops (ex-ice cream, demerged Dec-2025) incl. Foods, being combined with McCormick (announced 31-Mar-2026, not yet closed).
B15: PepsiCo | C15: PEP US | D15: 1 | E15: USD | F15: Dec | G15: 125.6 | H15: 1370 | I15: =G15*H15 -> 172072 | J15: 43500 | K15: 500 | L15: 1500 | M15: =I15+J15+K15-L15 -> 214572 | N15: =INDEX($D$7:$D$9,MATCH(E15,$C$7:$C$9,0)) -> 0.79 | O15: =I15*N15 -> 135936.88 | P15: =M15*N15 -> 169511.88 | Q15: 1 | S15: PepsiCo: close USD 125.60 on 1-Oct-2026 (52-week low; two broker downgrades in Sep-2026 on the North America turnaround). Core (non-GAAP) EBITDA/EPS consensus.
B16: Mondelez | C16: MDLZ US | D16: 1 | E16: USD | F16: Dec | G16: 57.76 | H16: 1276 | I16: =G16*H16 -> 73701.76 | J16: 19500 | K16: 100 | L16: 1000 | M16: =I16+J16+K16-L16 -> 92301.76 | N16: =INDEX($D$7:$D$9,MATCH(E16,$C$7:$C$9,0)) -> 0.79 | O16: =I16*N16 -> 58224.39 | P16: =M16*N16 -> 72918.39 | Q16: 1 | S16: Mondelez: close USD 57.76 on 1-Oct-2026 x 1,276m shares (market cap c.USD 74bn). Corrects the previous USD 45.10 input, which sat below the 52-week range (USD 51.20–66.65) and understated Mondelez's multiples by c.2x EBITDA. Cocoa-cost squeeze depresses 2025-26 margins.
B17: Coca-Cola | C17: KO US | D17: 2 | E17: USD | F17: Dec | G17: 86.1 | H17: 4300 | I17: =G17*H17 -> 370230 | J17: 31000 | K17: 2000 | L17: 19500 | M17: =I17+J17+K17-L17 -> 383730 | N17: =INDEX($D$7:$D$9,MATCH(E17,$C$7:$C$9,0)) -> 0.79 | O17: =I17*N17 -> 292481.7 | P17: =M17*N17 -> 303146.7 | Q17: 1 | S17: Coca-Cola: close USD 86.10 on 1-Oct-2026. Large equity-method stakes (bottlers, Monster etc.) deducted at book ~USD 19.5bn – market value is materially higher, so KO's EV/EBITDA is if anything understated. Structurally premium multiple (asset-light concentrate model, ~33% EBITDA margin): statistical outlier – toggle Q to 0 to test sensitivity.
B18: Hershey | C18: HSY US | D18: 2 | E18: USD | F18: Dec | G18: 159.3 | H18: 201 | I18: =G18*H18 -> 32019.3 | J18: 4900 | K18: 0 | L18: 0 | M18: =I18+J18+K18-L18 -> 36919.3 | N18: =INDEX($D$7:$D$9,MATCH(E18,$C$7:$C$9,0)) -> 0.79 | O18: =I18*N18 -> 25295.247 | P18: =M18*N18 -> 29166.247 | Q18: 1 | S18: Hershey: close USD 159.30 on 1-Oct-2026; c.201m shares. 2026E rebound reflects cocoa-cost normalisation.
B19: General Mills | C19: GIS US | D19: 2 | E19: USD | F19: May | G19: 31.67 | H19: 535 | I19: =G19*H19 -> 16943.45 | J19: 14200 | K19: 300 | L19: 500 | M19: =I19+J19+K19-L19 -> 30943.45 | N19: =INDEX($D$7:$D$9,MATCH(E19,$C$7:$C$9,0)) -> 0.79 | O19: =I19*N19 -> 13385.326 | P19: =M19*N19 -> 24445.326 | Q19: 1 | S19: General Mills: close USD 31.67 on 1-Oct-2026 (–22% in Sep-2026 after the Q1-FY27 print and CEO transition). Fiscal year ends late May -> financials CALENDARISED in Table C below (Table B links to it). CPW (Cereal Partners Worldwide) is a 50/50 JV with Nestlé.
B20: Kraft Heinz | C20: KHC US | D20: 2 | E20: USD | F20: Dec | G20: 22.19 | H20: 1185 | I20: =G20*H20 -> 26295.15 | J20: 19200 | K20: 150 | L20: 0 | M20: =I20+J20+K20-L20 -> 45645.15 | N20: =INDEX($D$7:$D$9,MATCH(E20,$C$7:$C$9,0)) -> 0.79 | O20: =I20*N20 -> 20773.169 | P20: =M20*N20 -> 36059.668 | Q20: 1 | S20: Kraft Heinz: latest close c.USD 22.2 (1–2 Oct-2026); planned separation paused Feb-2026; reduced 2026 outlook after soft Q2-2026.
S21: IMPORTANT: peer prices refreshed to 1-Oct-2026 closes; consensus estimates are approximate public-source figures (company reports, press, Yahoo/MarketScreener) as of Sep-2026. Refresh blue cells from Bloomberg / CapIQ / FactSet before external use. Net debt = latest reported gross financial debt incl. leases less cash & ST investments (approx.). Q column (yellow) = switch to exclude a peer from all statistics.
B22: Table B – Consensus financials, calendarised to December year-end (local currency mm; EPS per share)
B23: Company | C23: Ccy | D23: Sales | G23: Adj. EBITDA | J23: Adj. EBIT | M23: Adj. EPS
D24: CY2025A | E24: CY2026F | F24: CY2027F | G24: CY2025A | H24: CY2026F | I24: CY2027F | J24: CY2025A | K24: CY2026F | L24: CY2027F | M24: CY2025A | N24: CY2026F | O24: CY2027F
B25: =B13 -> Danone | C25: =E13 -> EUR | D25: 27450 | E25: 28300 | F25: 29350 | G25: 4855 | H25: 5070 | I25: 5320 | J25: 3705 | K25: 3905 | L25: 4140 | M25: 3.8 | N25: 4.02 | O25: 4.32 | S25: All figures on the companies' adjusted / underlying / 'core' basis (excl. restructuring, impairment, M&A costs) – the same basis used for Nestlé (see Nestle_Inputs). 2025A = reported; 2026E-27E = approximate sell-side consensus (Sep-2026). Danone/Unilever report in EUR; others in USD.
B26: =B14 -> Unilever | C26: =E14 -> EUR | D26: 51800 | E26: 52900 | F26: 54700 | G26: 11950 | H26: 12300 | I26: 12850 | J26: 10450 | K26: 10750 | L26: 11250 | M26: 2.8 | N26: 2.95 | O26: 3.15
B27: =B15 -> PepsiCo | C27: =E15 -> USD | D27: 93900 | E27: 96300 | F27: 99500 | G27: 17200 | H27: 17800 | I27: 18600 | J27: 13800 | K27: 14300 | L27: 15000 | M27: 8.1 | N27: 8.45 | O27: 8.95
B28: =B16 -> Mondelez | C28: =E16 -> USD | D28: 38500 | E28: 39600 | F28: 41000 | G28: 7150 | H28: 7300 | I28: 7800 | J28: 5950 | K28: 6050 | L28: 6500 | M28: 2.95 | N28: 3.05 | O28: 3.35
B29: =B17 -> Coca-Cola | C29: =E17 -> USD | D29: 47900 | E29: 50200 | F29: 52800 | G29: 16000 | H29: 16900 | I29: 17900 | J29: 14900 | K29: 15800 | L29: 16750 | M29: 3 | N29: 3.22 | O29: 3.45
B30: =B18 -> Hershey | C30: =E18 -> USD | D30: 11650 | E30: 12250 | F30: 12700 | G30: 2720 | H30: 3350 | I30: 3580 | J30: 2250 | K30: 2860 | L30: 3070 | M30: 6.1 | N30: 8.1 | O30: 8.9
B31: =B19 -> General Mills | C31: =E19 -> USD | D31: =I40 -> 18707.083 | E31: =J40 -> 17975 | F31: =K40 -> 18025 | G31: =I41 -> 3709.1667 | H31: =J41 -> 3421.6667 | I31: =K41 -> 3450 | J31: =I42 -> 3159.1667 | K31: =J42 -> 2871.6667 | L31: =K42 -> 2894.1667 | M31: =I43 -> 3.7375 | N31: =J43 -> 3.2075 | O31: =K43 -> 3.2508333 | S31: General Mills row links to Table C (calendarised) – do not overwrite.
B32: =B20 -> Kraft Heinz | C32: =E20 -> USD | D32: 24942 | E32: 24150 | F32: 24050 | G32: 5900 | H32: 5350 | I32: 5300 | J32: 4950 | K32: 4400 | L32: 4350 | M32: 2.58 | N32: 2.1 | O32: 2.15
B36: Table C – Calendarisation: General Mills (fiscal year ends last Sunday of May)
B37: Months of calendar year falling in the EARLIER fiscal year (Jan–May) | H37: 5 | S37: Calendarisation: CY2026 = 5/12 x FY26 (Jun-25 to May-26) + 7/12 x FY27 (Jun-26 to May-27). Without it General Mills' '2026' multiple would mix a period ending May-26 with Dec-26 peers.
B39: Metric (USD mm) | D39: FY25A (May-25) | E39: FY26A (May-26) | F39: FY27F (May-27) | G39: FY28F (May-28) | I39: CY2025A | J39: CY2026F | K39: CY2027F
B40: Net sales | D40: 19487 | E40: 18150 | F40: 17850 | G40: 18150 | I40: =$H$37/12*D40+(12-$H$37)/12*E40 -> 18707.083 | J40: =$H$37/12*E40+(12-$H$37)/12*F40 -> 17975 | K40: =$H$37/12*F40+(12-$H$37)/12*G40 -> 18025 | S40: FY25A-FY26A reported (adjusted); FY27E adjusted EPS USD 3.07 = consensus within the reaffirmed USD 3.00–3.20 guidance (23-Sep-2026, Q1-FY27 print: flat organic sales, lower profit on divestitures & inflation); FY28E = modest recovery consensus. Approximate – refresh before external use.
B41: Adj. EBITDA | D41: 4030 | E41: 3480 | F41: 3380 | G41: 3500 | I41: =$H$37/12*D41+(12-$H$37)/12*E41 -> 3709.1667 | J41: =$H$37/12*E41+(12-$H$37)/12*F41 -> 3421.6667 | K41: =$H$37/12*F41+(12-$H$37)/12*G41 -> 3450
B42: Adj. operating profit (EBIT) | D42: 3480 | E42: 2930 | F42: 2830 | G42: 2940 | I42: =$H$37/12*D42+(12-$H$37)/12*E42 -> 3159.1667 | J42: =$H$37/12*E42+(12-$H$37)/12*F42 -> 2871.6667 | K42: =$H$37/12*F42+(12-$H$37)/12*G42 -> 2894.1667
B43: Adj. diluted EPS (USD) | D43: 4.21 | E43: 3.4 | F43: 3.07 | G43: 3.38 | I43: =$H$37/12*D43+(12-$H$37)/12*E43 -> 3.7375 | J43: =$H$37/12*E43+(12-$H$37)/12*F43 -> 3.2075 | K43: =$H$37/12*F43+(12-$H$37)/12*G43 -> 3.2508333
B52: Trading comps range basis | E52: Precedents range basis
B53: 1 | E53: 1
B54: 2 | E54: 2
B55: 3 | E55: 3

Sheet Nestle_Inputs
K1: Basis of Assumption / Source
B3: Income Statement Bridge
B6: All figures in CHF millions unless stated | D6: =E6-1 -> 2023 | E6: =F6-1 -> 2024 | F6: 2025 | G6: =F6+1 -> 2026 | H6: =G6+1 -> 2027 | I6: =H6+1 -> 2028 | K6: Notes / Source
B7: Model Running: Base Case Drivers
B9: Sales | D9: 92998 | E9: 91354 | F9: 89490 | G9: 89937.45 | H9: 91286.512 | I9: 91742.944 | K9: 3-Statement Model (final, Base Case), Model sheet row 255 – identical in the DCF Model (row 440). 2023A–25A reported; 2026F–28F forecast.
B10: Sales growth | C10: % | E10: =E9/D9-1 -> -0.0176778 | F10: =F9/E9-1 -> -0.020404142 | G10: =G9/F9-1 -> 0.005 | H10: =H9/G9-1 -> 0.014999999 | I10: =I9/H9-1 -> 0.0050000005
B11: Operating profit (reported EBIT) | D11: 14063 | E11: 14724 | F11: 12277 | G11: 12383.451 | H11: 12834.192 | I11: 12686.43 | K11: 3-Statement Model row 267 / DCF Model row 452 (Base Case). Reported operating profit, i.e. after restructuring and other non-underlying items.
B12: Depreciation & amortisation | D12: 3458 | E12: 3582 | F12: 3633 | G12: 3445.54 | H12: 3487.477 | I12: 3522.5745 | K12: 3-Statement Model row 87 (combined D&A rate on opening PP&E + intangibles). 2027F–28F updated to the final model (CHF 3,487m / 3,523m), which now includes intangible capex in the asset base.
B13: EBITDA – reported (DCF basis) | D13: =D11+D12 -> 17521 | E13: =E11+E12 -> 18306 | F13: =F11+F12 -> 15910 | G13: =G11+G12 -> 15828.991 | H13: =H11+H12 -> 16321.669 | I13: =I11+I12 -> 16209.005
B15: Other trading income | D15: 132 | E15: 124 | F15: 135 | G15: 125.9124 | H15: 127.8011 | I15: 119.2658 | K15: 3-Statement Model rows 261, 262, 265 and 266 (Base Case) – identical in the DCF Model.
B16: Other trading expenses | D16: -1665 | E16: -1195 | F16: -1849 | G16: -2158.4988 | H16: -1734.4437 | I16: -1376.1442 | K16: As row 15 (3-Statement Model, Base Case).
B17: Other operating income | D17: 298 | E17: 474 | F17: 253 | G17: 269.8123 | H17: 255.6022 | I17: 247.7059 | K17: As row 15 (3-Statement Model, Base Case).
B18: Other operating expenses | D18: -755 | E18: -383 | F18: -651 | G18: -539.6247 | H18: -502.0758 | I18: -477.0633 | K18: As row 15 (3-Statement Model, Base Case).
B19: Net non-underlying items | D19: =SUM(D15:D18) -> -1990 | E19: =SUM(E15:E18) -> -980 | F19: =SUM(F15:F18) -> -2112 | G19: =SUM(G15:G18) -> -2302.3988 | H19: =SUM(H15:H18) -> -1853.1162 | I19: =SUM(I15:I18) -> -1486.2358 | K19: Nestlé's own KPI 'Underlying Trading Operating Profit' excludes these items. Peers' consensus EBITDA/EPS are ALSO on an adjusted/underlying basis, so Nestlé must be adjusted the same way – otherwise multiples are not like-for-like (reported 2025A EBITDA is CHF ~2.1bn lower).
B20: Adjusted EBIT | D20: =D11-D19 -> 16053 | E20: =E11-E19 -> 15704 | F20: =F11-F19 -> 14389 | G20: =G11-G19 -> 14685.85 | H20: =H11-H19 -> 14687.308 | I20: =I11-I19 -> 14172.666 | K20: Calc: Operating profit – net non-underlying items. 2025A = 16.1% of sales, consistent with Nestlé's reported underlying TOP margin for FY2025.
B22: Adjusted EBITDA (comps basis) | D22: =D20+D12 -> 19511 | E22: =E20+E12 -> 19286 | F22: =F20+F12 -> 18022 | G22: =G20+G12 -> 18131.39 | H22: =H20+H12 -> 18174.785 | I22: =I20+I12 -> 17695.241 | K22: PRIMARY metric for EV/EBITDA comps and precedents. 2025A is used as the LTM figure (valuation date 30-Jun-2026; the model has no H1-2026 split). Swap in true LTM Jun-26 if H1 data are added.
B23: Adj. EBITDA margin | C23: % | D23: =D22/D9 -> 0.20980021 | E23: =E22/E9 -> 0.21111281 | F23: =F22/F9 -> 0.20138563 | G23: =G22/G9 -> 0.2016 | H23: =H22/H9 -> 0.19909606 | I23: =I22/I9 -> 0.19287849
B24: Adj. EBIT margin | C24: % | D24: =D20/D9 -> 0.17261662 | E24: =E20/E9 -> 0.17190271 | F24: =F20/F9 -> 0.16078891 | G24: =G20/G9 -> 0.1632896 | H24: =H20/H9 -> 0.16089242 | I24: =I20/I9 -> 0.15448236
B25: Net profit attributable to parent (reported) | D25: 11209 | E25: 10884 | F25: 9033 | G25: 9249.174 | H25: 9649.4359 | I25: 9609.4927 | K25: 3-Statement Model row 278 (final). Higher than the previous DCF version because the interest rate on debt was reset to 2.9% (FY2025 actual cost) and the revolver/minimum-cash logic was added; 2026F CHF 9,249m.
B26: Adjusted net profit | D26: =D25-D19*(1-$D$55) -> 12731.35 | E26: =E25-E19*(1-$D$55) -> 11633.7 | F26: =F25-F19*(1-$D$55) -> 10648.68 | G26: =G25-G19*(1-$D$55) -> 11010.509 | H26: =H25-H19*(1-$D$55) -> 11067.07 | I26: =I25-I19*(1-$D$55) -> 10746.463 | K26: Calc: Reported NI + non-underlying items net of tax (tax rate in the market-data block below). Approximates Nestlé's 'underlying EPS' definition.
B27: Income from associates & JV (mainly L'Oréal) | D27: 1120 | E27: 1249 | F27: 1143 | G27: 1177.29 | H27: 1224.3816 | I27: 1273.3569 | K27: 3-Statement Model row 274: income from associates & JV grows 3–5% a year in the Base Case (mainly L'Oréal).
B28: Adjusted net profit excl. associates | D28: =D26-D27 -> 11611.35 | E28: =E26-E27 -> 10384.7 | F28: =F26-F27 -> 9505.68 | G28: =G26-G27 -> 9833.2191 | H28: =H26-H27 -> 9842.6882 | I28: =I26-I27 -> 9473.1062 | K28: Used for the P/E method: peers' P/E is applied to Nestlé's OWN operating earnings and the L'Oréal stake is added at market value separately (sum-of-the-parts). Applying a food-peer P/E (~15x) to L'Oréal earnings would undervalue a stake the market prices at ~30x.
B29: Diluted shares | C29: mm | D29: =$D$42 -> 2573 | E29: =$D$42 -> 2573 | F29: =$D$42 -> 2573 | G29: =$D$42 -> 2573 | H29: =$D$42 -> 2573 | I29: =$D$42 -> 2573 | K29: Links to diluted shares in the market-data block (2,573m, H1-2026 weighted average; DCF Input F207). Held flat – no buyback accretion assumed for multiples (the Base Case buyback only starts in 2030).
B30: Reported EPS | C30: CHF/sh | D30: =D25/D29 -> 4.3563933 | E30: =E25/E29 -> 4.2300816 | F30: =F25/F29 -> 3.5106879 | G30: =G25/G29 -> 3.5947042 | H30: =H25/H29 -> 3.7502666 | I30: =I25/I29 -> 3.7347426
B32: Adjusted EPS | C32: CHF/sh | D32: =D26/D29 -> 4.9480567 | E32: =E26/E29 -> 4.5214536 | F32: =F26/F29 -> 4.1386242 | G32: =G26/G29 -> 4.2792495 | H32: =H26/H29 -> 4.3012319 | I32: =I26/I29 -> 4.1766277 | K32: Adjusted EPS incl. associates – shown for reference (headline consensus basis).
B33: Adjusted EPS excl. associates | C33: CHF/sh | D33: =D28/D29 -> 4.5127672 | E33: =E28/E29 -> 4.036028 | F33: =F28/F29 -> 3.6943956 | G33: =G28/G29 -> 3.8216942 | H33: =H28/H29 -> 3.8253743 | I33: =I28/I29 -> 3.6817358
B34: Adjusted EPS growth | C34: % | E34: =E32/D32-1 -> -0.086216309 | F34: =F32/E32-1 -> -0.084669538 | G34: =G32/F32-1 -> 0.033978773 | H34: =H32/G32-1 -> 0.0051369751 | I34: =I32/H32-1 -> -0.02896943
B37: Market data & EV bridge
C40: Unit | D40: Value
B41: Share price (SIX close, 1-Oct-2026) | C41: CHF/sh | D41: 74.63 | K41: SIX close CHF 74.63 on 1-Oct-2026 – the same pricing date as the DCF Model (Input F208) and the peer set, so all three models share one pricing date.
B42: Diluted shares outstanding | C42: mm | D42: 2573 | K42: DCF Model Input F207 (weighted average shares outstanding H1-2026; issued 2,576.5m less treasury shares; no material dilutive instruments).
B43: Market capitalisation | D43: =D41*D42 -> 192022.99
B44: Net financial debt (30-Jun-2026) | D44: 56344 | K44: DCF Model Input N196: net financial debt CHF 56.3bn at 30-Jun-2026 (Nestlé H1-2026 results).
B45: Non-controlling interests | D45: 248 | K45: DCF Model Input N197 (FY2025 book value; immaterial).
B46: Net pension deficit (debt-like) | D46: 887 | K46: DCF Model Input N199: employee benefit liabilities CHF 2,299m less assets CHF 1,412m (FY2025 balance sheet), treated as debt-like.
B47: Nestlé stake in L'Oréal | C47: % | D47: 0.201 | K47: DCF Model Input N207–N211. L'Oréal is listed, so the 20.1% stake is valued at market (same treatment as the DCF Model).
B48: L'Oréal market capitalisation | C48: EUR mm | D48: 198430 | K48: EUR 371.75 closing price on 1-Oct-2026 x c.533.8m shares = EUR 198.4bn (DCF Input N208).
B49: EUR/CHF | C49: rate | D49: 0.93 | K49: Spot EUR/CHF, early Oct-2026 (DCF Input N209).
B50: Holding discount applied to L'Oréal stake | C50: % | D50: 0 | K50: No holding discount (Swiss participation exemption limits tax leakage on a disposal) – same as DCF Input N210.
B51: Associates at market value (L'Oréal stake) | D51: =D47*D48*D49*(1-D50) -> 37092.52 | K51: Associates income sits BELOW EBIT, so it is excluded from EBITDA; the stake must therefore be deducted from EV (and added back to equity) to keep numerator and denominator consistent.
B52: EV → Equity adjustment (– debt – NCI – pension + associates) | D52: =-D44-D45-D46+D51 -> -20386.48 | K52: Single bridge used for every method: Equity value = Enterprise value + this adjustment. Identical to the DCF Model equity bridge (Model sheet rows 277–282 and Output O15).
B54: Enterprise value at market (comps basis) | D54: =D43-D52 -> 212409.47 | K54: Nestlé EV on the SAME definition applied to the peers (market cap + net debt + NCI + debt-like items – equity investments).
B55: Tax rate applied to non-underlying items | C55: % | D55: 0.235 | K55: DCF Model Input M173: effective tax rate 23.5% (between the underlying 22.1–22.3% and reported 24.6% rates, incl. Pillar Two).
B56: 52-week low | C56: CHF/sh | D56: 70.29 | K56: 52-week range CHF 70.29–87.09 (SIX; high reached 22-Jul-2026). Source: Yahoo Finance / Investing.com, 1-Oct-2026.
B57: 52-week high | C57: CHF/sh | D57: 87.09
B58: Analyst target price – low | C58: CHF/sh | D58: 69 | K58: Sell-side consensus per Yahoo Finance, 1-Oct-2026: mean CHF 88.23, low CHF 69, high CHF 100 (MarketScreener / Investing.com show a similar c.CHF 88 mean).
B59: Analyst target price – high | C59: CHF/sh | D59: 100
B60: Analyst target price – mean (consensus) | C60: CHF/sh | D60: 88.23
B63: DCF Outputs
C66: Unit | D66: Low | E66: Base | F66: High
B67: Enterprise value – Perpetuity growth method | D67: 216776.36 | E67: 270962.36 | F67: 366878.64 | K67: Source: final DCF Model, Output sheet EV sensitivity (rows 25–29). Base = E16 (Model G277, XNPV); Low = WACC 5.59% / g 1.0% (E28); High = WACC 4.59% / g 2.0% (G26), i.e. WACC ±0.5% and g ±0.5% around the base – the standard football-field band.
B68: Enterprise value – Exit multiple method | D68: 220347.95 | E68: 232364.57 | F68: 244901.87 | K68: Source: final DCF Model, Output sheet rows 69–73. Base = E60 (Model G320); Low = WACC 5.59% / 13.0x (E72); High = WACC 4.59% / 14.0x (G70): WACC ±0.5% and exit multiple ±0.5x.
B69: WACC (base) | E69: 0.050865757 | K69: DCF Model Input N257: WACC 5.09% (CHF). Lower than the previous 5.21% because the pre-tax cost of debt now links to the 3-statement interest rate (2.9%); includes the corrected Mondelez market cap in the peer beta table.
B70: Terminal growth (base) | E70: 0.015 | K70: DCF Model Input F209 (= Base Case Term sales growth, 1.5% in CHF).
B71: Terminal EV/EBITDA multiple (base) | E71: 13.5 | K71: DCF Model Input F210.
B72: Check: base per-share value (perpetuity) vs DCF Model | C72: CHF/sh | D72: =(E67+D52)/D42 -> 97.386661 | E72: 97.39 | F72: =IF(ABS(D72-E72)<0.05,0,1) -> 0 | K72: Reconciliation: base per-share value (perpetuity) vs the DCF Model (Model M279 = Output G16 = CHF 97.39). Both the DCF Output dashboard and this model now use the same full equity bridge (net debt, NCI, pension, L'Oréal at market). Flag = 0 means tied.
