Workbook
Name ScenarioSwitch: Input!$D$6

Sheet Cover
C4: DCF Modeling | L4: CONFIDENTIAL
C7: Table of Contents | H7: Model Checks & Circularity
C9: Ouput | H9: Incorrect Date Set for Valuation? | L9: =Input!F200 -> 0
C10: Input | H10: Incorrect Date Set for First Cash Flow? | L10: =Input!F201 -> 0
C11: Model | H11: Terminal Growth Rate Greater Than or Equal To WACC? | L11: =Input!F212 -> 0
H12: Unused Tax Losses Remaining? (Levered Schedule) | L12: =Model!D127 -> 0
H13: Unused Tax Losses Remaining? (Unlevered Schedule) | L13: =Model!D165 -> 0
C14: Model Guide | H14: Two UFCF Methods Different? | L14: =IF(SUM(Model!I226:N226)>0,1,0) -> 0
H15: Balance Sheet Unbalanced? | L15: =IF(ROUND(SUMPRODUCT(ABS(Model!$F$580:$M$580)),2)=0,0,1) -> 0
C16: Adjustable Input | D16: (Grey Cell)
C17: Hardcode | D17: (Blue Font)
C18: Formula | D18: (Black Font)
O19: Do Not
C20: Model Circularity | O20: Delete
C22: Circularity Switch | D22: 0 | O22: Circularity
O23: 1
C24: =IF($D$22=1,"This model now has the circularity turned on. Please confirm the Excel settings below","") | O24: 0
C25: =IF($D$22=1,"PC","") | D25: =IF($D$22=1,"File - Options - Formulas - Check the box on the top-right labeled 'Enable iterative calculation'.","")
C26: =IF($D$22=1,"Mac","") | D26: =IF($D$22=1,"Excel - Preferences - Calculation - Check the box near the bottom labeled 'Use iterative calculation'.","")
C28: DISCLAIMER & NOTICE OF INTENT
C29: 1. Independent Portfolio Project: This financial model and dashboard were prepared solely by the author, in a personal capacity, to demonstrate
C30: skills in financial modeling and financial statement analysis. They do not reflect the views of any employer.
C31: 2. Public Data Sources: Historical figures are drawn from publicly available sources (Nestlé Investor Relations / Annual Reports). Forecasts and
C32: scenarios (Best / Base / Worst) are the author's own illustrative assumptions, not forecasts issued by Nestlé.
C33: 3. No Affiliation: This project is not affiliated with, authorized by, or endorsed by Nestlé S.A. Nestlé and related names and marks are the
C34: property of their respective owners and are used for identification only.
C35: 4. No Advice: Nothing herein constitutes investment advice, equity research, or a recommendation to buy or sell any security.

Sheet Output
B2: ="Nestlé S.A. | CHF millions | Scenario: "&INDEX(Input!$B$12:$B$14,Input!$D$6) -> Nestlé S.A. | CHF millions | Scenario: Base Case
B4: Dashboard: Perpetuity Method
B6: =Input!$B$8 -> All figures in CHF millions unless stated
B8: Driver Switch: | D8: 2
D10: Main Outputs 1 | L10: Selected Inputs
E12: Enterprise | F12: Equity | G12: Equity | H12: Premium | P12: Step
E13: Value | F13: Value | G13: Per Share | H13: (Discount) | L13: Terminal Growth Rate | O13: =Input!$F$209 -> 0.015 | P13: 0.005
E14: =Model!$G$277 -> 270962.42 | L14: WACC | O14: =Input!$N$257 -> 0.050865749 | P14: 0.005
D15: 1 | E15: 425996.36 | F15: =E15-$O$15 -> 405609.88 | G15: =F15/$O$16 -> 157.64084 | H15: =G15/$O$17-1 -> 1.1122986 | L15: Net Debt & Other Claims | N15: (at Val. Date) | O15: =Input!$N$196+Input!$N$197+Input!$N$199-Input!$N$198 -> 20386.48
D16: 2 | E16: 270962.42 | F16: =E16-$O$15 -> 250575.94 | G16: =F16/$O$16 -> 97.386683 | H16: =G16/$O$17-1 -> 0.30492674 | L16: Shares Outstanding | N16: (FD mm) | O16: =Input!$F$207 -> 2573
D17: 3 | E17: 163554.22 | F17: =E17-$O$15 -> 143167.74 | G17: =F17/$O$16 -> 55.642339 | H17: =G17/$O$17-1 -> -0.25442397 | L17: Current Stock Price | N17: (CHF/sh) | O17: =Input!$F$208 -> 74.63
D21: Enterprise Value 1 | L21: Equity Value per Share
D23: Terminal Growth Rate | L23: Terminal Growth Rate
C24: =Model!$G$277 -> 270962.42 | D24: =E24-$P$13 -> 0.005 | E24: =F24-$P$13 -> 0.01 | F24: =Input!$F$209 -> 0.015 | G24: =F24+$P$13 -> 0.02 | H24: =G24+$P$13 -> 0.025 | L24: =D24 -> 0.005 | M24: =E24 -> 0.01 | N24: =F24 -> 0.015 | O24: =G24 -> 0.02 | P24: =H24 -> 0.025
B25: WACC | C25: =C26-$P$14 -> 0.040865749 | D25: 280829.01 | E25: 319714.32 | F25: 373633.14 | G25: 453392.79 | H25: 583424.04 | J25: WACC | K25: =C25 -> 0.040865749 | L25: =D38/$O$16 -> 101.22135 | M25: =E38/$O$16 -> 116.33418 | N25: =F38/$O$16 -> 137.2898 | O25: =G38/$O$16 -> 168.2885 | P25: =H38/$O$16 -> 218.82533
C26: =C27-$P$14 -> 0.045865749 | D26: 247025.88 | E26: 275837.8 | F26: 313984.33 | G26: 366878.74 | H26: 445123.03 | K26: =C26 -> 0.045865749 | L26: =D39/$O$16 -> 88.083714 | M26: =E39/$O$16 -> 99.28151 | N26: =F39/$O$16 -> 114.10721 | O26: =G39/$O$16 -> 134.6647 | P26: =H39/$O$16 -> 165.07445
C27: =Input!$F$211 -> 0.050865749 | D27: 220591.2 | E27: 242695.3 | F27: 270962.42 | G27: 308387.61 | H27: 360281.83 | K27: =C27 -> 0.050865749 | L27: =D40/$O$16 -> 77.80984 | M27: =E40/$O$16 -> 86.40063 | N27: =F40/$O$16 -> 97.386683 | O27: =G40/$O$16 -> 111.93204 | P27: =H40/$O$16 -> 132.1008
C28: =C27+$P$14 -> 0.055865749 | D28: 199352.09 | E28: 216776.39 | F28: 238464.49 | G28: 266199.6 | H28: 302920.44 | K28: =C28 -> 0.055865749 | L28: =D41/$O$16 -> 69.555231 | M28: =E41/$O$16 -> 76.32721 | N28: =F41/$O$16 -> 84.756318 | O28: =G41/$O$16 -> 95.535608 | P28: =H41/$O$16 -> 109.80721
C29: =C28+$P$14 -> 0.060865749 | D29: 181913.56 | E29: 195950.93 | F29: 213048.83 | G29: 234330.65 | H29: 261546.22 | K29: =C29 -> 0.060865749 | L29: =D42/$O$16 -> 62.777721 | M29: =E42/$O$16 -> 68.233364 | N29: =F42/$O$16 -> 74.878488 | O29: =G42/$O$16 -> 83.149699 | P29: =H42/$O$16 -> 93.727067
D34: Equity Value | L34: Premium (Discount) to Stock Price
D36: Terminal Growth Rate | L36: Terminal Growth Rate
D37: =D24 -> 0.005 | E37: =E24 -> 0.01 | F37: =F24 -> 0.015 | G37: =G24 -> 0.02 | H37: =H24 -> 0.025 | L37: =D37 -> 0.005 | M37: =E37 -> 0.01 | N37: =F37 -> 0.015 | O37: =G37 -> 0.02 | P37: =H37 -> 0.025
B38: WACC | C38: =C25 -> 0.040865749 | D38: =D25-$O$15 -> 260442.53 | E38: =E25-$O$15 -> 299327.84 | F38: =F25-$O$15 -> 353246.66 | G38: =G25-$O$15 -> 433006.31 | H38: =H25-$O$15 -> 563037.56 | J38: WACC | K38: =C38 -> 0.040865749 | L38: =L25/$O$17-1 -> 0.35630909 | M38: =M25/$O$17-1 -> 0.55881249 | N38: =N25/$O$17-1 -> 0.83960608 | O38: =O25/$O$17-1 -> 1.2549712 | P38: =P25/$O$17-1 -> 1.9321362
C39: =C26 -> 0.045865749 | D39: =D26-$O$15 -> 226639.4 | E39: =E26-$O$15 -> 255451.32 | F39: =F26-$O$15 -> 293597.85 | G39: =G26-$O$15 -> 346492.26 | H39: =H26-$O$15 -> 424736.55 | K39: =C39 -> 0.045865749 | L39: =L26/$O$17-1 -> 0.18027219 | M39: =M26/$O$17-1 -> 0.33031635 | N39: =N26/$O$17-1 -> 0.52897238 | O39: =O26/$O$17-1 -> 0.80443114 | P39: =P26/$O$17-1 -> 1.2119047
C40: =C27 -> 0.050865749 | D40: =D27-$O$15 -> 200204.72 | E40: =E27-$O$15 -> 222308.82 | F40: =F27-$O$15 -> 250575.94 | G40: =G27-$O$15 -> 288001.13 | H40: =H27-$O$15 -> 339895.35 | K40: =C40 -> 0.050865749 | L40: =L27/$O$17-1 -> 0.042608071 | M40: =M27/$O$17-1 -> 0.15771982 | N40: =N27/$O$17-1 -> 0.30492674 | O40: =O27/$O$17-1 -> 0.49982631 | P40: =P27/$O$17-1 -> 0.77007633
C41: =C28 -> 0.055865749 | D41: =D28-$O$15 -> 178965.61 | E41: =E28-$O$15 -> 196389.91 | F41: =F28-$O$15 -> 218078.01 | G41: =G28-$O$15 -> 245813.12 | H41: =H28-$O$15 -> 282533.96 | K41: =C41 -> 0.055865749 | L41: =L28/$O$17-1 -> -0.067999045 | M41: =M28/$O$17-1 -> 0.022741663 | N41: =N28/$O$17-1 -> 0.13568696 | O41: =O28/$O$17-1 -> 0.28012338 | P41: =P28/$O$17-1 -> 0.47135486
C42: =C29 -> 0.060865749 | D42: =D29-$O$15 -> 161527.08 | E42: =E29-$O$15 -> 175564.45 | F42: =F29-$O$15 -> 192662.35 | G42: =G29-$O$15 -> 213944.17 | H42: =H29-$O$15 -> 241159.74 | K42: =C42 -> 0.060865749 | L42: =L29/$O$17-1 -> -0.15881386 | M42: =M29/$O$17-1 -> -0.085711318 | N42: =N29/$O$17-1 -> 0.0033296025 | O42: =O29/$O$17-1 -> 0.11415917 | P42: =P29/$O$17-1 -> 0.25588995
P44: These tables require the workbook calculation to be set to automatic to update.
B48: Dashboard: Multiple Method
B50: =Input!$B$8 -> All figures in CHF millions unless stated
B51: =CONCATENATE("Model Running: ",INDEX(Input!$B$12:$B$14,Input!$D$6)," Drivers") -> Model Running: Base Case Drivers
D54: Main Outputs 1 | L54: Selected Inputs
E56: Enterprise | F56: Equity | G56: Equity | H56: Premium | P56: Step
E57: Value | F57: Value | G57: Per Share | H57: (Discount) | L57: Terminal Multiple | O57: =Input!$F$210 -> 13.5 | P57: 0.5
E58: =Model!$G$325 -> 232364.58 | L58: WACC | O58: =Input!$N$257 -> 0.050865749 | P58: 0.005
D59: 1 | E59: 303567.82 | F59: =E59-$O$59 -> 283181.34 | G59: =F59/$O$60 -> 110.05882 | H59: =G59/$O$61-1 -> 0.47472625 | L59: Net Debt & Other Claims | N59: (at Val. Date) | O59: =Input!$N$196+Input!$N$197+Input!$N$199-Input!$N$198 -> 20386.48
D60: 2 | E60: 232364.58 | F60: =E60-$O$59 -> 211978.1 | G60: =F60/$O$60 -> 82.385579 | H60: =G60/$O$61-1 -> 0.1039204 | L60: Shares Outstanding | N60: (FD mm) | O60: =Input!$F$207 -> 2573
D61: 3 | E61: 168418.31 | F61: =E61-$O$59 -> 148031.83 | G61: =F61/$O$60 -> 57.532777 | H61: =G61/$O$61-1 -> -0.22909317 | L61: Current Stock Price | N61: (CHF/sh) | O61: =Input!$F$208 -> 74.63
D65: Enterprise Value 1 | L65: Equity Value per Share
D67: Terminal Multiple | L67: Terminal Multiple
C68: =Model!$G$325 -> 232364.58 | D68: =E68-$P$57 -> 12.5 | E68: =F68-$P$57 -> 13 | F68: =Input!$F$210 -> 13.5 | G68: =F68+$P$57 -> 14 | H68: =G68+$P$57 -> 14.5 | L68: =D68 -> 12.5 | M68: =E68 -> 13 | N68: =F68 -> 13.5 | O68: =G68 -> 14 | P68: =H68 -> 14.5
B69: WACC | C69: =C70-$P$58 -> 0.040865749 | D69: 229165.17 | E69: 236369.56 | F69: 243573.95 | G69: 250778.33 | H69: 257982.72 | J69: WACC | K69: =C69 -> 0.040865749 | L69: =D82/$O$60 -> 81.142127 | M69: =E82/$O$60 -> 83.942122 | N69: =F82/$O$60 -> 86.742116 | O69: =G82/$O$60 -> 89.542111 | P69: =H82/$O$60 -> 92.342105
C70: =C71-$P$58 -> 0.045865749 | D70: 223851.22 | E70: 230868.11 | F70: 237884.99 | G70: 244901.88 | H70: 251918.77 | K70: =C70 -> 0.045865749 | L70: =D83/$O$60 -> 79.076851 | M70: =E83/$O$60 -> 81.803974 | N70: =F83/$O$60 -> 84.531097 | O70: =G83/$O$60 -> 87.25822 | P70: =H83/$O$60 -> 89.985343
C71: =Input!$F$211 -> 0.050865749 | D71: 218694.32 | E71: 225529.45 | F71: 232364.58 | G71: 239199.7 | H71: 246034.83 | K71: =C71 -> 0.050865749 | L71: =D84/$O$60 -> 77.072615 | M71: =E84/$O$60 -> 79.729097 | N71: =F84/$O$60 -> 82.385579 | O71: =G84/$O$60 -> 85.042062 | P71: =H84/$O$60 -> 87.698544
C72: =C71+$P$58 -> 0.055865749 | D72: 213689.05 | E72: 220347.96 | F72: 227006.87 | G72: 233665.78 | H72: 240324.68 | K72: =C72 -> 0.055865749 | L72: =D85/$O$60 -> 75.127311 | M72: =E85/$O$60 -> 77.715305 | N72: =F85/$O$60 -> 80.303299 | O72: =G85/$O$60 -> 82.891292 | P72: =H85/$O$60 -> 85.479286
C73: =C72+$P$58 -> 0.060865749 | D73: 208830.21 | E73: 215318.24 | F73: 221806.27 | G73: 228294.3 | H73: 234782.33 | K73: =C73 -> 0.060865749 | L73: =D86/$O$60 -> 73.238915 | M73: =E86/$O$60 -> 75.760497 | N73: =F86/$O$60 -> 78.282079 | O73: =G86/$O$60 -> 80.803661 | P73: =H86/$O$60 -> 83.325243
D78: Equity Value | L78: Premium (Discount) to Stock Price
D80: Terminal Multiple | L80: Terminal Multiple
D81: =D68 -> 12.5 | E81: =E68 -> 13 | F81: =F68 -> 13.5 | G81: =G68 -> 14 | H81: =H68 -> 14.5 | L81: =D81 -> 12.5 | M81: =E81 -> 13 | N81: =F81 -> 13.5 | O81: =G81 -> 14 | P81: =H81 -> 14.5
B82: WACC | C82: =C69 -> 0.040865749 | D82: =D69-$O$59 -> 208778.69 | E82: =E69-$O$59 -> 215983.08 | F82: =F69-$O$59 -> 223187.46 | G82: =G69-$O$59 -> 230391.85 | H82: =H69-$O$59 -> 237596.24 | J82: WACC | K82: =C82 -> 0.040865749 | L82: =L69/$O$61-1 -> 0.087258843 | M82: =M69/$O$61-1 -> 0.12477719 | N82: =N69/$O$61-1 -> 0.16229554 | O82: =O69/$O$61-1 -> 0.19981389 | P82: =P69/$O$61-1 -> 0.23733224
C83: =C70 -> 0.045865749 | D83: =D70-$O$59 -> 203464.74 | E83: =E70-$O$59 -> 210481.63 | F83: =F70-$O$59 -> 217498.51 | G83: =G70-$O$59 -> 224515.4 | H83: =H70-$O$59 -> 231532.29 | K83: =C83 -> 0.045865749 | L83: =L70/$O$61-1 -> 0.059585302 | M83: =M70/$O$61-1 -> 0.096127216 | N83: =N70/$O$61-1 -> 0.13266913 | O83: =O70/$O$61-1 -> 0.16921104 | P83: =P70/$O$61-1 -> 0.20575296
C84: =C71 -> 0.050865749 | D84: =D71-$O$59 -> 198307.84 | E84: =E71-$O$59 -> 205142.97 | F84: =F71-$O$59 -> 211978.1 | G84: =G71-$O$59 -> 218813.22 | H84: =H71-$O$59 -> 225648.35 | K84: =C84 -> 0.050865749 | L84: =L71/$O$61-1 -> 0.032729664 | M84: =M71/$O$61-1 -> 0.068325032 | N84: =N71/$O$61-1 -> 0.1039204 | O84: =O71/$O$61-1 -> 0.13951577 | P84: =P71/$O$61-1 -> 0.17511113
C85: =C72 -> 0.055865749 | D85: =D72-$O$59 -> 193302.57 | E85: =E72-$O$59 -> 199961.48 | F85: =F72-$O$59 -> 206620.39 | G85: =G72-$O$59 -> 213279.3 | H85: =H72-$O$59 -> 219938.2 | K85: =C85 -> 0.055865749 | L85: =L72/$O$61-1 -> 0.0066636894 | M85: =M72/$O$61-1 -> 0.041341349 | N85: =N72/$O$61-1 -> 0.076019008 | O85: =O72/$O$61-1 -> 0.11069667 | P85: =P72/$O$61-1 -> 0.14537433
C86: =C73 -> 0.060865749 | D86: =D73-$O$59 -> 188443.73 | E86: =E73-$O$59 -> 194931.76 | F86: =F73-$O$59 -> 201419.79 | G86: =G73-$O$59 -> 207907.82 | H86: =H73-$O$59 -> 214395.85 | K86: =C86 -> 0.060865749 | L86: =L73/$O$61-1 -> -0.018639757 | M86: =M73/$O$61-1 -> 0.015148023 | N86: =N73/$O$61-1 -> 0.048935804 | O86: =O73/$O$61-1 -> 0.082723584 | P86: =P73/$O$61-1 -> 0.11651136
P88: These tables require the workbook calculation to be set to automatic to update.

Sheet Input
B2: ="Nestlé S.A. | CHF millions | Scenario: "&INDEX(Input!$B$12:$B$14,Input!$D$6) -> Nestlé S.A. | CHF millions | Scenario: Base Case | I2: =F173 -> 2026 | J2: =I2+1 -> 2027 | K2: =J2+1 -> 2028 | L2: =K2+1 -> 2029 | M2: =L2+1 -> 2030 | N2: Term | P2: Justification / Basis of assumption
B4: Growth & Margin Drivers
C6: Model Running: | D6: =Output!$D$8 -> 2
B8: All figures in CHF millions unless stated | I8: =I$2 -> 2026 | J8: =J$2 -> 2027 | K8: =K$2 -> 2028 | L8: =L$2 -> 2029 | M8: =M$2 -> 2030 | N8: =N$2 -> Term
B10: Sales growth, % YoY | I10: =INDEX(I12:I14,$D$6) -> 0.005 | J10: =INDEX(J12:J14,$D$6) -> 0.015 | K10: =INDEX(K12:K14,$D$6) -> 0.005 | L10: =INDEX(L12:L14,$D$6) -> 0.02 | M10: =INDEX(M12:M14,$D$6) -> 0.028 | N10: =INDEX(N12:N14,$D$6) -> 0.015
B12: Best Case | I12: 0.025 | J12: 0.035 | K12: 0.04 | L12: 0.045 | M12: 0.05 | N12: 0.02 | P12: Best Case: reported sales growth converges toward the organic growth guidance (3–4% for 2026) as the c.3% FX headwind from a strong CHF and the 2025–26 portfolio exits (Waters JV, VMS, ice cream) roll off, building to 5% by 2030. Source: Nestlé H1 2026 results and FY2026 guidance. | Term (N): 2.0% perpetual growth in CHF – upper end of the long-run CHF nominal range (c.1% inflation + c.1% real volume).
B13: Base Case | I13: 0.005 | J13: 0.015 | K13: 0.005 | L13: 0.02 | M13: 0.028 | N13: 0.015 | P13: Base Case: 2026 +0.5% = organic growth guidance of 3–4% less a c.3% FX headwind at spot rates (H1 2026 guidance); 2027 +1.5% as FX normalises; 2028 slows under an assumed mild global slowdown; 2029–30 returns toward the organic trend (2.0–2.8%). The Waters deconsolidation into the Peranel JV (FY2025 sales CHF 3.5bn, closing H1 2027) is not modelled separately and would lower 2027 reported sales by up to c.4pp. | Term (N): 1.5% perpetual growth in CHF = c.0.5–1.0% long-run CHF inflation (SNB target 0–2%) plus c.1% real volume, net of the structural drag from CHF appreciation on translated sales. Feeds the Gordon-growth terminal value via cell F209.
B14: Worst Case | I14: -0.015 | J14: -0.01 | K14: -0.055 | L14: -0.03 | M14: 0.005 | N14: 0.01 | P14: Worst Case: a demand and macro shock in 2028–29 (–5.5% and –3.0%), sized on the roughly ten-year cadence of past global stress events (1998, 2008, 2020). Consumer staples are assumed to decline less than cyclical sectors, with stabilisation in 2030. | Term (N): 1.0% – persistent CHF strength and a low-volume staples environment.
B17: Other revenue, % of sales | I17: =INDEX(I19:I21,$D$6) -> 0.0042 | J17: =INDEX(J19:J21,$D$6) -> 0.0043 | K17: =INDEX(K19:K21,$D$6) -> 0.0043 | L17: =INDEX(L19:L21,$D$6) -> 0.0044 | M17: =INDEX(M19:M21,$D$6) -> 0.0045 | N17: =INDEX(N19:N21,$D$6) -> 0.0045
B19: Best Case | I19: 0.0042 | J19: 0.0044 | K19: 0.0046 | L19: 0.0048 | M19: 0.005 | N19: =M19 -> 0.005 | P19: Other revenue (royalty and licensing-type income) as % of sales. FY23–25 range 0.38–0.44%; the Best Case trends gently upward with stronger sales momentum. | Term (N), all scenarios: held at the 2030 ratio so that margins are stable in perpetuity.
B20: Base Case | I20: 0.0042 | J20: 0.0043 | K20: 0.0043 | L20: 0.0044 | M20: 0.0045 | N20: =M20 -> 0.0045 | P20: Held at 0.42–0.45% of sales, close to the FY2025 level (0.44%) and slightly above the FY23–25 average (0.41%).
B21: Worst Case | I21: 0.0038 | J21: 0.0035 | K21: 0.003 | L21: 0.0033 | M21: 0.0036 | N21: =M21 -> 0.0036 | P21: Compressed during the 2028–29 downturn on lower royalty and licensing volumes, recovering partially by 2030.
B24: COGS | I24: =INDEX(I26:I28,$D$6) -> 0.00090441985 | J24: =INDEX(J26:J28,$D$6) -> 0.018740719 | K24: =INDEX(K26:K28,$D$6) -> 0.017768006 | L24: =INDEX(L26:L28,$D$6) -> 0.018371853 | M24: =INDEX(M26:M28,$D$6) -> 0.025530179 | N24: =INDEX(N26:N28,$D$6) -> 0.015
B26: Best Case | I26: 0.015082154 | J26: 0.028739312 | K26: 0.030626201 | L26: 0.034982241 | M26: 0.035676958 | N26: =N12 -> 0.02 | P26: COGS is projected as a growth rate on the prior year and is the main lever for the gross-margin path. In the Best Case COGS grows slower than sales, supported by 'Fuel for Growth' procurement savings (CHF 3bn gross savings target by end-2027) and easing cocoa and coffee costs. | Term (N), all scenarios: COGS grows at the terminal sales growth rate, freezing the 2030 gross margin in perpetuity (no margin drift in the terminal year).
B27: Base Case | I27: 0.00090441985 | J27: 0.018740719 | K27: 0.017768006 | L27: 0.018371853 | M27: 0.025530179 | N27: =N13 -> 0.015 | P27: Calibrated so that the EBITDA margin moves from 17.5% (2026) to 18.3% (2030), recovering above the FY2025 level (17.7%) but staying below FY2024 (20.0%), as coffee and cocoa cost relief and 'Fuel for Growth' savings are partly reinvested.
B28: Worst Case | I28: -0.010364991 | J28: 0.00033932446 | K28: -0.052572217 | L28: -0.0018388641 | M28: -5.4555294e-05 | N28: =N14 -> 0.01 | P28: In the 2028 shock year COGS falls less than sales (–5.3% vs –5.5%): input costs and FX stay elevated while volumes soften, the typical operating-deleverage pattern for consumer staples in a downturn.
B31: Distribution expenses | I31: =INDEX(I33:I35,$D$6) -> 0.081 | J31: =INDEX(J33:J35,$D$6) -> 0.0805 | K31: =INDEX(K33:K35,$D$6) -> 0.08 | L31: =INDEX(L33:L35,$D$6) -> 0.0795 | M31: =INDEX(M33:M35,$D$6) -> 0.079 | N31: =INDEX(N33:N35,$D$6) -> 0.079
B33: Best Case | I33: 0.08 | J33: 0.0785 | K33: 0.077 | L33: 0.0755 | M33: 0.074 | N33: =M33 -> 0.074 | P33: Distribution costs as % of sales continue the FY23–25 decline (8.3% to 8.2%) through logistics and network efficiencies, reaching 7.4% by 2030. | Term (N), all scenarios: held at the 2030 ratio (steady state).
B34: Base Case | I34: 0.081 | J34: 0.0805 | K34: 0.08 | L34: 0.0795 | M34: 0.079 | N34: =M34 -> 0.079 | P34: Gradual improvement from the FY2025 level (8.2%) to 7.9% by 2030 from ongoing logistics and network efficiency.
B35: Worst Case | I35: 0.083 | J35: 0.085 | K35: 0.09 | L35: 0.087 | M35: 0.084 | N35: =M35 -> 0.084 | P35: Rises to 9.0% in 2028 as freight costs increase and lower volumes absorb fixed distribution costs, then partially normalises.
B38: Marketing & administration expenses | I38: =INDEX(I40:I42,$D$6) -> 0.2 | J38: =INDEX(J40:J42,$D$6) -> 0.201 | K38: =INDEX(K40:K42,$D$6) -> 0.201 | L38: =INDEX(L40:L42,$D$6) -> 0.202 | M38: =INDEX(M40:M42,$D$6) -> 0.203 | N38: =INDEX(N40:N42,$D$6) -> 0.203
B40: Best Case | I40: 0.201 | J40: 0.203 | K40: 0.205 | L40: 0.206 | M40: 0.208 | N40: =M40 -> 0.208 | P40: Includes a deliberate step-up in advertising and promotion, in line with management's stated intent to lift A&P toward c.9% of sales, within a Marketing & Administration total that has run at 19–20% of sales; reaches 20.8% by 2030. | Term (N), all scenarios: held at the 2030 ratio (steady state).
B41: Base Case | I41: 0.2 | J41: 0.201 | K41: 0.201 | L41: 0.202 | M41: 0.203 | N41: =M41 -> 0.203 | P41: Modest reinvestment from 20.0% to 20.3% of sales, broadly in line with the FY2025 level (20.0%).
B42: Worst Case | I42: 0.197 | J42: 0.202 | K42: 0.213 | L42: 0.205 | M42: 0.199 | N42: =M42 -> 0.199 | P42: Rises to 21.3% in 2028: overheads are less flexible than marketing spend, so the ratio increases even as A&P is reduced; it partially normalises thereafter.
B45: Other trading income | I45: =INDEX(I47:I49,$D$6) -> 0.0014 | J45: =INDEX(J47:J49,$D$6) -> 0.0014 | K45: =INDEX(K47:K49,$D$6) -> 0.0013 | L45: =INDEX(L47:L49,$D$6) -> 0.0014 | M45: =INDEX(M47:M49,$D$6) -> 0.0014 | N45: =INDEX(N47:N49,$D$6) -> 0.0014
B47: Best Case | I47: 0.0016 | J47: 0.0017 | K47: 0.0017 | L47: 0.0018 | M47: 0.0018 | N47: =M47 -> 0.0018 | P47: Small and historically volatile line (FY23–25: 0.14–0.15% of sales); the Best Case is slightly higher. | Term (N), all scenarios: held at the 2030 ratio (steady state).
B48: Base Case | I48: 0.0014 | J48: 0.0014 | K48: 0.0013 | L48: 0.0014 | M48: 0.0014 | N48: =M48 -> 0.0014 | P48: Held near the FY23–25 average.
B49: Worst Case | I49: 0.0008 | J49: 0.0006 | K49: 0.0005 | L49: 0.0007 | M49: 0.0009 | N49: =M49 -> 0.0009 | P49: Compressed during the 2028–29 downturn.
B52: Other trading expenses | I52: =INDEX(I54:I56,$D$6) -> 0.024 | J52: =INDEX(J54:J56,$D$6) -> 0.019 | K52: =INDEX(K54:K56,$D$6) -> 0.015 | L52: =INDEX(L54:L56,$D$6) -> 0.0115 | M52: =INDEX(M54:M56,$D$6) -> 0.0095 | N52: =INDEX(N54:N56,$D$6) -> 0.0095
B54: Best Case | I54: 0.022 | J54: 0.017 | K54: 0.013 | L54: 0.01 | M54: 0.0085 | N54: =M54 -> 0.0085 | P54: Elevated in 2026–27 by 'Fuel for Growth' restructuring and impairment-type charges (c.16,000 role reductions by end-2027, announced in Q4 2025), fading from 2028 as the programme completes; the Best Case assumes faster execution. | Term (N): Best and Base held at the 2030 ratio, by which point the restructuring programme is complete.
B55: Base Case | I55: 0.024 | J55: 0.019 | K55: 0.015 | L55: 0.0115 | M55: 0.0095 | N55: =M55 -> 0.0095 | P55: H1 2026 other trading expenses ran at 1.9% of sales (restructuring and net other trading items CHF 0.8bn vs CHF 0.4bn in H1 2025) as 'Fuel for Growth' restructuring accelerated; 2.4% for the full year allows for H2 phasing, declining to 0.95% of sales by 2030 as the programme completes.
B56: Worst Case | I56: 0.027 | J56: 0.025 | K56: 0.034 | L56: 0.021 | M56: 0.016 | N56: 0.012 | P56: Adds further impairment and restructuring charges in the 2028 shock year (3.4% of sales) on top of the ongoing programme, before receding. | Term (N): normalised to 1.2% – the 2030 ratio (1.6%) still carries downturn-related charges, and one-off costs should not be capitalised into perpetuity.
B59: Other operating income | I59: =INDEX(I61:I63,$D$6) -> 0.003 | J59: =INDEX(J61:J63,$D$6) -> 0.0028 | K59: =INDEX(K61:K63,$D$6) -> 0.0027 | L59: =INDEX(L61:L63,$D$6) -> 0.0028 | M59: =INDEX(M61:M63,$D$6) -> 0.0028 | N59: =INDEX(N61:N63,$D$6) -> 0.0028
B61: Best Case | I61: 0.0035 | J61: 0.0035 | K61: 0.0035 | L61: 0.0034 | M61: 0.0034 | N61: =M61 -> 0.0034 | P61: Historically volatile, disposal-gain-type line (FY23–25: 0.28–0.52% of sales); the Best Case assumes slightly more portfolio gains. | Term (N), all scenarios: held at the 2030 ratio (steady state).
B62: Base Case | I62: 0.003 | J62: 0.0028 | K62: 0.0027 | L62: 0.0028 | M62: 0.0028 | N62: =M62 -> 0.0028 | P62: Held near the FY2025 level (0.28% of sales), below the FY23–25 average (0.37%), which included higher disposal gains in 2024.
B63: Worst Case | I63: 0.0015 | J63: 0.0012 | K63: 0.001 | L63: 0.0012 | M63: 0.0015 | N63: =M63 -> 0.0015 | P63: Compressed in the downturn as fewer disposal gains are realised.
B66: Other operating expenses | I66: =INDEX(I68:I70,$D$6) -> 0.006 | J66: =INDEX(J68:J70,$D$6) -> 0.0055 | K66: =INDEX(K68:K70,$D$6) -> 0.0052 | L66: =INDEX(L68:L70,$D$6) -> 0.005 | M66: =INDEX(M68:M70,$D$6) -> 0.0048 | N66: =INDEX(N68:N70,$D$6) -> 0.0048
B68: Best Case | I68: 0.005 | J68: 0.0045 | K68: 0.0042 | L68: 0.004 | M68: 0.0038 | N68: =M68 -> 0.0038 | P68: Historically 0.42–0.81% of sales (FY23–25); the Best Case trends lower. | Term (N): Best and Base held at the 2030 ratio.
B69: Base Case | I69: 0.006 | J69: 0.0055 | K69: 0.0052 | L69: 0.005 | M69: 0.0048 | N69: =M69 -> 0.0048 | P69: 0.60% of sales in 2026 easing to 0.48% by 2030, below FY2025 (0.73%, incl. infant-formula inventory write-offs). Excludes the CHF 1.3bn one-off non-cash write-down on assets held for sale booked in H1 2026, so reported 2026 net profit will be lower than modelled; the non-cash share of this line is added back in the cash flow via row 168.
B70: Worst Case | I70: 0.0085 | J70: 0.01 | K70: 0.0135 | L70: 0.0105 | M70: 0.0085 | N70: 0.007 | P70: Rises to 1.35% of sales in the 2028 trough, then recedes. | Term (N): normalised to 0.7% (vs 0.85% in 2030) for the same reason as other trading expenses – downturn charges are not carried into perpetuity.
B73: Income from associates & JV, growth % YoY | I73: =INDEX(I75:I77,$D$6) -> 0.03 | J73: =INDEX(J75:J77,$D$6) -> 0.04 | K73: =INDEX(K75:K77,$D$6) -> 0.04 | L73: =INDEX(L75:L77,$D$6) -> 0.05 | M73: =INDEX(M75:M77,$D$6) -> 0.05 | N73: =INDEX(N75:N77,$D$6) -> 0.015
B75: Best Case | I75: 0.06 | J75: 0.06 | K75: 0.07 | L75: 0.07 | M75: 0.07 | N75: =N12 -> 0.02 | P75: Year-on-year growth in income from associates & JV (mainly the L'Oréal stake); the Best Case assumes 6–7% growth. | Term (N), all scenarios: grows at terminal sales growth. Note: income from associates & JV is excluded from EBIT and UFCF; the value of the L'Oréal stake is captured at market value in the equity bridge (rows 207–211).
B76: Base Case | I76: 0.03 | J76: 0.04 | K76: 0.04 | L76: 0.05 | M76: 0.05 | N76: =N13 -> 0.015 | P76: Modest recovery (3–5% a year) after the FY2025 decline (–8.5%).
B77: Worst Case | I77: -0.1 | J77: -0.05 | K77: -0.15 | L77: -0.05 | M77: 0.03 | N77: =N14 -> 0.01 | P77: Declines with the equity-market and consumer downturn in 2026–29, then recovers slightly in 2030.
B81: Working Capital Drivers
B83: All figures in CHF millions unless stated | I83: =I$2 -> 2026 | J83: =J$2 -> 2027 | K83: =K$2 -> 2028 | L83: =L$2 -> 2029 | M83: =M$2 -> 2030 | N83: =N$2 -> Term
B86: DSO | F86: (Days) | I86: =INDEX(I88:I90,$D$6) -> 43 | J86: =INDEX(J88:J90,$D$6) -> 43 | K86: =INDEX(K88:K90,$D$6) -> 42.5 | L86: =INDEX(L88:L90,$D$6) -> 42 | M86: =INDEX(M88:M90,$D$6) -> 42 | N86: =INDEX(N88:N90,$D$6) -> 42
B88: Best Case | I88: 42.5 | J88: 42 | K88: 41.5 | L88: 41 | M88: 40.5 | N88: =M88 -> 40.5 | P88: Best Case: DSO improves c.0.5 day a year to 40.5 days by 2030 as receivables processing moves into expanded shared services with tighter escalation and governance (FY2025 strategic update). | Term (N), all scenarios: held at the 2030 level, so net working capital grows in line with sales in perpetuity.
B89: Base Case | I89: 43 | J89: 43 | K89: 42.5 | L89: 42 | M89: 42 | N89: =M89 -> 42 | P89: Base Case: starts from the FY2025 actual (43.1 days) and eases to 42 days by 2030, supported by tighter receivables governance and the expansion of shared services (FY2023–25 range: 43–45 days).
B90: Worst Case | I90: 45 | J90: 46 | K90: 48 | L90: 47 | M90: 46 | N90: =M90 -> 46 | P90: Worst Case: customers and distributors stretch payment terms in the 2028 downturn (48 days, above the FY2024 peak of 45 days), normalising partially to 46 days by 2030.
B93: DSI | F93: (Days) | I93: =INDEX(I95:I97,$D$6) -> 93 | J93: =INDEX(J95:J97,$D$6) -> 91 | K93: =INDEX(K95:K97,$D$6) -> 89 | L93: =INDEX(L95:L97,$D$6) -> 88 | M93: =INDEX(M95:M97,$D$6) -> 87 | N93: =INDEX(N95:N97,$D$6) -> 87
B95: Best Case | I95: 92 | J95: 88 | K95: 86 | L95: 85 | M95: 84 | N95: =M95 -> 84 | P95: Best Case: inventory days fall back below the FY2023 level (86 days) to 84 days by 2030 as lower coffee and cocoa costs flow through and data-driven inventory resets (finished goods, raw & packaging, spare parts) are fully embedded. | Term (N), all scenarios: held at the 2030 level.
B96: Base Case | I96: 93 | J96: 91 | K96: 89 | L96: 88 | M96: 87 | N96: =M96 -> 87 | P96: Base Case: gradual normalisation from the commodity-inflated FY2024–25 level (96–99 days) to 87 days by 2030, close to FY2023 (86 days); 2026 (93 days) reflects the working-capital improvement reported in H1 2026, partly from lower coffee and cocoa costs.
B97: Worst Case | I97: 98 | J97: 100 | K97: 104 | L97: 100 | M97: 97 | N97: =M97 -> 97 | P97: Worst Case: renewed commodity inflation combined with a volume shortfall builds inventory to 104 days in 2028 (above the FY2024 peak of 99 days), before partial correction to 97 days by 2030.
B100: DPO | F100: (Days) | I100: =INDEX(I102:I104,$D$6) -> 150 | J100: =INDEX(J102:J104,$D$6) -> 150 | K100: =INDEX(K102:K104,$D$6) -> 150 | L100: =INDEX(L102:L104,$D$6) -> 150 | M100: =INDEX(M102:M104,$D$6) -> 150 | N100: =INDEX(N102:N104,$D$6) -> 150
B102: Best Case | I102: 152 | J102: 153 | K102: 154 | L102: 155 | M102: 155 | N102: =M102 -> 155 | P102: Best Case: further extension of supplier terms and supply-chain-finance coverage, rising to 155 days by 2030 (the previous Base Case path). | Term (N), all scenarios: held at the 2030 level.
B103: Base Case | I103: 150 | J103: 150 | K103: 150 | L103: 150 | M103: 150 | N103: =M103 -> 150 | P103: Base Case: held flat at 150 days, the FY2025 level and close to the FY2023–25 average (151 days). Payable days are already high for the sector; lower commodity prices reduce payable balances, and further extension would rely on supplier-finance programmes.
B104: Worst Case | I104: 148 | J104: 145 | K104: 140 | L104: 142 | M104: 144 | N104: =M104 -> 144 | P104: Worst Case: suppliers tighten terms and lower purchase volumes reduce payables in the downturn, falling to 140 days in 2028 (FY2023 level: 139 days) and recovering to 144 days by 2030.
B107: Prepayments | F107: (Days) | I107: 2 | J107: 2 | K107: 2 | L107: 2 | M107: 2 | N107: =M107 -> 2 | P107: prepayments are c.CHF 0.5bn (c.2 days of sales, stable over FY2023–25); scenario impact on cash is immaterial, so a single input applies to all scenarios. | Term (N): held at the 2030 level.
B108: Accruals | F108: (Days) | I108: 40 | J108: 40 | K108: 40 | L108: 41 | M108: 41 | N108: =M108 -> 41 | P108: accruals held at 40–41 days of COGS, in line with FY2024–25 (41–42 days); a single input applies to all scenarios. | Term (N): held at the 2030 level.
B111: Capex, D&A & Fixed Asset Drivers
B113: All figures in CHF millions unless stated | I113: =I$2 -> 2026 | J113: =J$2 -> 2027 | K113: =K$2 -> 2028 | L113: =L$2 -> 2029 | M113: =M$2 -> 2030 | N113: =N$2 -> Term
B116: Capex | F116: % Sales | I116: =INDEX(I118:I120,$D$6) -> 0.049 | J116: =INDEX(J118:J120,$D$6) -> 0.048 | K116: =INDEX(K118:K120,$D$6) -> 0.048 | L116: =INDEX(L118:L120,$D$6) -> 0.047 | M116: =INDEX(M118:M120,$D$6) -> 0.047 | N116: =INDEX(N118:N120,$D$6) -> 0.042219178
B118: Best Case | I118: 0.046 | J118: 0.045 | K118: 0.044 | L118: 0.044 | M118: 0.044 | N118: =($N$124+$N$10)*(Model!$M$83+Model!$M$84)/Model!$N$440-$N$123 -> 0.042219178 | P118: Best Case: capex at the lower end of management's 4-5% of sales range (4.4-4.6% on this model's basis), reflecting tighter business-case scrutiny and the end of the 2022-24 capacity build-out; absolute capex still rises with sales. | Term (N), all scenarios: formula-driven steady-state reinvestment – total capex = (D&A rate + terminal growth) × 2030 closing PP&E and intangibles, less intangible capex (N123). This lets the asset base grow at the terminal growth rate (c.1.2x D&A) instead of the simplistic 'capex = D&A', which would be inconsistent with positive growth. The formula adapts automatically to the running scenario, so it is identical in all three rows.
B119: Base Case | I119: 0.049 | J119: 0.048 | K119: 0.048 | L119: 0.047 | M119: 0.047 | N119: =($N$124+$N$10)*(Model!$M$83+Model!$M$84)/Model!$N$440-$N$123 -> 0.042219178 | P119: Base Case: 4.9% of sales in 2026 easing to 4.7% by 2030. Management guides capex to normalise within 4–5% of sales (FY2025: 4.8% on Nestlé's definition vs 5.1% on this model's cash-flow PP&E basis), and lower capex already supported H1 2026 free cash flow. Source: FY2025 results call (19 Feb 2026); H1 2026 results.
B120: Worst Case | I120: 0.05 | J120: 0.05 | K120: 0.053 | L120: 0.052 | M120: 0.05 | N120: =($N$124+$N$10)*(Model!$M$83+Model!$M$84)/Model!$N$440-$N$123 -> 0.042219178 | P120: Worst Case: absolute capex is sticky (committed projects; safety and quality spend non-negotiable) at c.CHF 4.4-4.8bn while sales fall, lifting the ratio to 5.3% in 2028; trimmed back to 5.0% by 2030.
B123: Expenditure on intangible assets | F123: % Sales | I123: 0.004 | J123: 0.004 | K123: 0.004 | L123: 0.0045 | M123: 0.0045 | N123: =M123 -> 0.0045 | P123: intangible expenditure (mainly IT/software) ran at 0.36–0.53% of sales over FY2023–25 (cash-flow basis) and is immaterial to group cash flow; a single input applies to all scenarios. | Term (N): held at the 2030 ratio; included in the steady-state total capex calibration (row 118–120).
B124: Combined D&A | F124: % Opening | I124: 0.07 | J124: 0.069 | K124: 0.068 | L124: 0.067 | M124: 0.067 | N124: =M124 -> 0.067 | P124: the D&A rate is an accounting estimate on the opening asset base (FY2024–25: 6.9–7.4%). Capex scenarios already flow into D&A through the asset base; a single input applies to all scenarios. | Term (N): held at the 2030 rate.
B125: D&A allocated to PP&E | I125: 0.85 | J125: 0.85 | K125: 0.85 | L125: 0.85 | M125: 0.85 | N125: =M125 -> 0.85 | P125: c.85% of D&A relates to PP&E (incl. right-of-use assets), the remainder to intangibles; a structural split, not scenario-dependent. | Term (N): held at the 2030 split.
B129: Equity & Dividend Drivers
B131: All figures in CHF millions unless stated | I131: =I$2 -> 2026 | J131: =J$2 -> 2027 | K131: =K$2 -> 2028 | L131: =L$2 -> 2029 | M131: =M$2 -> 2030 | N131: =N$2 -> Term
B134: Dividend payout ratio | F134: % Net Profit | I134: =INDEX(I136:I138,$D$6) -> 0.865 | J134: =INDEX(J136:J138,$D$6) -> 0.842 | K134: =INDEX(K136:K138,$D$6) -> 0.859 | L134: =INDEX(L136:L138,$D$6) -> 0.823 | M134: =INDEX(M136:M138,$D$6) -> 0.79 | N134: =INDEX(N136:N138,$D$6) -> 0.79
B136: Best Case | I136: 0.806 | J136: 0.751 | K136: 0.697 | L136: 0.647 | M136: 0.602 | N136: =M136 -> 0.602 | P136: Best Case: dividend per share rises CHF 0.10 a year from 2027 (CHF 3.10 paid in April 2026 = c.CHF 8.0bn cash), funded by stronger profit and cash flow. Payout back-solved from Best Case net profit. | Term (N), all scenarios: held at 2030. Financing items do not affect UFCF; shown for completeness.
B137: Base Case | I137: 0.865 | J137: 0.842 | K137: 0.859 | L137: 0.823 | M137: 0.79 | N137: =M137 -> 0.79 | P137: Base Case: reflects the progressive dividend – CHF 3.10/share paid April 2026 (c.CHF 8.0bn, already paid), then +CHF 0.05/share a year, in line with the FY2025 increase. Payout (79–87% of reported net profit) is back-solved from Base Case net profit and should be re-checked if margin inputs change.
B138: Worst Case | I138: 0.982 | J138: 0.7 | K138: 0.7 | L138: 0.7 | M138: 0.7 | N138: =M138 -> 0.7 | P138: Worst Case: 2026 fixed at the CHF 8.0bn already paid. From 2027 the payout input is set at 70%, so the dividend floor holds the prior-year dividend, capped at 100% of net profit (cell F186).
B141: Treasury share purchases | I141: =INDEX(I143:I145,$D$6) -> 0 | J141: =INDEX(J143:J145,$D$6) -> 0 | K141: =INDEX(K143:K145,$D$6) -> 1000 | L141: =INDEX(L143:L145,$D$6) -> 1500 | M141: =INDEX(M143:M145,$D$6) -> 2000 | N141: =INDEX(N143:N145,$D$6) -> 2000
B143: Best Case | I143: 0 | J143: 1000 | K143: 2500 | L143: 3500 | M143: 4000 | N143: =M143 -> 4000 | P143: Best Case: buybacks resume from 2027 and scale to CHF 4bn a year as leverage reaches the middle of the 2–3x target range (Nestlé bought back CHF 4.7–5.2bn a year in 2023–24). Executed only when prior-year leverage is within the ceiling (F185). | Term (N): held at 2030 (financing item, no impact on UFCF).
B144: Base Case | I144: 0 | J144: 0 | K144: 1000 | L144: 1500 | M144: 2000 | N144: =M144 -> 2000 | P144: Base Case: nil in 2026–27 (no programme in place; management prioritises the dividend and net debt reduction, with buybacks only from excess cash), then CHF 1.0–2.0bn a year. Leverage-gated (F185): Base Case model leverage falls below the 3.0x ceiling in 2029 (c.2.9x), so the first buyback (CHF 2.0bn) is executed in 2030.
B145: Worst Case | I145: 0 | J145: 0 | K145: 0 | L145: 0 | M145: 0 | N145: =M145 -> 0 | P145: Worst Case: no buybacks; all surplus cash goes to protecting the dividend and the balance sheet.
B148: Dividends received from associates & JV | F148: % Opening | I148: =INDEX(I150:I152,$D$6) -> 0.065 | J148: =INDEX(J150:J152,$D$6) -> 0.06 | K148: =INDEX(K150:K152,$D$6) -> 0.06 | L148: =INDEX(L150:L152,$D$6) -> 0.06 | M148: =INDEX(M150:M152,$D$6) -> 0.06 | N148: =INDEX(N150:N152,$D$6) -> 0.06
B150: Best Case | I150: 0.065 | J150: 0.065 | K150: 0.065 | L150: 0.065 | M150: 0.065 | N150: =M150 -> 0.065 | P150: Best Case: 6.5% of the opening balance throughout, supported by a progressive L'Oreal dividend and distributions from the new waters JV (Peranel) once established. | Term (N): held at 2030 (associates' dividends are excluded from UFCF; the stake is valued in the equity bridge).
B151: Base Case | I151: 0.065 | J151: 0.06 | K151: 0.06 | L151: 0.06 | M151: 0.06 | N151: =M151 -> 0.06 | P151: Base Case: ordinary distributions ran at 5.3-5.8% of the opening balance in FY2024-25, excluding the CHF 2.0bn extraordinary Froneri distribution in 2025; the lower 2026 opening base lifts the ratio to c.6%.
B152: Worst Case | I152: 0.06 | J152: 0.05 | K152: 0.045 | L152: 0.045 | M152: 0.05 | N152: =M152 -> 0.05 | P152: Worst Case: 2026 close to Base (main dividends received in H1); associates cut distributions to 4.5-5.0% in the 2027-29 downturn.
B155: Dividends to NCI | F155: % NCI Profit | I155: 0.75 | J155: 0.75 | K155: 0.75 | L155: 0.75 | M155: 0.75 | N155: =M155 -> 0.75 | P155: dividends to NCI are small (c.CHF 0.2bn) and follow subsidiary policy; held at 75% of NCI profit, within the FY2023-25 range (60-108%). | Term (N): held at 2030 (financing item, no impact on UFCF).
B159: Other Inputs: Part 1
B161: All figures in CHF millions unless stated | I161: =I$2 -> 2026 | J161: =J$2 -> 2027 | K161: =K$2 -> 2028 | L161: =L$2 -> 2029 | M161: =M$2 -> 2030 | N161: =N$2 -> Term
B164: Other Annual Inputs
B166: Financial Debt | F166: Increase / (Decrease) | I166: -0.02 | J166: -0.01 | K166: 0 | L166: 0.01 | M166: 0.01 | N166: =M166 -> 0.01 | P166: Year-on-year change in total financial debt: modest deleveraging in 2026–27 (FY2025: –9.0%), stable in 2028 and modest growth from 2029 in line with the business. Any short-term funding need is met by the revolving credit line. The c.CHF 2.8bn Peranel JV proceeds expected in H1 2027 are not modelled and would accelerate deleveraging. | Term (N): held at 2030 (financing item, no impact on UFCF).
B167: Current Portion | F167: % Financial Debt | I167: 0.2 | J167: 0.2 | K167: 0.2 | L167: 0.2 | M167: 0.2 | N167: =M167 -> 0.2 | P167: Share of financial debt maturing within one year, held at 20%: the FY2025 level and the top of the FY2023–25 range (17–20%). Affects only the current/non-current split and liquidity ratios, not cash. | Term (N): held at 2030 (classification only).
B168: Non-cash charges | F168: % Other Exp. | I168: 0.35 | J168: 0.35 | K168: 0.35 | L168: 0.35 | M168: 0.35 | N168: 0 | P168: Share of other trading and other operating expenses that is non-cash (impairments, write-downs), added back in the cash flow and written off against goodwill. Impairments were 27%, 37% and 37% of these expenses in FY2023–25; 35% applied. Restructuring is treated as cash. | Term (N): set to 0% – the terminal year is normalised with no non-cash impairment add-back, so the perpetuity cash flow reflects only recurring cash costs (recurring write-downs effectively represent capital consumed).
C172: Dates | I172: Taxes
C173: First Year of Forecast | E173: (YYYY) | F173: 2026 | I173: Tax Rate | M173: 0.235 | P173: Effective tax rate on profit before tax, associates and JV. 23.5% sits between the underlying rate (22.1% FY2025; 22.3% H1 2026) and the reported rate (24.6% FY2025), allowing for recurring non-deductible items and the OECD Pillar Two 15% minimum tax. Cash taxes come from the tax depreciation schedule; the timing difference is recorded in deferred tax liabilities. | The same rate drives unlevered cash taxes in the UFCF and the after-tax cost of debt in the WACC (cell N246).
C174: Days in Period | E174: (Days) | F174: 365 | I174: First Year Tax Depreciation | M174: 0.15 | P174: Share of current-year capex added to the tax depreciation base in the year of spend (partial-year convention); the full amount enters the base from the following year.
I175: Blended Tax Depreciation Rate | M175: 0.08 | P175: Blended tax depreciation rate on the tax basis (8%), slightly above the book D&A rate (c.7%), reflecting moderately accelerated tax allowances; the resulting timing difference builds a deferred tax liability.
I176: Tax Basis for Assets | M176: 49222 | P176: Opening tax basis of depreciable assets, proxied to the FY2025 net book value of PP&E and intangible assets (CHF 49,222m), as the tax basis is not disclosed. Both PP&E and intangible capex and D&A flow through the tax schedule, consistent with this base.
I177: Tax Losses | M177: 0 | P177: Opening tax loss carryforwards assumed nil, given the Group's consistent consolidated profitability (not disclosed).
C180: Other Single Inputs | I180: Interest Rates
I181: Cash & ST Investment | M181: 0.025 | P181: Interest rate earned on cash and short-term investments, applied to opening balances. Set below the FY2025 implied yield (3.8%; FY2024: 6.1%) to reflect lower CHF and EUR short-term rates.
C182: Non-controlling interests, % of profit | F182: 0.025 | I182: Financial Debt | M182: 0.029 | P182: F182 – NCI share of profit, held near the FY23–25 average (2.4–2.6%). | M182 – Interest rate on opening financial debt (2.9%): FY2025 financial expense equalled 2.9% of opening debt, and Nestlé reports an average cost of net debt of 2.5–2.6% (FY2025, H1 2026); the small cushion covers refinancing of maturing low-coupon debt. | M182 is also the pre-tax cost of debt in the WACC (cell N245), keeping the valuation consistent with the operating model.
C183: R&D Cost | F183: 0.018 | I183: Revolving Credit Line | M183: 0.042 | P183: F183 – R&D cost, held at the FY23–25 average (1.8% of sales). | M183 – Interest rate on the revolving credit line (4.2%), priced at a spread above term debt in line with typical committed-facility pricing.
...

Sheet Model
B2: ="Nestlé S.A. | CHF millions | Scenario: "&INDEX(Input!$B$12:$B$14,Input!$D$6) -> Nestlé S.A. | CHF millions | Scenario: Base Case | F2: =G2-1 -> 2023 | G2: =H2-1 -> 2024 | H2: =I2-1 -> 2025 | I2: =Input!$I$2 -> 2026 | J2: =I2+1 -> 2027 | K2: =J2+1 -> 2028 | L2: =K2+1 -> 2029 | M2: =L2+1 -> 2030 | N2: Term
B4: Growth & Margin Drivers
B6: =Input!$B$8 -> All figures in CHF millions unless stated | F6: =F$2 -> 2023 | G6: =G$2 -> 2024 | H6: =H$2 -> 2025 | I6: =I$2 -> 2026 | J6: =J$2 -> 2027 | K6: =K$2 -> 2028 | L6: =L$2 -> 2029 | M6: =M$2 -> 2030 | N6: =N$2 -> Term
B7: =CONCATENATE("Model Running: ",INDEX(Input!$B$12:$B$14,Input!$D$6)," Drivers") -> Model Running: Base Case Drivers
B9: Sales growth | G9: -0.0176778 | H9: -0.020404142 | I9: =Input!I$10 -> 0.005 | J9: =Input!J$10 -> 0.015 | K9: =Input!K$10 -> 0.005 | L9: =Input!L$10 -> 0.02 | M9: =Input!M$10 -> 0.028 | N9: =Input!N$10 -> 0.015
B10: Other revenue | F10: 0.0037957806 | G10: 0.0040063927 | H10: 0.004413901 | I10: =Input!I$17 -> 0.0042 | J10: =Input!J$17 -> 0.0043 | K10: =Input!K$17 -> 0.0043 | L10: =Input!L$17 -> 0.0044 | M10: =Input!M$17 -> 0.0045 | N10: =Input!N$17 -> 0.0045
B11: Cost of goods sold | G11: -0.032943888 | H11: 0.00049311691 | I11: =Input!I$24 -> 0.00090441985 | J11: =Input!J$24 -> 0.018740719 | K11: =Input!K$24 -> 0.017768006 | L11: =Input!L$24 -> 0.018371853 | M11: =Input!M$24 -> 0.025530179 | N11: =Input!N$24 -> 0.015
B12: Distribution expenses | F12: 0.083496419 | G12: 0.082831622 | H12: 0.081640407 | I12: =Input!I$31 -> 0.081 | J12: =Input!J$31 -> 0.0805 | K12: =Input!K$31 -> 0.08 | L12: =Input!L$31 -> 0.0795 | M12: =Input!M$31 -> 0.079 | N12: =Input!N$31 -> 0.079
B13: Marketing & administration expenses | F13: 0.18870298 | G13: 0.19826171 | H13: 0.19983238 | I13: =Input!I$38 -> 0.2 | J13: =Input!J$38 -> 0.201 | K13: =Input!K$38 -> 0.201 | L13: =Input!L$38 -> 0.202 | M13: =Input!M$38 -> 0.203 | N13: =Input!N$38 -> 0.203
B14: R&D costs | F14: 0.017806835 | G14: 0.018247696 | H14: 0.01802436 | I14: =Input!$F$183 -> 0.018 | J14: =Input!$F$183 -> 0.018 | K14: =Input!$F$183 -> 0.018 | L14: =Input!$F$183 -> 0.018 | M14: =Input!$F$183 -> 0.018 | N14: =Input!$F$183 -> 0.018
B15: Other trading income | F15: 0.0014193854 | G15: 0.0013573571 | H15: 0.0015085484 | I15: =Input!I$45 -> 0.0014 | J15: =Input!J$45 -> 0.0014 | K15: =Input!K$45 -> 0.0013 | L15: =Input!L$45 -> 0.0014 | M15: =Input!M$45 -> 0.0014 | N15: =Input!N$45 -> 0.0014
B16: Other trading expenses | F16: 0.017903611 | G16: 0.013080982 | H16: 0.020661526 | I16: =Input!I$52 -> 0.024 | J16: =Input!J$52 -> 0.019 | K16: =Input!K$52 -> 0.015 | L16: =Input!L$52 -> 0.0115 | M16: =Input!M$52 -> 0.0095 | N16: =Input!N$52 -> 0.0095
B17: Other operating income | F17: 0.00320437 | G17: 0.005188607 | H17: 0.0028271315 | I17: =Input!I$59 -> 0.003 | J17: =Input!J$59 -> 0.0028 | K17: =Input!K$59 -> 0.0027 | L17: =Input!L$59 -> 0.0028 | M17: =Input!M$59 -> 0.0028 | N17: =Input!N$59 -> 0.0028
B18: Other operating expenses | F18: 0.0081184542 | G18: 0.004192482 | H18: 0.0072745558 | I18: =Input!I$66 -> 0.006 | J18: =Input!J$66 -> 0.0055 | K18: =Input!K$66 -> 0.0052 | L18: =Input!L$66 -> 0.005 | M18: =Input!M$66 -> 0.0048 | N18: =Input!N$66 -> 0.0048
B19: Effective tax rate | F19: 0.18216169 | G19: 0.25032102 | H19: 0.24555855 | I19: =Input!$M$173 -> 0.235 | J19: =Input!$M$173 -> 0.235 | K19: =Input!$M$173 -> 0.235 | L19: =Input!$M$173 -> 0.235 | M19: =Input!$M$173 -> 0.235 | N19: =Input!$M$173 -> 0.235
B20: Income from associates & JV | G20: 0.11517857 | H20: -0.084867894 | I20: =Input!I$73 -> 0.03 | J20: =Input!J$73 -> 0.04 | K20: =Input!K$73 -> 0.04 | L20: =Input!L$73 -> 0.05 | M20: =Input!M$73 -> 0.05 | N20: =Input!N$73 -> 0.015
B21: Non-controlling interests | F21: 0.026066557 | G21: 0.025953105 | H21: 0.023881565 | I21: =Input!$F$182 -> 0.025 | J21: =Input!$F$182 -> 0.025 | K21: =Input!$F$182 -> 0.025 | L21: =Input!$F$182 -> 0.025 | M21: =Input!$F$182 -> 0.025 | N21: =Input!$F$182 -> 0.025
B22: Non-cash share of other trading & operating expenses | F22: =IFERROR(F474/-(F447+F451),0) -> 0.26735537 | G22: =IFERROR(G474/-(G447+G451),0) -> 0.36755387 | H22: =IFERROR(H474/-(H447+H451),0) -> 0.3692 | I22: =Input!I$168 -> 0.35 | J22: =Input!J$168 -> 0.35 | K22: =Input!K$168 -> 0.35 | L22: =Input!L$168 -> 0.35 | M22: =Input!M$168 -> 0.35 | N22: =Input!N$168 -> 0
B24: Equity & Dividend Drivers
B26: =Input!$B$8 -> All figures in CHF millions unless stated | F26: =F$2 -> 2023 | G26: =G$2 -> 2024 | H26: =H$2 -> 2025 | I26: =I$2 -> 2026 | J26: =J$2 -> 2027 | K26: =K$2 -> 2028 | L26: =L$2 -> 2029 | M26: =M$2 -> 2030 | N26: =N$2 -> Term
B27: =CONCATENATE("Model Running: ",INDEX(Input!$B$12:$B$14,Input!$D$6)," Drivers") -> Model Running: Base Case Drivers
B29: Dividend payout ratio, % of net profit (parent) | F29: 0.6984566 | G29: 0.71811834 | H29: 0.86892505 | I29: =Input!I$134 -> 0.865 | J29: =Input!J$134 -> 0.842 | K29: =Input!K$134 -> 0.859 | L29: =Input!L$134 -> 0.823 | M29: =Input!M$134 -> 0.79 | N29: =Input!N$134 -> 0.79
B30: Dividends to NCI, % of NCI profit | F30: 1.0766667 | G30: 0.6 | H30: 0.77828054 | I30: =Input!I$155 -> 0.75 | J30: =Input!J$155 -> 0.75 | K30: =Input!K$155 -> 0.75 | L30: =Input!L$155 -> 0.75 | M30: =Input!M$155 -> 0.75 | N30: =Input!N$155 -> 0.75
B31: Treasury share purchases, CHF mm/year | F31: 5234 | G31: 4678 | H31: 213 | I31: =IF((H549+H560+H556-H526)/(H452+H473)>Input!$F$185,0,Input!I$141) -> 0 | J31: =IF((I549+I560+I556-I526)/(I452+I473)>Input!$F$185,0,Input!J$141) -> 0 | K31: =IF((J549+J560+J556-J526)/(J452+J473)>Input!$F$185,0,Input!K$141) -> 0 | L31: =IF((K549+K560+K556-K526)/(K452+K473)>Input!$F$185,0,Input!L$141) -> 0 | M31: =IF((L549+L560+L556-L526)/(L452+L473)>Input!$F$185,0,Input!M$141) -> 2000 | N31: =Input!N$141 -> 2000
B32: Dividends received from associates & JV, % of opening balance | G32: 0.057992054 | H32: 0.19223789 | I32: =Input!I$148 -> 0.065 | J32: =Input!J$148 -> 0.06 | K32: =Input!K$148 -> 0.06 | L32: =Input!L$148 -> 0.06 | M32: =Input!M$148 -> 0.06 | N32: =Input!N$148 -> 0.06
B35: Working Capital Schedule
B37: =Input!$B$8 -> All figures in CHF millions unless stated | F37: =F$2 -> 2023 | G37: =G$2 -> 2024 | H37: =H$2 -> 2025 | I37: =I$2 -> 2026 | J37: =J$2 -> 2027 | K37: =K$2 -> 2028 | L37: =L$2 -> 2029 | M37: =M$2 -> 2030 | N37: =N$2 -> Term
B38: =CONCATENATE("Model Running: ",INDEX(Input!$B$12:$B$14,Input!$D$6)," Drivers") -> Model Running: Base Case Drivers
B40: Days in Period | F40: =Input!$F$174 -> 365 | G40: =Input!$F$174 -> 365 | H40: =Input!$F$174 -> 365 | I40: =Input!$F$174 -> 365 | J40: =Input!$F$174 -> 365 | K40: =Input!$F$174 -> 365 | L40: =Input!$F$174 -> 365 | M40: =Input!$F$174 -> 365 | N40: =Input!$F$174 -> 365
B41: Revenue | F41: =F440 -> 92998 | G41: =G440 -> 91354 | H41: =H440 -> 89490 | I41: =I440 -> 89937.45 | J41: =J440 -> 91286.512 | K41: =K440 -> 91742.944 | L41: =L440 -> 93577.803 | M41: =M440 -> 96197.982 | N41: =N440 -> 97640.951
B42: COGS | F42: =-F442 -> 50328 | G42: =-G442 -> 48670 | H42: =-H442 -> 48694 | I42: =-I442 -> 48738.04 | J42: =-J442 -> 49651.426 | K42: =-K442 -> 50533.633 | L42: =-L442 -> 51462.029 | M42: =-M442 -> 52775.864 | N42: =-N442 -> 53567.502
B44: AMOUNTS PER DAY
B45: Accounts Receivable (Days) | F45: =(F52/F41)*F40 -> 43.153347 | G45: =(G52/G41)*G40 -> 44.952766 | H45: =(H52/H41)*H40 -> 43.074813 | I45: =Input!I86 -> 43 | J45: =Input!J86 -> 43 | K45: =Input!K86 -> 42.5 | L45: =Input!L86 -> 42 | M45: =Input!M86 -> 42 | N45: =Input!N86 -> 42
B46: Inventory (Days) | F46: =(F53/F42)*F40 -> 86.274837 | G46: =(G53/G42)*G40 -> 99.443189 | H46: =(H53/H42)*H40 -> 96.043558 | I46: =Input!I93 -> 93 | J46: =Input!J93 -> 91 | K46: =Input!K93 -> 89 | L46: =Input!L93 -> 88 | M46: =Input!M93 -> 87 | N46: =Input!N93 -> 87
B47: Accounts Payable (Days) | F47: =(F54/F42)*F40 -> 139.27555 | G47: =(G54/G42)*G40 -> 163.5413 | H47: =(H54/H42)*H40 -> 150.0882 | I47: =Input!I100 -> 150 | J47: =Input!J100 -> 150 | K47: =Input!K100 -> 150 | L47: =Input!L100 -> 150 | M47: =Input!M100 -> 150 | N47: =Input!N100 -> 150
B48: Prepayments (Days) | F48: =(F55/F41)*F40 -> 2.0448289 | G48: =(G55/G41)*G40 -> 2.1695273 | H48: =(H55/H41)*H40 -> 1.953682 | I48: =Input!I107 -> 2 | J48: =Input!J107 -> 2 | K48: =Input!K107 -> 2 | L48: =Input!L107 -> 2 | M48: =Input!M107 -> 2 | N48: =Input!N107 -> 2
B49: Accruals (Days) | F49: =(F56/F42)*F40 -> 37.074392 | G49: =(G56/G42)*G40 -> 40.992192 | H49: =(H56/H42)*H40 -> 41.789029 | I49: =Input!I108 -> 40 | J49: =Input!J108 -> 40 | K49: =Input!K108 -> 40 | L49: =Input!L108 -> 41 | M49: =Input!M108 -> 41 | N49: =Input!N108 -> 41
B51: TOTAL AMOUNTS
B52: Accounts Receivable | F52: 10995 | G52: 11251 | H52: 10561 | I52: =(I45/I40)*I41 -> 10595.371 | J52: =(J45/J40)*J41 -> 10754.301 | K52: =(K45/K40)*K41 -> 10682.398 | L52: =(L45/L40)*L41 -> 10767.857 | M52: =(M45/M40)*M41 -> 11069.357 | N52: =(N45/N40)*N41 -> 11235.397
B53: Inventory | F53: 11896 | G53: 13260 | H53: 12813 | I53: =(I46/I40)*I42 -> 12418.185 | J53: =(J46/J40)*J42 -> 12378.849 | K53: =(K46/K40)*K42 -> 12321.899 | L53: =(L46/L40)*L42 -> 12407.284 | M53: =(M46/M40)*M42 -> 12579.452 | N53: =(N46/N40)*N42 -> 12768.144
B54: Accounts Payable | F54: 19204 | G54: 21807 | H54: 20023 | I54: =(I47/I40)*I42 -> 20029.331 | J54: =(J47/J40)*J42 -> 20404.696 | K54: =(K47/K40)*K42 -> 20767.246 | L54: =(L47/L40)*L42 -> 21148.779 | M54: =(M47/M40)*M42 -> 21688.711 | N54: =(N47/N40)*N42 -> 22014.042
B55: Prepayments | F55: 521 | G55: 543 | H55: 479 | I55: =(I48/I40)*I41 -> 492.80795 | J55: =(J48/J40)*J41 -> 500.20006 | K55: =(K48/K40)*K41 -> 502.70106 | L55: =(L48/L40)*L41 -> 512.75509 | M55: =(M48/M40)*M41 -> 527.11223 | N55: =(N48/N40)*N41 -> 535.01891
B56: Accruals | F56: 5112 | G56: 5466 | H56: 5575 | I56: =(I49/I40)*I42 -> 5341.155 | J56: =(J49/J40)*J42 -> 5441.2521 | K56: =(K49/K40)*K42 -> 5537.9323 | L56: =(L49/L40)*L42 -> 5780.6663 | M56: =(M49/M40)*M42 -> 5928.2477 | N56: =(N49/N40)*N42 -> 6017.1714
B59: CASH CHANGES
B60: Accounts Receivable | G60: =F52-G52 -> -256 | H60: =G52-H52 -> 690 | I60: =H52-I52 -> -34.370822 | J60: =I52-J52 -> -158.93056 | K60: =J52-K52 -> 71.903759 | L60: =K52-L52 -> -85.459181 | M60: =L52-M52 -> -301.49999 | N60: =M52-N52 -> -166.04035
B61: Inventory | G61: =F53-G53 -> -1364 | H61: =G53-H53 -> 447 | I61: =H53-I53 -> 394.81451 | J61: =I53-J53 -> 39.33688 | K61: =J53-K53 -> 56.949166 | L61: =K53-L53 -> -85.384261 | M61: =L53-M53 -> -172.16876 | N61: =M53-N53 -> -188.69179
B62: Prepayments | G62: =F55-G55 -> -22 | H62: =G55-H55 -> 64 | I62: =H55-I55 -> -13.807945 | J62: =I55-J55 -> -7.3921192 | K62: =J55-K55 -> -2.5010003 | L62: =K55-L55 -> -10.054021 | M62: =L55-M55 -> -14.357142 | N62: =M55-N55 -> -7.9066834
B63: Accounts Payable | G63: =G54-F54 -> 2603 | H63: =H54-G54 -> -1784 | I63: =I54-H54 -> 6.3314329 | J63: =J54-I54 -> 375.36408 | K63: =K54-J54 -> 362.55074 | L63: =L54-K54 -> 381.53279 | M63: =M54-L54 -> 539.93211 | N63: =N54-M54 -> 325.33067
B64: Accruals | G64: =G56-F56 -> 354 | H64: =H56-G56 -> 109 | I64: =I56-H56 -> -233.84495 | J64: =J56-I56 -> 100.09709 | K64: =K56-J56 -> 96.680198 | L64: =L56-K56 -> 242.73394 | M64: =M56-L56 -> 147.58144 | N64: =N56-M56 -> 88.923716
B65: Cash from Working Capital Items | G65: =G60+G61+G62+G63+G64 -> 1315 | H65: =H60+H61+H62+H63+H64 -> -474 | I65: =I60+I61+I62+I63+I64 -> 119.12223 | J65: =J60+J61+J62+J63+J64 -> 348.47536 | K65: =K60+K61+K62+K63+K64 -> 585.58287 | L65: =L60+L61+L62+L63+L64 -> 443.36926 | M65: =M60+M61+M62+M63+M64 -> 199.48765 | N65: =N60+N61+N62+N63+N64 -> 51.615561
B68: Asset Schedule
B70: =Input!$B$8 -> All figures in CHF millions unless stated | F70: =F$2 -> 2023 | G70: =G$2 -> 2024 | H70: =H$2 -> 2025 | I70: =I$2 -> 2026 | J70: =J$2 -> 2027 | K70: =K$2 -> 2028 | L70: =L$2 -> 2029 | M70: =M$2 -> 2030 | N70: =N$2 -> Term
B71: =CONCATENATE("Model Running: ",INDEX(Input!$B$12:$B$14,Input!$D$6)," Drivers") -> Model Running: Base Case Drivers
B73: Capital Expenditure
B74: Capex, % of sales | F74: =-F490/F440 -> 0.061442182 | G74: =-G490/G440 -> 0.061715962 | H74: =-H490/H440 -> 0.050586658 | I74: =Input!I116 -> 0.049 | J74: =Input!J116 -> 0.048 | K74: =Input!K116 -> 0.048 | L74: =Input!L116 -> 0.047 | M74: =Input!M116 -> 0.047 | N74: =Input!N116 -> 0.042219178
B75: Capital Expenditure — PP&E | F75: =-F440*F74 -> -5714 | G75: =-G440*G74 -> -5638 | H75: =-H440*H74 -> -4527 | I75: =-I440*I74 -> -4406.9351 | J75: =-J440*J74 -> -4381.7526 | K75: =-K440*K74 -> -4403.6613 | L75: =-L440*L74 -> -4398.1568 | M75: =-M440*M74 -> -4521.3051 | N75: =-N440*N74 -> -4122.3207
B77: Intangible capex, % of sales | F77: =-F491/F440 -> 0.0052581776 | G77: =-G491/G440 -> 0.0035575892 | H77: =-H491/H440 -> 0.0042909822 | I77: =Input!I123 -> 0.004 | J77: =Input!J123 -> 0.004 | K77: =Input!K123 -> 0.004 | L77: =Input!L123 -> 0.0045 | M77: =Input!M123 -> 0.0045 | N77: =Input!N123 -> 0.0045
B78: Capital Expenditure — Intangible assets | F78: =-F440*F77 -> -489 | G78: =-G440*G77 -> -325 | H78: =-H440*H77 -> -384 | I78: =-I440*I77 -> -359.7498 | J78: =-J440*J77 -> -365.14605 | K78: =-K440*K77 -> -366.97178 | L78: =-L440*L77 -> -421.10011 | M78: =-M440*M77 -> -432.89092 | N78: =-N440*N77 -> -439.38428
B80: TOTAL DEPRECIATION & AMORTIZATION
B81: Combined D&A rate, % of opening PP&E + intangibles | G81: 0.073564446 | H81: 0.068610602 | I81: =Input!I124 -> 0.07 | J81: =Input!J124 -> 0.069 | K81: =Input!K124 -> 0.068 | L81: =Input!L124 -> 0.067 | M81: =Input!M124 -> 0.067 | N81: =Input!N124 -> 0.067
B82: D&A allocated to PP&E (remainder to intangibles), % | F82: 0.85 | G82: 0.85 | H82: 0.85 | I82: =Input!I125 -> 0.85 | J82: =Input!J125 -> 0.85 | K82: =Input!K125 -> 0.85 | L82: =Input!L125 -> 0.85 | M82: =Input!M125 -> 0.85 | N82: =Input!N125 -> 0.85
B83: Property, plant and equipment | F83: =F97 -> 30467 | G83: =G97 -> 33706 | H83: =H97 -> 32549 | I83: =I97 -> 34027.226 | J83: =J97 -> 35444.623 | K83: =K97 -> 36854.096 | L83: =L97 -> 38231.02 | M83: =M97 -> 39659.058 | N83: =N97 -> 40613.219
B84: Intangible assets | F84: =F103 -> 18225 | G84: =G103 -> 19245 | H84: =H103 -> 16673 | I84: =I103 -> 16515.919 | J84: =J103 -> 16357.943 | K84: =K103 -> 16196.529 | L84: =L103 -> 16084.47 | M84: =M103 -> 15971.49 | N84: =N103 -> 15851.788
B86: Total Depreciation & Amortization | G86: =G81*(F83+F84) -> 3582 | H86: =H81*(G83+G84) -> 3633 | I86: =I81*(H83+H84) -> 3445.54 | J86: =J81*(I83+I84) -> 3487.477 | K86: =K81*(J83+J84) -> 3522.5745 | L86: =L81*(K83+K84) -> 3554.3919 | M86: =M81*(L83+L84) -> 3639.1378 | N86: =N81*(M83+M84) -> 3727.2467
B87: Depreciation — PP&E | G87: =G82*G86 -> 3044.7 | H87: =H82*H86 -> 3088.05 | I87: =I82*I86 -> 2928.709 | J87: =J82*J86 -> 2964.3554 | K87: =K82*K86 -> 2994.1883 | L87: =L82*L86 -> 3021.2331 | M87: =M82*M86 -> 3093.2672 | N87: =N82*N86 -> 3168.1597
B88: Amortization — Intangible assets | G88: =G86-G87 -> 537.3 | H88: =H86-H87 -> 544.95 | I88: =I86-I87 -> 516.831 | J88: =J86-J87 -> 523.12155 | K88: =K86-K87 -> 528.38618 | L88: =L86-L87 -> 533.15878 | M88: =M86-M87 -> 545.87067 | N88: =N86-N87 -> 559.08701
B92: PROPERTY, PLANT & EQUIPMENT
B93: Beginning | G93: =F97 -> 30467 | H93: =G97 -> 33706 | I93: =H97 -> 32549 | J93: =I97 -> 34027.226 | K93: =J97 -> 35444.623 | L93: =K97 -> 36854.096 | M93: =L97 -> 38231.02 | N93: =M97 -> 39659.058
B94: Capital Expenditure | G94: =-G75 -> 5638 | H94: =-H75 -> 4527 | I94: =-I75 -> 4406.9351 | J94: =-J75 -> 4381.7526 | K94: =-K75 -> 4403.6613 | L94: =-L75 -> 4398.1568 | M94: =-M75 -> 4521.3051 | N94: =-N75 -> 4122.3207
B95: Depreciation | G95: =-G87 -> -3044.7 | H95: =-H87 -> -3088.05 | I95: =-I87 -> -2928.709 | J95: =-J87 -> -2964.3554 | K95: =-K87 -> -2994.1883 | L95: =-L87 -> -3021.2331 | M95: =-M87 -> -3093.2672 | N95: =-N87 -> -3168.1597
B96: Other movements (FX, leases, impairments, disposals) | G96: =G537-SUM(G93:G95) -> 645.7 | H96: =H537-SUM(H93:H95) -> -2595.95 | I96: 0 | J96: 0 | K96: 0 | L96: 0 | M96: 0 | N96: 0
B97: Ending | F97: =F537 -> 30467 | G97: =SUM(G93:G96) -> 33706 | H97: =SUM(H93:H96) -> 32549 | I97: =SUM(I93:I96) -> 34027.226 | J97: =SUM(J93:J96) -> 35444.623 | K97: =SUM(K93:K96) -> 36854.096 | L97: =SUM(L93:L96) -> 38231.02 | M97: =SUM(M93:M96) -> 39659.058 | N97: =SUM(N93:N96) -> 40613.219
B98: INTANGIBLE ASSETS
B99: Beginning | G99: =F103 -> 18225 | H99: =G103 -> 19245 | I99: =H103 -> 16673 | J99: =I103 -> 16515.919 | K99: =J103 -> 16357.943 | L99: =K103 -> 16196.529 | M99: =L103 -> 16084.47 | N99: =M103 -> 15971.49
B100: Capital Expenditure | G100: =-G78 -> 325 | H100: =-H78 -> 384 | I100: =-I78 -> 359.7498 | J100: =-J78 -> 365.14605 | K100: =-K78 -> 366.97178 | L100: =-L78 -> 421.10011 | M100: =-M78 -> 432.89092 | N100: =-N78 -> 439.38428
B101: Amortization | G101: =-G88 -> -537.3 | H101: =-H88 -> -544.95 | I101: =-I88 -> -516.831 | J101: =-J88 -> -523.12155 | K101: =-K88 -> -528.38618 | L101: =-L88 -> -533.15878 | M101: =-M88 -> -545.87067 | N101: =-N88 -> -559.08701
B102: Other movements (FX, acquisitions, impairments, disposals) | G102: =G539-SUM(G99:G101) -> 1232.3 | H102: =H539-SUM(H99:H101) -> -2411.05 | I102: 0 | J102: 0 | K102: 0 | L102: 0 | M102: 0 | N102: 0
B103: Ending | F103: =F539 -> 18225 | G103: =SUM(G99:G102) -> 19245 | H103: =SUM(H99:H102) -> 16673 | I103: =SUM(I99:I102) -> 16515.919 | J103: =SUM(J99:J102) -> 16357.943 | K103: =SUM(K99:K102) -> 16196.529 | L103: =SUM(L99:L102) -> 16084.47 | M103: =SUM(M99:M102) -> 15971.49 | N103: =SUM(N99:N102) -> 15851.788
C106: First Year Tax Depreciation | D106: =Input!M174 -> 0.15
C107: Blended Tax Depreciation Rate | D107: =Input!M175 -> 0.08
B109: TAX BASIS
B110: Beginning | I110: =H113 -> 49222 | J110: =I113 -> 49993.725 | K110: =J113 -> 50684.162 | L110: =K113 -> 51342.815 | M110: =L113 -> 51996.816
B111: Capital Expenditure | I111: =I94+I100 -> 4766.6848 | J111: =J94+J100 -> 4746.8986 | K111: =K94+K100 -> 4770.6331 | L111: =L94+L100 -> 4819.2569 | M111: =M94+M100 -> 4954.1961
B112: Tax Depreciation | I112: =-(I110+I111*$D$106)*$D$107 -> -3994.9602 | J112: =-(J110+J111*$D$106)*$D$107 -> -4056.4608 | K112: =-(K110+K111*$D$106)*$D$107 -> -4111.9806 | L112: =-(L110+L111*$D$106)*$D$107 -> -4165.2563 | M112: =-(M110+M111*$D$106)*$D$107 -> -4219.1956
B113: Ending | H113: =Input!M176 -> 49222 | I113: =I110+I111+I112 -> 49993.725 | J113: =J110+J111+J112 -> 50684.162 | K113: =K110+K111+K112 -> 51342.815 | L113: =L110+L111+L112 -> 51996.816 | M113: =M110+M111+M112 -> 52731.816
B115: Model uses a blended D&A rate on opening net book value , consistent with the level of disclosure in Nestlé's consolidated statements. All PP&E and intangible capex is depreciated/amortized on this blended basis;
B116: Historical 'Other movements' reconcile the PP&E and intangibles roll-forwards to reported balances (FX, leases, impairments, disposals); the forecast assumes none, so the asset base moves only with capex and D&A.
B118: Income Tax Schedule (Levered)
B120: =Input!$B$8 -> All figures in CHF millions unless stated | F120: =F$2 -> 2023 | G120: =G$2 -> 2024 | H120: =H$2 -> 2025 | I120: =I$2 -> 2026 | J120: =J$2 -> 2027 | K120: =K$2 -> 2028 | L120: =L$2 -> 2029 | M120: =M$2 -> 2030
B121: =CONCATENATE("Model Running: ",INDEX(Input!$B$12:$B$14,Input!$D$6)," Drivers") -> Model Running: Base Case Drivers
C123: EBT | I123: =I456 -> 10861.493 | J123: =J456 -> 11336.57 | K123: =K456 -> 11218.998 | L123: =L456 -> 11908.664 | M123: =M456 -> 12610.504
C124: Profitable Before Tax? | I124: =IF(I133>0,1,0) -> 1 | J124: =IF(J133>0,1,0) -> 1 | K124: =IF(K133>0,1,0) -> 1 | L124: =IF(L133>0,1,0) -> 1 | M124: =IF(M133>0,1,0) -> 1
C126: Tax Rate | D126: =Input!$M$173 -> 0.235
C127: Unused Tax Loss Remaining | D127: =IF(M144=0,0,1) -> 0
B129: ADJUSTMENT FOR DEPRECIATION
B130: EBT | I130: =I123 -> 10861.493 | J130: =J123 -> 11336.57 | K130: =K123 -> 11218.998 | L130: =L123 -> 11908.664 | M130: =M123 -> 12610.504
B131: Add: Accounting Depreciation | I131: =I86 -> 3445.54 | J131: =J86 -> 3487.477 | K131: =K86 -> 3522.5745 | L131: =L86 -> 3554.3919 | M131: =M86 -> 3639.1378
B132: Less: Tax Depreciation | I132: =I112 -> -3994.9602 | J132: =J112 -> -4056.4608 | K132: =K112 -> -4111.9806 | L132: =L112 -> -4165.2563 | M132: =M112 -> -4219.1956
B133: EBT After Adjustment | I133: =SUM(I130:I132) -> 10312.073 | J133: =SUM(J130:J132) -> 10767.586 | K133: =SUM(K130:K132) -> 10629.591 | L133: =SUM(L130:L132) -> 11297.799 | M133: =SUM(M130:M132) -> 12030.446
B135: ADJUSTMENT FOR TAX LOSSES 1
...
