Workbook
Name ScenarioSwitch: Input!$D$6

Sheet Cover
C4: 3-Statement Modeling | L4: CONFIDENTIAL
C7: Table of Contents | J7: Model Checks
C9: Dashboard | J9: Unused Tax Losses Remaining? | L9: =Model!$D$128 -> 0
C10: Ouput | J10: Balance Sheet Unbalanced? | L10: =IF(ROUND(SUMPRODUCT(ABS(Model!$F$395:$M$395)),2)=0,0,1) -> 0
C11: Input
C12: Model
C14: Model Guide
C16: Adjustable Input | D16: (Grey Cell)
C17: Hardcode | D17: (Blue Font)
C18: Formula | D18: (Black Font)
P19: Do Not
C20: Model Circularity | P20: Delete
C22: Circularity Switch | D22: 0 | P22: Circularity
P23: 1
C24: =IF($D$22=1,"This model now has the circularity turned on. Please confirm the Excel settings below","") | P24: 0
C25: =IF($D$22=1,"PC","") | D25: =IF($D$22=1,"File - Options - Formulas - Check the box on the top-right labeled 'Enable iterative calculation'.","")
C26: =IF($D$22=1,"Mac","") | D26: =IF($D$22=1,"Excel - Preferences - Calculation - Check the box near the bottom labeled 'Use iterative calculation'.","")
C28: DISCLAIMER & NOTICE OF INTENT
C29: 1. Independent Portfolio Project: This financial model and dashboard were prepared solely by the author, in a personal capacity, to demonstrate
C30: skills in financial modeling and financial statement analysis. They do not reflect the views of any employer.
C31: 2. Public Data Sources: Historical figures are drawn from publicly available sources (Nestlé Investor Relations / Annual Reports). Forecasts and
C32: scenarios (Best / Base / Worst) are the author's own illustrative assumptions, not forecasts issued by Nestlé.
C33: 3. No Affiliation: This project is not affiliated with, authorized by, or endorsed by Nestlé S.A. Nestlé and related names and marks are the
C34: property of their respective owners and are used for identification only.
C35: 4. No Advice: Nothing herein constitutes investment advice, equity research, or a recommendation to buy or sell any security.

Sheet Dashboard
Q1: EXECUTIVE FINANCIAL DASHBOARD
B2: ="Nestlé S.A. | CHF millions | Model Scenario: " -> Nestlé S.A. | CHF millions | Model Scenario: | F2: 2 | O2: Reporting year ▸ | P2: 2026F
B4: Key Performance Indicators
B6: REVENUE (CHF m) | D6: EBITDA MARGIN | F6: NET PROFIT (CHF m) | H6: FREE CASH FLOW (CHF m) | J6: ROE | L6: ROIC | N6: NET DEBT / EBITDA | P6: CASH CONVERSION CYCLE
B7: =$P$101 -> 90315.187 | D7: =$P$104 -> 0.17526389 | F7: =$P$107 -> 9486.3323 | H7: =$P$126 -> 8966.7167 | J7: =$P$108 -> 0.27603888 | L7: =$P$110 -> 0.10907626 | N7: =$P$127 -> 3.3157317 | P7: =$P$114 -> -14.179845
B8: =IF(ISNUMBER($Q$101),IF($P$101>=$Q$101,"▲ ","▼ ")&TEXT(ABS($P$101/$Q$101-1),"0.0%")&" vs "&$Q$99,"n.a.") -> ▲ 0.5% vs 2025A | D8: =IF(ISNUMBER($Q$104),IF($P$104>=$Q$104,"▲ ","▼ ")&TEXT(ABS($P$104-$Q$104)*100,"0.0")&" pp vs "&$Q$99,"n.a.") -> ▼ 0.2 pp vs 2025A | F8: =IF(ISNUMBER($Q$107),IF($P$107>=$Q$107,"▲ ","▼ ")&TEXT(ABS($P$107/$Q$107-1),"0.0%")&" vs "&$Q$99,"n.a.") -> ▲ 2.5% vs 2025A | H8: =IF(ISNUMBER($Q$126),IF($P$126>=$Q$126,"▲ ","▼ ")&TEXT(ABS($P$126/$Q$126-1),"0.0%")&" vs "&$Q$99,"n.a.") -> ▼ 18.4% vs 2025A | J8: =IF(ISNUMBER($Q$108),IF($P$108>=$Q$108,"▲ ","▼ ")&TEXT(ABS($P$108-$Q$108)*100,"0.0")&" pp vs "&$Q$99,"n.a.") -> ▼ 0.4 pp vs 2025A | L8: =IF(ISNUMBER($Q$110),IF($P$110>=$Q$110,"▲ ","▼ ")&TEXT(ABS($P$110-$Q$110)*100,"0.0")&" pp vs "&$Q$99,"n.a.") -> ▲ 0.2 pp vs 2025A | N8: =IF(ISNUMBER($Q$127),IF($P$127>=$Q$127,"▲ ","▼ ")&TEXT(ABS($P$127-$Q$127),"0.00")&"x vs "&$Q$99,"n.a.") -> ▼ 0.03x vs 2025A | P8: =IF(ISNUMBER($Q$114),IF($P$114>=$Q$114,"▲ ","▼ ")&TEXT(ABS($P$114-$Q$114),"0.0")&" days vs "&$Q$99,"n.a.") -> ▼ 3.0 days vs 2025A
B10: Income Summary | J10: Cash Flow
B30: Revenue & Profitability Margin | J30: Net Profit vs Free Cash Flow
B50: Expenses Summary | J50: Working Capital Cycle
B70: Cash Generation Sensitivity | J70: Liquidity Sensitivity
B72: Sensitivity inputs | J72: Sensitivity inputs
B73: Revenue Growth Step | D73: 0.01 | J73: DSO | L73: 2
B74: EBITDA Margin Step | D74: 0.02 | J74: DPO | L74: 5
D77: Free Cash Flow | L77: Cash Balance
D79: Revenue Growth | L79: DSO
C80: =$P$126 -> 8966.7167 | D80: =E80-$D$73 -> -0.015214026 | E80: =F80-$D$73 -> -0.0052140258 | F80: =$P$100 -> 0.0047859742 | G80: =F80+$D$73 -> 0.014785974 | H80: =G80+$D$73 -> 0.024785974 | K80: =$P$124 -> 4210.2724 | L80: =M80+$L$73 -> 46.820155 | M80: =N80+$L$73 -> 44.820155 | N80: =$P$111 -> 42.820155 | O80: =N80-$L$73 -> 40.820155 | P80: =O80-$L$73 -> 38.820155
B81: EBITDA Margin | C81: =C82+$D$74 -> 0.21526389 | D81: =$C$80+(($Q$101*(1+D$80)*$C81)-$P$102)*(1-$P$137) -> 11434.322 | E81: =$C$80+(($Q$101*(1+E$80)*$C81)-$P$102)*(1-$P$137) -> 11582.342 | F81: =$C$80+(($Q$101*(1+F$80)*$C81)-$P$102)*(1-$P$137) -> 11730.361 | G81: =$C$80+(($Q$101*(1+G$80)*$C81)-$P$102)*(1-$P$137) -> 11878.381 | H81: =$C$80+(($Q$101*(1+H$80)*$C81)-$P$102)*(1-$P$137) -> 12026.401 | J81: DPO | K81: =K82+$L$74 -> 160 | L81: =$K$80-(L$80-$N$80)*$P$101/365-($K81-$K$83)*$P$142/365 -> 4555.8057 | M81: =$K$80-(M$80-$N$80)*$P$101/365-($K81-$K$83)*$P$142/365 -> 5050.6834 | N81: =$K$80-(N$80-$N$80)*$P$101/365-($K81-$K$83)*$P$142/365 -> 5545.5612 | O81: =$K$80-(O$80-$N$80)*$P$101/365-($K81-$K$83)*$P$142/365 -> 6040.4389 | P81: =$K$80-(P$80-$N$80)*$P$101/365-($K81-$K$83)*$P$142/365 -> 6535.3167
C82: =C83+$D$74 -> 0.19526389 | D82: =$C$80+(($Q$101*(1+D$80)*$C82)-$P$102)*(1-$P$137) -> 10080.004 | E82: =$C$80+(($Q$101*(1+E$80)*$C82)-$P$102)*(1-$P$137) -> 10214.272 | F82: =$C$80+(($Q$101*(1+F$80)*$C82)-$P$102)*(1-$P$137) -> 10348.539 | G82: =$C$80+(($Q$101*(1+G$80)*$C82)-$P$102)*(1-$P$137) -> 10482.806 | H82: =$C$80+(($Q$101*(1+H$80)*$C82)-$P$102)*(1-$P$137) -> 10617.074 | K82: =K83+$L$74 -> 155 | L82: =$K$80-(L$80-$N$80)*$P$101/365-($K82-$K$83)*$P$142/365 -> 3888.1613 | M82: =$K$80-(M$80-$N$80)*$P$101/365-($K82-$K$83)*$P$142/365 -> 4383.0391 | N82: =$K$80-(N$80-$N$80)*$P$101/365-($K82-$K$83)*$P$142/365 -> 4877.9168 | O82: =$K$80-(O$80-$N$80)*$P$101/365-($K82-$K$83)*$P$142/365 -> 5372.7945 | P82: =$K$80-(P$80-$N$80)*$P$101/365-($K82-$K$83)*$P$142/365 -> 5867.6723
C83: =$P$104 -> 0.17526389 | D83: =$C$80+(($Q$101*(1+D$80)*$C83)-$P$102)*(1-$P$137) -> 8725.6866 | E83: =$C$80+(($Q$101*(1+E$80)*$C83)-$P$102)*(1-$P$137) -> 8846.2016 | F83: =$C$80+(($Q$101*(1+F$80)*$C83)-$P$102)*(1-$P$137) -> 8966.7167 | G83: =$C$80+(($Q$101*(1+G$80)*$C83)-$P$102)*(1-$P$137) -> 9087.2317 | H83: =$C$80+(($Q$101*(1+H$80)*$C83)-$P$102)*(1-$P$137) -> 9207.7467 | K83: =$P$113 -> 150 | L83: =$K$80-(L$80-$N$80)*$P$101/365-($K83-$K$83)*$P$142/365 -> 3220.5169 | M83: =$K$80-(M$80-$N$80)*$P$101/365-($K83-$K$83)*$P$142/365 -> 3715.3947 | N83: =$K$80-(N$80-$N$80)*$P$101/365-($K83-$K$83)*$P$142/365 -> 4210.2724 | O83: =$K$80-(O$80-$N$80)*$P$101/365-($K83-$K$83)*$P$142/365 -> 4705.1502 | P83: =$K$80-(P$80-$N$80)*$P$101/365-($K83-$K$83)*$P$142/365 -> 5200.0279
C84: =C83-$D$74 -> 0.15526389 | D84: =$C$80+(($Q$101*(1+D$80)*$C84)-$P$102)*(1-$P$137) -> 7371.3691 | E84: =$C$80+(($Q$101*(1+E$80)*$C84)-$P$102)*(1-$P$137) -> 7478.1317 | F84: =$C$80+(($Q$101*(1+F$80)*$C84)-$P$102)*(1-$P$137) -> 7584.8943 | G84: =$C$80+(($Q$101*(1+G$80)*$C84)-$P$102)*(1-$P$137) -> 7691.6569 | H84: =$C$80+(($Q$101*(1+H$80)*$C84)-$P$102)*(1-$P$137) -> 7798.4195 | K84: =K83-$L$74 -> 145 | L84: =$K$80-(L$80-$N$80)*$P$101/365-($K84-$K$83)*$P$142/365 -> 2552.8726 | M84: =$K$80-(M$80-$N$80)*$P$101/365-($K84-$K$83)*$P$142/365 -> 3047.7503 | N84: =$K$80-(N$80-$N$80)*$P$101/365-($K84-$K$83)*$P$142/365 -> 3542.628 | O84: =$K$80-(O$80-$N$80)*$P$101/365-($K84-$K$83)*$P$142/365 -> 4037.5058 | P84: =$K$80-(P$80-$N$80)*$P$101/365-($K84-$K$83)*$P$142/365 -> 4532.3835
C85: =C84-$D$74 -> 0.13526389 | D85: =$C$80+(($Q$101*(1+D$80)*$C85)-$P$102)*(1-$P$137) -> 6017.0515 | E85: =$C$80+(($Q$101*(1+E$80)*$C85)-$P$102)*(1-$P$137) -> 6110.0617 | F85: =$C$80+(($Q$101*(1+F$80)*$C85)-$P$102)*(1-$P$137) -> 6203.0719 | G85: =$C$80+(($Q$101*(1+G$80)*$C85)-$P$102)*(1-$P$137) -> 6296.0821 | H85: =$C$80+(($Q$101*(1+H$80)*$C85)-$P$102)*(1-$P$137) -> 6389.0923 | K85: =K84-$L$74 -> 140 | L85: =$K$80-(L$80-$N$80)*$P$101/365-($K85-$K$83)*$P$142/365 -> 1885.2282 | M85: =$K$80-(M$80-$N$80)*$P$101/365-($K85-$K$83)*$P$142/365 -> 2380.1059 | N85: =$K$80-(N$80-$N$80)*$P$101/365-($K85-$K$83)*$P$142/365 -> 2874.9837 | O85: =$K$80-(O$80-$N$80)*$P$101/365-($K85-$K$83)*$P$142/365 -> 3369.8614 | P85: =$K$80-(P$80-$N$80)*$P$101/365-($K85-$K$83)*$P$142/365 -> 3864.7391
C86: =C85-$D$74 -> 0.11526389 | D86: =$C$80+(($Q$101*(1+D$80)*$C86)-$P$102)*(1-$P$137) -> 4662.734 | E86: =$C$80+(($Q$101*(1+E$80)*$C86)-$P$102)*(1-$P$137) -> 4741.9918 | F86: =$C$80+(($Q$101*(1+F$80)*$C86)-$P$102)*(1-$P$137) -> 4821.2496 | G86: =$C$80+(($Q$101*(1+G$80)*$C86)-$P$102)*(1-$P$137) -> 4900.5073 | H86: =$C$80+(($Q$101*(1+H$80)*$C86)-$P$102)*(1-$P$137) -> 4979.7651 | K86: =K85-$L$74 -> 135 | L86: =$K$80-(L$80-$N$80)*$P$101/365-($K86-$K$83)*$P$142/365 -> 1217.5838 | M86: =$K$80-(M$80-$N$80)*$P$101/365-($K86-$K$83)*$P$142/365 -> 1712.4615 | N86: =$K$80-(N$80-$N$80)*$P$101/365-($K86-$K$83)*$P$142/365 -> 2207.3393 | O86: =$K$80-(O$80-$N$80)*$P$101/365-($K86-$K$83)*$P$142/365 -> 2702.217 | P86: =$K$80-(P$80-$N$80)*$P$101/365-($K86-$K$83)*$P$142/365 -> 3197.0948
B98: Chart Data | P98: CY | Q98: PY
B99: Period | H99: =TEXT(Output!F2,"0")&"A" -> 2023A | I99: =TEXT(Output!G2,"0")&"A" -> 2024A | J99: =TEXT(Output!H2,"0")&"A" -> 2025A | K99: =TEXT(Output!I2,"0")&"F" -> 2026F | L99: =TEXT(Output!J2,"0")&"F" -> 2027F | M99: =TEXT(Output!K2,"0")&"F" -> 2028F | N99: =TEXT(Output!L2,"0")&"F" -> 2029F | O99: =TEXT(Output!M2,"0")&"F" -> 2030F | P99: =$P$2 -> 2026F | Q99: =IF(MATCH($P$2,$H$99:$O$99,0)=1,"n.a.",INDEX($H$99:$O$99,MATCH($P$2,$H$99:$O$99,0)-1)) -> 2025A
B100: Revenue Growth | H100: =Output!F156 -> 0 | I100: =Output!G156 -> -0.017471693 | J100: =Output!H156 -> -0.020006542 | K100: =Output!I156 -> 0.0047859742 | L100: =Output!J156 -> 0.015101075 | M100: =Output!K156 -> 0.005 | N100: =Output!L156 -> 0.020101563 | O100: =Output!M156 -> 0.02810235 | P100: =INDEX($H100:$O100,MATCH($P$2,$H$99:$O$99,0)) -> 0.0047859742 | Q100: =IF(MATCH($P$2,$H$99:$O$99,0)=1,"n.a.",INDEX($H100:$O100,MATCH($P$2,$H$99:$O$99,0)-1)) -> -0.020006542
B101: Revenue (CHF m) | H101: =Output!F9 -> 93351 | I101: =Output!G9 -> 91720 | J101: =Output!H9 -> 89885 | K101: =Output!I9 -> 90315.187 | L101: =Output!J9 -> 91679.044 | M101: =Output!K9 -> 92137.439 | N101: =Output!L9 -> 93989.546 | O101: =Output!M9 -> 96630.873 | P101: =INDEX($H101:$O101,MATCH($P$2,$H$99:$O$99,0)) -> 90315.187 | Q101: =IF(MATCH($P$2,$H$99:$O$99,0)=1,"n.a.",INDEX($H101:$O101,MATCH($P$2,$H$99:$O$99,0)-1)) -> 89885
B102: EBITDA (CHF m) | H102: =Output!F14 -> 17521 | I102: =Output!G14 -> 18306 | J102: =Output!H14 -> 15910 | K102: =Output!I14 -> 15828.991 | L102: =Output!J14 -> 16321.669 | M102: =Output!K14 -> 16209.005 | N102: =Output!L14 -> 16904.349 | O102: =Output!M14 -> 17663.153 | P102: =INDEX($H102:$O102,MATCH($P$2,$H$99:$O$99,0)) -> 15828.991 | Q102: =IF(MATCH($P$2,$H$99:$O$99,0)=1,"n.a.",INDEX($H102:$O102,MATCH($P$2,$H$99:$O$99,0)-1)) -> 15910
B103: Gross margin | H103: =Output!F83 -> 0.46087348 | I103: =Output!G83 -> 0.46936328 | J103: =Output!H83 -> 0.45826334 | K103: =Output!I83 -> 0.4603561 | L103: =Output!J83 -> 0.45842121 | M103: =Output!K83 -> 0.45154073 | N103: =Output!L83 -> 0.45247071 | O103: =Output!M83 -> 0.45384055 | P103: =INDEX($H103:$O103,MATCH($P$2,$H$99:$O$99,0)) -> 0.4603561 | Q103: =IF(MATCH($P$2,$H$99:$O$99,0)=1,"n.a.",INDEX($H103:$O103,MATCH($P$2,$H$99:$O$99,0)-1)) -> 0.45826334
B104: EBITDA margin | H104: =Output!F86 -> 0.18768947 | I104: =Output!G86 -> 0.1995857 | J104: =Output!H86 -> 0.17700395 | K104: =Output!I86 -> 0.17526389 | L104: =Output!J86 -> 0.17803053 | M104: =Output!K86 -> 0.17592203 | N104: =Output!L86 -> 0.17985351 | O104: =Output!M86 -> 0.18278995 | P104: =INDEX($H104:$O104,MATCH($P$2,$H$99:$O$99,0)) -> 0.17526389 | Q104: =IF(MATCH($P$2,$H$99:$O$99,0)=1,"n.a.",INDEX($H104:$O104,MATCH($P$2,$H$99:$O$99,0)-1)) -> 0.17700395
B105: EBIT margin | H105: =Output!F90 -> 0.15064648 | I105: =Output!G90 -> 0.16053205 | J105: =Output!H90 -> 0.13658564 | K105: =Output!I90 -> 0.13711372 | L105: =Output!J90 -> 0.13999046 | M105: =Output!K90 -> 0.13769029 | N105: =Output!L90 -> 0.14203662 | O105: =Output!M90 -> 0.14512975 | P105: =INDEX($H105:$O105,MATCH($P$2,$H$99:$O$99,0)) -> 0.13711372 | Q105: =IF(MATCH($P$2,$H$99:$O$99,0)=1,"n.a.",INDEX($H105:$O105,MATCH($P$2,$H$99:$O$99,0)-1)) -> 0.13658564
B106: Net profit margin | H106: =Output!F98 -> 0.12328738 | I106: =Output!G98 -> 0.1218273 | J106: =Output!H98 -> 0.10295377 | K106: =Output!I98 -> 0.10503585 | L106: =Output!J98 -> 0.10795114 | M106: =Output!K98 -> 0.10696944 | N106: =Output!L98 -> 0.11115228 | O106: =Output!M98 -> 0.11436212 | P106: =INDEX($H106:$O106,MATCH($P$2,$H$99:$O$99,0)) -> 0.10503585 | Q106: =IF(MATCH($P$2,$H$99:$O$99,0)=1,"n.a.",INDEX($H106:$O106,MATCH($P$2,$H$99:$O$99,0)-1)) -> 0.10295377
B107: Net profit (CHF m) | H107: =Output!F24 -> 11509 | I107: =Output!G24 -> 11174 | J107: =Output!H24 -> 9254 | K107: =Output!I24 -> 9486.3323 | L107: =Output!J24 -> 9896.8573 | M107: =Output!K24 -> 9855.89 | N107: =Output!L24 -> 10447.153 | O107: =Output!M24 -> 11050.912 | P107: =INDEX($H107:$O107,MATCH($P$2,$H$99:$O$99,0)) -> 9486.3323 | Q107: =IF(MATCH($P$2,$H$99:$O$99,0)=1,"n.a.",INDEX($H107:$O107,MATCH($P$2,$H$99:$O$99,0)-1)) -> 9254
B108: Return on equity | H108: =Output!F79 -> 0.31629428 | I108: =Output!G79 -> 0.30452675 | J108: =Output!H79 -> 0.27993224 | K108: =Output!I79 -> 0.27603888 | L108: =Output!J79 -> 0.27527672 | M108: =Output!K79 -> 0.26374556 | N108: =Output!L79 -> 0.2662567 | O108: =Output!M79 -> 0.27928286 | P108: =INDEX($H108:$O108,MATCH($P$2,$H$99:$O$99,0)) -> 0.27603888 | Q108: =IF(MATCH($P$2,$H$99:$O$99,0)=1,"n.a.",INDEX($H108:$O108,MATCH($P$2,$H$99:$O$99,0)-1)) -> 0.27993224
B109: Return on assets | H109: =Output!F80 -> 0.090944291 | I109: =Output!G80 -> 0.080236098 | J109: =Output!H80 -> 0.072779608 | K109: =Output!I80 -> 0.074576039 | L109: =Output!J80 -> 0.076819763 | M109: =Output!K80 -> 0.075324088 | N109: =Output!L80 -> 0.077938368 | O109: =Output!M80 -> 0.081396615 | P109: =INDEX($H109:$O109,MATCH($P$2,$H$99:$O$99,0)) -> 0.074576039 | Q109: =IF(MATCH($P$2,$H$99:$O$99,0)=1,"n.a.",INDEX($H109:$O109,MATCH($P$2,$H$99:$O$99,0)-1)) -> 0.072779608
B110: Return on invested capital | H110: =Output!F82 -> 0.13248468 | I110: =Output!G82 -> 0.11656413 | J110: =Output!H82 -> 0.10728797 | K110: =Output!I82 -> 0.10907626 | L110: =Output!J82 -> 0.11243851 | M110: =Output!K82 -> 0.11067382 | N110: =Output!L82 -> 0.11558303 | O110: =Output!M82 -> 0.11997637 | P110: =INDEX($H110:$O110,MATCH($P$2,$H$99:$O$99,0)) -> 0.10907626 | Q110: =IF(MATCH($P$2,$H$99:$O$99,0)=1,"n.a.",INDEX($H110:$O110,MATCH($P$2,$H$99:$O$99,0)-1)) -> 0.10728797
B111: DSO | H111: =Output!F118 -> 42.990166 | I111: =Output!G118 -> 44.773386 | J111: =Output!H118 -> 42.88552 | K111: =Output!I118 -> 42.820155 | L111: =Output!J118 -> 42.815892 | M111: =Output!K118 -> 42.318032 | N111: =Output!L118 -> 41.81601 | O111: =Output!M118 -> 41.811847 | P111: =INDEX($H111:$O111,MATCH($P$2,$H$99:$O$99,0)) -> 42.820155 | Q111: =IF(MATCH($P$2,$H$99:$O$99,0)=1,"n.a.",INDEX($H111:$O111,MATCH($P$2,$H$99:$O$99,0)-1)) -> 42.88552
B112: DSI | H112: =Output!F120 -> 86.274837 | I112: =Output!G120 -> 99.443189 | J112: =Output!H120 -> 96.043558 | K112: =Output!I120 -> 93 | L112: =Output!J120 -> 91 | M112: =Output!K120 -> 89 | N112: =Output!L120 -> 88 | O112: =Output!M120 -> 87 | P112: =INDEX($H112:$O112,MATCH($P$2,$H$99:$O$99,0)) -> 93 | Q112: =IF(MATCH($P$2,$H$99:$O$99,0)=1,"n.a.",INDEX($H112:$O112,MATCH($P$2,$H$99:$O$99,0)-1)) -> 96.043558
B113: DPO | H113: =Output!F122 -> 139.27555 | I113: =Output!G122 -> 163.5413 | J113: =Output!H122 -> 150.0882 | K113: =Output!I122 -> 150 | L113: =Output!J122 -> 150 | M113: =Output!K122 -> 150 | N113: =Output!L122 -> 150 | O113: =Output!M122 -> 150 | P113: =INDEX($H113:$O113,MATCH($P$2,$H$99:$O$99,0)) -> 150 | Q113: =IF(MATCH($P$2,$H$99:$O$99,0)=1,"n.a.",INDEX($H113:$O113,MATCH($P$2,$H$99:$O$99,0)-1)) -> 150.0882
B114: Cash Cycle | H114: =Output!F123 -> -10.010549 | I114: =Output!G123 -> -19.324723 | J114: =Output!H123 -> -11.159126 | K114: =Output!I123 -> -14.179845 | L114: =Output!J123 -> -16.184108 | M114: =Output!K123 -> -18.681968 | N114: =Output!L123 -> -20.18399 | O114: =Output!M123 -> -21.188153 | P114: =INDEX($H114:$O114,MATCH($P$2,$H$99:$O$99,0)) -> -14.179845 | Q114: =IF(MATCH($P$2,$H$99:$O$99,0)=1,"n.a.",INDEX($H114:$O114,MATCH($P$2,$H$99:$O$99,0)-1)) -> -11.159126
B116: Operating cash flow | H116: =Output!F36 -> 15941 | I116: =Output!G36 -> 16675 | J116: =Output!H36 -> 15904 | K116: =Output!I36 -> 13733.402 | L116: =Output!J36 -> 14174.144 | M116: =Output!K36 -> 14255.556 | N116: =Output!L36 -> 14599.324 | O116: =Output!M36 -> 14942.689 | P116: =INDEX($H116:$O116,MATCH($P$2,$H$99:$O$99,0)) -> 13733.402 | Q116: =IF(MATCH($P$2,$H$99:$O$99,0)=1,"n.a.",INDEX($H116:$O116,MATCH($P$2,$H$99:$O$99,0)-1)) -> 15904
B117: Beginning | H117: =Model!F329 -> 5511 | I117: =Model!G329 -> 4816 | J117: =Model!H329 -> 5558 | K117: =Model!I329 -> 4579 | L117: =Model!J329 -> 4210.2724 | M117: =Model!K329 -> 4760.1772 | N117: =Model!L329 -> 5805.748 | O117: =Model!M329 -> 7568.1546 | P117: =INDEX($H117:$O117,MATCH($P$2,$H$99:$O$99,0)) -> 4579 | Q117: =IF(MATCH($P$2,$H$99:$O$99,0)=1,"n.a.",INDEX($H117:$O117,MATCH($P$2,$H$99:$O$99,0)-1)) -> 5558
B118: EBIT | H118: =Model!F287 -> 14063 | I118: =Model!G287 -> 14724 | J118: =Model!H287 -> 12277 | K118: =Model!I287 -> 12383.451 | L118: =Model!J287 -> 12834.192 | M118: =Model!K287 -> 12686.43 | N118: =Model!L287 -> 13349.957 | O118: =Model!M287 -> 14024.015 | P118: =INDEX($H118:$O118,MATCH($P$2,$H$99:$O$99,0)) -> 12383.451 | Q118: =IF(MATCH($P$2,$H$99:$O$99,0)=1,"n.a.",INDEX($H118:$O118,MATCH($P$2,$H$99:$O$99,0)-1)) -> 12277
B119: Non-Cash Adj | H119: =SUM(Model!F288:F291)+Model!F326+Model!F331 -> 3726 | I119: =SUM(Model!G288:G291)+Model!G326+Model!G331 -> 4046 | J119: =SUM(Model!H288:H291)+Model!H326+Model!H331 -> 4452 | K119: =SUM(Model!I288:I291)+Model!I326+Model!I331 -> 4389.8832 | L119: =SUM(Model!J288:J291)+Model!J326+Model!J331 -> 4270.2588 | M119: =SUM(Model!K288:K291)+Model!K326+Model!K331 -> 4171.1971 | N119: =SUM(Model!L288:L291)+Model!L326+Model!L331 -> 4094.8037 | O119: =SUM(Model!M288:M291)+Model!M326+Model!M331 -> 4120.6087 | P119: =INDEX($H119:$O119,MATCH($P$2,$H$99:$O$99,0)) -> 4389.8832 | Q119: =IF(MATCH($P$2,$H$99:$O$99,0)=1,"n.a.",INDEX($H119:$O119,MATCH($P$2,$H$99:$O$99,0)-1)) -> 4452
B120: NWC | H120: =Model!F294+Model!F295 -> 709 | I120: =Model!G294+Model!G295 -> 874 | J120: =Model!H294+Model!H295 -> -319 | K120: =Model!I294+Model!I295 -> 119.12223 | L120: =Model!J294+Model!J295 -> 348.47536 | M120: =Model!K294+Model!K295 -> 585.58287 | N120: =Model!L294+Model!L295 -> 443.36926 | O120: =Model!M294+Model!M295 -> 199.48765 | P120: =INDEX($H120:$O120,MATCH($P$2,$H$99:$O$99,0)) -> 119.12223 | Q120: =IF(MATCH($P$2,$H$99:$O$99,0)=1,"n.a.",INDEX($H120:$O120,MATCH($P$2,$H$99:$O$99,0)-1)) -> -319
B121: Int/Tax/Div | H121: =SUM(Model!F298:F301) -> -3239 | I121: =SUM(Model!G298:G301) -> -2918 | J121: =SUM(Model!H298:H301) -> -957 | K121: =SUM(Model!I298:I301) -> -3159.0552 | L121: =SUM(Model!J298:J301) -> -3278.7817 | M121: =SUM(Model!K298:K301) -> -3187.6543 | N121: =SUM(Model!L298:L301) -> -3288.8065 | O121: =SUM(Model!M298:M301) -> -3401.4222 | P121: =INDEX($H121:$O121,MATCH($P$2,$H$99:$O$99,0)) -> -3159.0552 | Q121: =IF(MATCH($P$2,$H$99:$O$99,0)=1,"n.a.",INDEX($H121:$O121,MATCH($P$2,$H$99:$O$99,0)-1)) -> -957
B122: Investing | H122: =Output!F37 -> -6196 | I122: =Output!G37 -> -8624 | J122: =Output!H37 -> -4367 | K122: =Output!I37 -> -4766.6848 | L122: =Output!J37 -> -4746.8986 | M122: =Output!K37 -> -4770.6331 | N122: =Output!L37 -> -4819.2569 | O122: =Output!M37 -> -4954.1961 | P122: =INDEX($H122:$O122,MATCH($P$2,$H$99:$O$99,0)) -> -4766.6848 | Q122: =IF(MATCH($P$2,$H$99:$O$99,0)=1,"n.a.",INDEX($H122:$O122,MATCH($P$2,$H$99:$O$99,0)-1)) -> -4367
B123: Financing | H123: =Output!F38 -> -9758 | I123: =Output!G38 -> -7362 | J123: =Output!H38 -> -12065 | K123: =Output!I38 -> -9335.4442 | L123: =Output!J38 -> -8877.3407 | M123: =Output!K38 -> -8439.3522 | N123: =Output!L38 -> -8017.6604 | O123: =Output!M38 -> -10152.276 | P123: =INDEX($H123:$O123,MATCH($P$2,$H$99:$O$99,0)) -> -9335.4442 | Q123: =IF(MATCH($P$2,$H$99:$O$99,0)=1,"n.a.",INDEX($H123:$O123,MATCH($P$2,$H$99:$O$99,0)-1)) -> -12065
B124: Ending | H124: =SUM(H117:H121)+SUM(H122:H123) -> 4816 | I124: =SUM(I117:I121)+SUM(I122:I123) -> 5556 | J124: =SUM(J117:J121)+SUM(J122:J123) -> 4579 | K124: =SUM(K117:K121)+SUM(K122:K123) -> 4210.2724 | L124: =SUM(L117:L121)+SUM(L122:L123) -> 4760.1772 | M124: =SUM(M117:M121)+SUM(M122:M123) -> 5805.748 | N124: =SUM(N117:N121)+SUM(N122:N123) -> 7568.1546 | O124: =SUM(O117:O121)+SUM(O122:O123) -> 7404.3711 | P124: =INDEX($H124:$O124,MATCH($P$2,$H$99:$O$99,0)) -> 4210.2724 | Q124: =IF(MATCH($P$2,$H$99:$O$99,0)=1,"n.a.",INDEX($H124:$O124,MATCH($P$2,$H$99:$O$99,0)-1)) -> 4579
B126: Free cash flow (CHF m) | H126: =Output!F36+Model!F305+Model!F306 -> 9738 | I126: =Output!G36+Model!G305+Model!G306 -> 10712 | J126: =Output!H36+Model!H305+Model!H306 -> 10993 | K126: =Output!I36+Model!I305+Model!I306 -> 8966.7167 | L126: =Output!J36+Model!J305+Model!J306 -> 9427.2455 | M126: =Output!K36+Model!K305+Model!K306 -> 9484.9229 | N126: =Output!L36+Model!L305+Model!L306 -> 9780.0671 | O126: =Output!M36+Model!M305+Model!M306 -> 9988.4928 | P126: =INDEX($H126:$O126,MATCH($P$2,$H$99:$O$99,0)) -> 8966.7167 | Q126: =IF(MATCH($P$2,$H$99:$O$99,0)=1,"n.a.",INDEX($H126:$O126,MATCH($P$2,$H$99:$O$99,0)-1)) -> 10993
B127: Net debt / EBITDA | H127: =Output!F136 -> 2.877975 | I127: =Output!G136 -> 3.1685786 | J127: =Output!H136 -> 3.3483972 | K127: =Output!I136 -> 3.3157317 | L127: =Output!J136 -> 3.147217 | M127: =Output!K136 -> 3.1045868 | N127: =Output!L136 -> 2.9058282 | O127: =Output!M136 -> 2.8223621 | P127: =INDEX($H127:$O127,MATCH($P$2,$H$99:$O$99,0)) -> 3.3157317 | Q127: =IF(MATCH($P$2,$H$99:$O$99,0)=1,"n.a.",INDEX($H127:$O127,MATCH($P$2,$H$99:$O$99,0)-1)) -> 3.3483972
B128: Interest coverage (EBITDA / interest) | H128: =Output!F147 -> 10.657543 | I128: =Output!G147 -> 9.9327184 | J128: =Output!H147 -> 8.713034 | K128: =Output!I147 -> 9.4348905 | L128: =Output!J147 -> 9.9270933 | M128: =Output!K147 -> 9.958151 | N128: =Output!L147 -> 10.385342 | O128: =Output!M147 -> 10.744079 | P128: =INDEX($H128:$O128,MATCH($P$2,$H$99:$O$99,0)) -> 9.4348905 | Q128: =IF(MATCH($P$2,$H$99:$O$99,0)=1,"n.a.",INDEX($H128:$O128,MATCH($P$2,$H$99:$O$99,0)-1)) -> 8.713034
B129: Current ratio | H129: =Output!F145 -> 0.83208392 | I129: =Output!G145 -> 0.82094114 | J129: =Output!H145 -> 0.78559493 | K129: =Output!I145 -> 0.77746373 | L129: =Output!J145 -> 0.78721172 | M129: =Output!K145 -> 0.80080743 | N129: =Output!L145 -> 0.83322072 | O129: =Output!M145 -> 0.82515934 | P129: =INDEX($H129:$O129,MATCH($P$2,$H$99:$O$99,0)) -> 0.77746373 | Q129: =IF(MATCH($P$2,$H$99:$O$99,0)=1,"n.a.",INDEX($H129:$O129,MATCH($P$2,$H$99:$O$99,0)-1)) -> 0.78559493
B130: Quick ratio | H130: =Output!F146 -> 0.51129867 | I130: =Output!G146 -> 0.51158342 | J130: =Output!H146 -> 0.47073279 | K130: =Output!I146 -> 0.46854964 | L130: =Output!J146 -> 0.48202494 | M130: =Output!K146 -> 0.50042555 | N130: =Output!L146 -> 0.53609224 | O130: =Output!M146 -> 0.52957697 | P130: =INDEX($H130:$O130,MATCH($P$2,$H$99:$O$99,0)) -> 0.46854964 | Q130: =IF(MATCH($P$2,$H$99:$O$99,0)=1,"n.a.",INDEX($H130:$O130,MATCH($P$2,$H$99:$O$99,0)-1)) -> 0.47073279
B131: Revenue growth | H131: n.a. | I131: =Output!G156 -> -0.017471693 | J131: =Output!H156 -> -0.020006542 | K131: =Output!I156 -> 0.0047859742 | L131: =Output!J156 -> 0.015101075 | M131: =Output!K156 -> 0.005 | N131: =Output!L156 -> 0.020101563 | O131: =Output!M156 -> 0.02810235 | P131: =INDEX($H131:$O131,MATCH($P$2,$H$99:$O$99,0)) -> 0.0047859742 | Q131: =IF(MATCH($P$2,$H$99:$O$99,0)=1,"n.a.",INDEX($H131:$O131,MATCH($P$2,$H$99:$O$99,0)-1)) -> -0.020006542
B132: EBITDA growth | H132: n.a. | I132: =Output!G157 -> 0.044803379 | J132: =Output!H157 -> -0.13088605 | K132: =Output!I157 -> -0.0050916908 | L132: =Output!J157 -> 0.031125 | M132: =Output!K157 -> -0.0069027045 | N132: =Output!L157 -> 0.042898653 | O132: =Output!M157 -> 0.044888042 | P132: =INDEX($H132:$O132,MATCH($P$2,$H$99:$O$99,0)) -> -0.0050916908 | Q132: =IF(MATCH($P$2,$H$99:$O$99,0)=1,"n.a.",INDEX($H132:$O132,MATCH($P$2,$H$99:$O$99,0)-1)) -> -0.13088605
B133: Net profit growth | H133: n.a. | I133: =Output!G159 -> -0.029107655 | J133: =Output!H159 -> -0.17182746 | K133: =Output!I159 -> 0.025106148 | L133: =Output!J159 -> 0.043275417 | M133: =Output!K159 -> -0.0041394284 | N133: =Output!L159 -> 0.05999079 | O133: =Output!M159 -> 0.05779173 | P133: =INDEX($H133:$O133,MATCH($P$2,$H$99:$O$99,0)) -> 0.025106148 | Q133: =IF(MATCH($P$2,$H$99:$O$99,0)=1,"n.a.",INDEX($H133:$O133,MATCH($P$2,$H$99:$O$99,0)-1)) -> -0.17182746
B134: Operating costs incl. D&A (CHF m) | H134: =Output!F13+Output!F16 -> -28960 | I134: =Output!G13+Output!G16 -> -28326 | J134: =Output!H13+Output!H16 -> -28914 | K134: =Output!I13+Output!I16 -> -29193.696 | L134: =Output!J13+Output!J16 -> -29193.426 | M134: =Output!K13+Output!K16 -> -28917.376 | N134: =Output!L13+Output!L16 -> -29177.559 | O134: =Output!M13+Output!M16 -> -29830.994 | P134: =INDEX($H134:$O134,MATCH($P$2,$H$99:$O$99,0)) -> -29193.696 | Q134: =IF(MATCH($P$2,$H$99:$O$99,0)=1,"n.a.",INDEX($H134:$O134,MATCH($P$2,$H$99:$O$99,0)-1)) -> -28914
B135: Net interest (CHF m) | H135: =Output!F19 -> -1360 | I135: =Output!G19 -> -1485 | J135: =Output!H19 -> -1526 | K135: =Output!I19 -> -1521.958 | L135: =Output!J19 -> -1497.622 | M135: =Output!K19 -> -1467.4329 | N135: =Output!L19 -> -1441.2936 | O135: =Output!M19 -> -1413.5106 | P135: =INDEX($H135:$O135,MATCH($P$2,$H$99:$O$99,0)) -> -1521.958 | Q135: =IF(MATCH($P$2,$H$99:$O$99,0)=1,"n.a.",INDEX($H135:$O135,MATCH($P$2,$H$99:$O$99,0)-1)) -> -1526
B136: Income from associates (CHF m) | H136: =Output!F23 -> 1120 | I136: =Output!G23 -> 1249 | J136: =Output!H23 -> 1143 | K136: =Output!I23 -> 1177.29 | L136: =Output!J23 -> 1224.3816 | M136: =Output!K23 -> 1273.3569 | N136: =Output!L23 -> 1337.0247 | O136: =Output!M23 -> 1403.8759 | P136: =INDEX($H136:$O136,MATCH($P$2,$H$99:$O$99,0)) -> 1177.29 | Q136: =IF(MATCH($P$2,$H$99:$O$99,0)=1,"n.a.",INDEX($H136:$O136,MATCH($P$2,$H$99:$O$99,0)-1)) -> 1143
B137: Effective tax rate | H137: =Output!F101 -> 0.18216169 | I137: =Output!G101 -> 0.25032102 | J137: =Output!H101 -> 0.24555855 | K137: =Output!I101 -> 0.235 | L137: =Output!J101 -> 0.235 | M137: =Output!K101 -> 0.235 | N137: =Output!L101 -> 0.235 | O137: =Output!M101 -> 0.235 | P137: =INDEX($H137:$O137,MATCH($P$2,$H$99:$O$99,0)) -> 0.235 | Q137: =IF(MATCH($P$2,$H$99:$O$99,0)=1,"n.a.",INDEX($H137:$O137,MATCH($P$2,$H$99:$O$99,0)-1)) -> 0.24555855
B138: Asset turnover | H138: =Output!F113 -> 0.737661 | I138: =Output!G113 -> 0.65860524 | J138: =Output!H113 -> 0.7069154 | K138: =Output!I113 -> 0.71000559 | L138: =Output!J113 -> 0.71161604 | M138: =Output!K113 -> 0.70416457 | N138: =Output!L113 -> 0.70118549 | O138: =Output!M113 -> 0.71174453 | P138: =INDEX($H138:$O138,MATCH($P$2,$H$99:$O$99,0)) -> 0.71000559 | Q138: =IF(MATCH($P$2,$H$99:$O$99,0)=1,"n.a.",INDEX($H138:$O138,MATCH($P$2,$H$99:$O$99,0)-1)) -> 0.7069154
B139: Total assets / equity | H139: =Output!F132 -> 3.4778905 | I139: =Output!G132 -> 3.7953833 | J139: =Output!H132 -> 3.8463004 | K139: =Output!I132 -> 3.701442 | L139: =Output!J132 -> 3.5834102 | M139: =Output!K132 -> 3.501477 | N139: =Output!L132 -> 3.4162468 | O139: =Output!M132 -> 3.431136 | P139: =INDEX($H139:$O139,MATCH($P$2,$H$99:$O$99,0)) -> 3.701442 | Q139: =IF(MATCH($P$2,$H$99:$O$99,0)=1,"n.a.",INDEX($H139:$O139,MATCH($P$2,$H$99:$O$99,0)-1)) -> 3.8463004
B141: Revenue | H141: =Output!F9 -> 93351 | I141: =Output!G9 -> 91720 | J141: =Output!H9 -> 89885 | K141: =Output!I9 -> 90315.187 | L141: =Output!J9 -> 91679.044 | M141: =Output!K9 -> 92137.439 | N141: =Output!L9 -> 93989.546 | O141: =Output!M9 -> 96630.873 | P141: =INDEX($H141:$O141,MATCH($P$2,$H$99:$O$99,0)) -> 90315.187 | Q141: =IF(MATCH($P$2,$H$99:$O$99,0)=1,"n.a.",INDEX($H141:$O141,MATCH($P$2,$H$99:$O$99,0)-1)) -> 89885
B142: COGS | H142: =Output!F10 -> -50328 | I142: =Output!G10 -> -48670 | J142: =Output!H10 -> -48694 | K142: =Output!I10 -> -48738.04 | L142: =Output!J10 -> -49651.426 | M142: =Output!K10 -> -50533.633 | N142: =Output!L10 -> -51462.029 | O142: =Output!M10 -> -52775.864 | P142: =INDEX($H142:$O142,MATCH($P$2,$H$99:$O$99,0)) -> -48738.04 | Q142: =IF(MATCH($P$2,$H$99:$O$99,0)=1,"n.a.",INDEX($H142:$O142,MATCH($P$2,$H$99:$O$99,0)-1)) -> -48694
B143: SG&A | H143: =Output!F13 -> -25502 | I143: =Output!G13 -> -24744 | J143: =Output!H13 -> -25281 | K143: =Output!I13 -> -25748.156 | L143: =Output!J13 -> -25705.949 | M143: =Output!K13 -> -25394.802 | N143: =Output!L13 -> -25623.167 | O143: =Output!M13 -> -26191.856 | P143: =INDEX($H143:$O143,MATCH($P$2,$H$99:$O$99,0)) -> -25748.156 | Q143: =IF(MATCH($P$2,$H$99:$O$99,0)=1,"n.a.",INDEX($H143:$O143,MATCH($P$2,$H$99:$O$99,0)-1)) -> -25281
B144: Depre | H144: =Output!F16 -> -3458 | I144: =Output!G16 -> -3582 | J144: =Output!H16 -> -3633 | K144: =Output!I16 -> -3445.54 | L144: =Output!J16 -> -3487.477 | M144: =Output!K16 -> -3522.5745 | N144: =Output!L16 -> -3554.3919 | O144: =Output!M16 -> -3639.1378 | P144: =INDEX($H144:$O144,MATCH($P$2,$H$99:$O$99,0)) -> -3445.54 | Q144: =IF(MATCH($P$2,$H$99:$O$99,0)=1,"n.a.",INDEX($H144:$O144,MATCH($P$2,$H$99:$O$99,0)-1)) -> -3633
B145: Net Interest | H145: =Output!F19 -> -1360 | I145: =Output!G19 -> -1485 | J145: =Output!H19 -> -1526 | K145: =Output!I19 -> -1521.958 | L145: =Output!J19 -> -1497.622 | M145: =Output!K19 -> -1467.4329 | N145: =Output!L19 -> -1441.2936 | O145: =Output!M19 -> -1413.5106 | P145: =INDEX($H145:$O145,MATCH($P$2,$H$99:$O$99,0)) -> -1521.958 | Q145: =IF(MATCH($P$2,$H$99:$O$99,0)=1,"n.a.",INDEX($H145:$O145,MATCH($P$2,$H$99:$O$99,0)-1)) -> -1526
B146: Taxes | H146: =Output!F22 -> -2314 | I146: =Output!G22 -> -3314 | J146: =Output!H22 -> -2640 | K146: =Output!I22 -> -2552.4509 | L146: =Output!J22 -> -2664.0938 | M146: =Output!K22 -> -2636.4644 | N146: =Output!L22 -> -2798.536 | O146: =Output!M22 -> -2963.4685 | P146: =INDEX($H146:$O146,MATCH($P$2,$H$99:$O$99,0)) -> -2552.4509 | Q146: =IF(MATCH($P$2,$H$99:$O$99,0)=1,"n.a.",INDEX($H146:$O146,MATCH($P$2,$H$99:$O$99,0)-1)) -> -2640
B147: JV income | H147: =Output!F23 -> 1120 | I147: =Output!G23 -> 1249 | J147: =Output!H23 -> 1143 | K147: =Output!I23 -> 1177.29 | L147: =Output!J23 -> 1224.3816 | M147: =Output!K23 -> 1273.3569 | N147: =Output!L23 -> 1337.0247 | O147: =Output!M23 -> 1403.8759 | P147: =INDEX($H147:$O147,MATCH($P$2,$H$99:$O$99,0)) -> 1177.29 | Q147: =IF(MATCH($P$2,$H$99:$O$99,0)=1,"n.a.",INDEX($H147:$O147,MATCH($P$2,$H$99:$O$99,0)-1)) -> 1143
B148: Net Profit | H148: =Output!F24 -> 11509 | I148: =Output!G24 -> 11174 | J148: =Output!H24 -> 9254 | K148: =Output!I24 -> 9486.3323 | L148: =Output!J24 -> 9896.8573 | M148: =Output!K24 -> 9855.89 | N148: =Output!L24 -> 10447.153 | O148: =Output!M24 -> 11050.912 | P148: =INDEX($H148:$O148,MATCH($P$2,$H$99:$O$99,0)) -> 9486.3323 | Q148: =IF(MATCH($P$2,$H$99:$O$99,0)=1,"n.a.",INDEX($H148:$O148,MATCH($P$2,$H$99:$O$99,0)-1)) -> 9254
B150: Cost of goods sold | H150: =-Model!F257 -> 50328 | I150: =-Model!G257 -> 48670 | J150: =-Model!H257 -> 48694 | K150: =-Model!I257 -> 48738.04 | L150: =-Model!J257 -> 49651.426 | M150: =-Model!K257 -> 50533.633 | N150: =-Model!L257 -> 51462.029 | O150: =-Model!M257 -> 52775.864 | P150: =INDEX($H150:$O150,MATCH($P$2,$H$99:$O$99,0)) -> 48738.04 | Q150: =IF(MATCH($P$2,$H$99:$O$99,0)=1,"n.a.",INDEX($H150:$O150,MATCH($P$2,$H$99:$O$99,0)-1)) -> 48694
B151: Distribution expenses | H151: =-Model!F258 -> 7765 | I151: =-Model!G258 -> 7567 | J151: =-Model!H258 -> 7306 | K151: =-Model!I258 -> 7284.9335 | L151: =-Model!J258 -> 7348.5642 | M151: =-Model!K258 -> 7339.4355 | N151: =-Model!L258 -> 7439.4354 | O151: =-Model!M258 -> 7599.6406 | P151: =INDEX($H151:$O151,MATCH($P$2,$H$99:$O$99,0)) -> 7284.9335 | Q151: =IF(MATCH($P$2,$H$99:$O$99,0)=1,"n.a.",INDEX($H151:$O151,MATCH($P$2,$H$99:$O$99,0)-1)) -> 7306
B152: Marketing and administration expenses | H152: =-Model!F259 -> 17549 | I152: =-Model!G259 -> 18112 | J152: =-Model!H259 -> 17883 | K152: =-Model!I259 -> 17987.49 | L152: =-Model!J259 -> 18348.589 | M152: =-Model!K259 -> 18440.332 | N152: =-Model!L259 -> 18902.716 | O152: =-Model!M259 -> 19528.19 | P152: =INDEX($H152:$O152,MATCH($P$2,$H$99:$O$99,0)) -> 17987.49 | Q152: =IF(MATCH($P$2,$H$99:$O$99,0)=1,"n.a.",INDEX($H152:$O152,MATCH($P$2,$H$99:$O$99,0)-1)) -> 17883
B153: Research and development costs | H153: =-Model!F260 -> 1656 | I153: =-Model!G260 -> 1667 | J153: =-Model!H260 -> 1613 | K153: =-Model!I260 -> 1618.8741 | L153: =-Model!J260 -> 1643.1572 | M153: =-Model!K260 -> 1651.373 | N153: =-Model!L260 -> 1684.4005 | O153: =-Model!M260 -> 1731.5637 | P153: =INDEX($H153:$O153,MATCH($P$2,$H$99:$O$99,0)) -> 1618.8741 | Q153: =IF(MATCH($P$2,$H$99:$O$99,0)=1,"n.a.",INDEX($H153:$O153,MATCH($P$2,$H$99:$O$99,0)-1)) -> 1613
B154: Other trading expenses | H154: =-Model!F262 -> 1665 | I154: =-Model!G262 -> 1195 | J154: =-Model!H262 -> 1849 | K154: =-Model!I262 -> 2158.4988 | L154: =-Model!J262 -> 1734.4437 | M154: =-Model!K262 -> 1376.1442 | N154: =-Model!L262 -> 1076.1447 | O154: =-Model!M262 -> 913.88083 | P154: =INDEX($H154:$O154,MATCH($P$2,$H$99:$O$99,0)) -> 2158.4988 | Q154: =IF(MATCH($P$2,$H$99:$O$99,0)=1,"n.a.",INDEX($H154:$O154,MATCH($P$2,$H$99:$O$99,0)-1)) -> 1849
B155: Other operating expenses | H155: =-Model!F266 -> 755 | I155: =-Model!G266 -> 383 | J155: =-Model!H266 -> 651 | K155: =-Model!I266 -> 539.6247 | L155: =-Model!J266 -> 502.07581 | M155: =-Model!K266 -> 477.06331 | N155: =-Model!L266 -> 467.88902 | O155: =-Model!M266 -> 461.75031 | P155: =INDEX($H155:$O155,MATCH($P$2,$H$99:$O$99,0)) -> 539.6247 | Q155: =IF(MATCH($P$2,$H$99:$O$99,0)=1,"n.a.",INDEX($H155:$O155,MATCH($P$2,$H$99:$O$99,0)-1)) -> 651
B156: Financial expense | H156: =-Model!F270 -> 1644 | I156: =-Model!G270 -> 1843 | J156: =-Model!H270 -> 1826 | K156: =-Model!I270 -> 1677.708 | L156: =-Model!J270 -> 1644.1538 | M156: =-Model!K270 -> 1627.7123 | N156: =-Model!L270 -> 1627.7123 | O156: =-Model!M270 -> 1643.9894 | P156: =INDEX($H156:$O156,MATCH($P$2,$H$99:$O$99,0)) -> 1677.708 | Q156: =IF(MATCH($P$2,$H$99:$O$99,0)=1,"n.a.",INDEX($H156:$O156,MATCH($P$2,$H$99:$O$99,0)-1)) -> 1826
B157: Taxes | H157: =Model!F273*-1 -> 2314 | I157: =Model!G273*-1 -> 3314 | J157: =Model!H273*-1 -> 2640 | K157: =Model!I273*-1 -> 2552.4509 | L157: =Model!J273*-1 -> 2664.0938 | M157: =Model!K273*-1 -> 2636.4644 | N157: =Model!L273*-1 -> 2798.536 | O157: =Model!M273*-1 -> 2963.4685 | P157: =INDEX($H157:$O157,MATCH($P$2,$H$99:$O$99,0)) -> 2552.4509 | Q157: =IF(MATCH($P$2,$H$99:$O$99,0)=1,"n.a.",INDEX($H157:$O157,MATCH($P$2,$H$99:$O$99,0)-1)) -> 2640
B162: METHODOLOGY & NOTES
B164: Ratios use year-end balances (ROE, ROA, ROIC, turnover, leverage) so the DuPont identities reconcile exactly; ROE/ROA use profit for the year (incl. NCI) over total equity incl. NCI. All Check rows on the Output sheet equal zero.
B165: Interest-bearing debt = non-current + current financial debt + revolver. Net debt deducts cash only (not short-term investments) and uses reported EBITDA, so leverage reads c.0.5x above Nestlé's own definition (FY2025: 3.35x vs 2.85x reported).
B166: ROIC = EBIT × (1 − effective tax rate) ÷ (total equity + interest-bearing debt − cash). RONA = net profit ÷ (PP&E + receivables + inventory − payables). DSO on revenue incl. other revenue; DSI and DPO on COGS.
B167: Free cash flow = operating cash flow − capex − expenditure on intangibles, before lease repayments; not comparable with Nestlé's reported FCF (FY2025: CHF 11.0bn here vs CHF 9.2bn reported). A = actual (2023-2025), F = forecast under the selected scenario.
B168: Sensitivity grids are closed-form (no Data Tables) and recalculate with the model and the reporting-year selector. FCF grid: ΔEBITDA × (1 − tax rate), with capex, working capital and interest held constant. Cash grid: ΔDSO × revenue/365 and ΔDPO × COGS/365.

Sheet Output
B2: ="Nestlé S.A. | CHF millions | Scenario: "&INDEX(Input!$B$12:$B$14,ScenarioSwitch) -> Nestlé S.A. | CHF millions | Scenario: Base Case | F2: =G2-1 -> 2023 | G2: =H2-1 -> 2024 | H2: =I2-1 -> 2025 | I2: =Input!$I$2 -> 2026 | J2: =I2+1 -> 2027 | K2: =J2+1 -> 2028 | L2: =K2+1 -> 2029 | M2: =L2+1 -> 2030
B4: INCOME STATEMENT
B6: =Input!$B$131 -> All figures in CHF millions unless stated | F6: =F$2 -> 2023 | G6: =G$2 -> 2024 | H6: =H$2 -> 2025 | I6: =I$2 -> 2026 | J6: =J$2 -> 2027 | K6: =K$2 -> 2028 | L6: =L$2 -> 2029 | M6: =M$2 -> 2030
B7: =CONCATENATE("Model Running: ",INDEX(Input!$B$12:$B$14,Input!$D$6)," Drivers") -> Model Running: Base Case Drivers
B9: Revenue | F9: =Model!F255+Model!F256 -> 93351 | G9: =Model!G255+Model!G256 -> 91720 | H9: =Model!H255+Model!H256 -> 89885 | I9: =Model!I255+Model!I256 -> 90315.187 | J9: =Model!J255+Model!J256 -> 91679.044 | K9: =Model!K255+Model!K256 -> 92137.439 | L9: =Model!L255+Model!L256 -> 93989.546 | M9: =Model!M255+Model!M256 -> 96630.873
B10: Cost of Good Sold | F10: =Model!F257 -> -50328 | G10: =Model!G257 -> -48670 | H10: =Model!H257 -> -48694 | I10: =Model!I257 -> -48738.04 | J10: =Model!J257 -> -49651.426 | K10: =Model!K257 -> -50533.633 | L10: =Model!L257 -> -51462.029 | M10: =Model!M257 -> -52775.864
B11: Gross Profit | F11: =SUM(F9:F10) -> 43023 | G11: =SUM(G9:G10) -> 43050 | H11: =SUM(H9:H10) -> 41191 | I11: =SUM(I9:I10) -> 41577.147 | J11: =SUM(J9:J10) -> 42027.618 | K11: =SUM(K9:K10) -> 41603.806 | L11: =SUM(L9:L10) -> 42527.517 | M11: =SUM(M9:M10) -> 43855.009
B13: SG&A Expenses | F13: =SUM(Model!F258:F262)+SUM(Model!F265:F266)+Model!F288 -> -25502 | G13: =SUM(Model!G258:G262)+SUM(Model!G265:G266)+Model!G288 -> -24744 | H13: =SUM(Model!H258:H262)+SUM(Model!H265:H266)+Model!H288 -> -25281 | I13: =SUM(Model!I258:I262)+SUM(Model!I265:I266)+Model!I288 -> -25748.156 | J13: =SUM(Model!J258:J262)+SUM(Model!J265:J266)+Model!J288 -> -25705.949 | K13: =SUM(Model!K258:K262)+SUM(Model!K265:K266)+Model!K288 -> -25394.802 | L13: =SUM(Model!L258:L262)+SUM(Model!L265:L266)+Model!L288 -> -25623.167 | M13: =SUM(Model!M258:M262)+SUM(Model!M265:M266)+Model!M288 -> -26191.856
B14: EBITDA | F14: =F11+F13 -> 17521 | G14: =G11+G13 -> 18306 | H14: =H11+H13 -> 15910 | I14: =I11+I13 -> 15828.991 | J14: =J11+J13 -> 16321.669 | K14: =K11+K13 -> 16209.005 | L14: =L11+L13 -> 16904.349 | M14: =M11+M13 -> 17663.153
B16: Depreciation | F16: =Model!F288*-1 -> -3458 | G16: =Model!G288*-1 -> -3582 | H16: =Model!H288*-1 -> -3633 | I16: =Model!I288*-1 -> -3445.54 | J16: =Model!J288*-1 -> -3487.477 | K16: =Model!K288*-1 -> -3522.5745 | L16: =Model!L288*-1 -> -3554.3919 | M16: =Model!M288*-1 -> -3639.1378
B17: EBIT | F17: =F14+F16 -> 14063 | G17: =G14+G16 -> 14724 | H17: =H14+H16 -> 12277 | I17: =I14+I16 -> 12383.451 | J17: =J14+J16 -> 12834.192 | K17: =K14+K16 -> 12686.43 | L17: =L14+L16 -> 13349.957 | M17: =M14+M16 -> 14024.015
B19: Net Interest | F19: =SUM(Model!F269:F270) -> -1360 | G19: =SUM(Model!G269:G270) -> -1485 | H19: =SUM(Model!H269:H270) -> -1526 | I19: =SUM(Model!I269:I270) -> -1521.958 | J19: =SUM(Model!J269:J270) -> -1497.622 | K19: =SUM(Model!K269:K270) -> -1467.4329 | L19: =SUM(Model!L269:L270) -> -1441.2936 | M19: =SUM(Model!M269:M270) -> -1413.5106
B20: EBT | F20: =F17+F19 -> 12703 | G20: =G17+G19 -> 13239 | H20: =H17+H19 -> 10751 | I20: =I17+I19 -> 10861.493 | J20: =J17+J19 -> 11336.57 | K20: =K17+K19 -> 11218.998 | L20: =L17+L19 -> 11908.664 | M20: =M17+M19 -> 12610.504
B22: Taxes | F22: =Model!F273 -> -2314 | G22: =Model!G273 -> -3314 | H22: =Model!H273 -> -2640 | I22: =Model!I273 -> -2552.4509 | J22: =Model!J273 -> -2664.0938 | K22: =Model!K273 -> -2636.4644 | L22: =Model!L273 -> -2798.536 | M22: =Model!M273 -> -2963.4685
B23: Income from associates and joint ventures | F23: =Model!F274 -> 1120 | G23: =Model!G274 -> 1249 | H23: =Model!H274 -> 1143 | I23: =Model!I274 -> 1177.29 | J23: =Model!J274 -> 1224.3816 | K23: =Model!K274 -> 1273.3569 | L23: =Model!L274 -> 1337.0247 | M23: =Model!M274 -> 1403.8759
B24: Net Profit | F24: =SUM(F20:F23) -> 11509 | G24: =SUM(G20:G23) -> 11174 | H24: =SUM(H20:H23) -> 9254 | I24: =SUM(I20:I23) -> 9486.3323 | J24: =SUM(J20:J23) -> 9896.8573 | K24: =SUM(K20:K23) -> 9855.89 | L24: =SUM(L20:L23) -> 10447.153 | M24: =SUM(M20:M23) -> 11050.912
B26: NCI | F26: =Model!F277 -> 300 | G26: =Model!G277 -> 290 | H26: =Model!H277 -> 221 | I26: =Model!I277 -> 237.15831 | J26: =Model!J277 -> 247.42143 | K26: =Model!K277 -> 246.39725 | L26: =Model!L277 -> 261.17881 | M26: =Model!M277 -> 276.27279
B27: Parent | F27: =Model!F278 -> 11209 | G27: =Model!G278 -> 10884 | H27: =Model!H278 -> 9033 | I27: =Model!I278 -> 9249.174 | J27: =Model!J278 -> 9649.4359 | K27: =Model!K278 -> 9609.4927 | L27: =Model!L278 -> 10185.974 | M27: =Model!M278 -> 10774.639
B31: CASHFLOW STATEMENT
B33: =Input!$B$131 -> All figures in CHF millions unless stated | F33: =F$2 -> 2023 | G33: =G$2 -> 2024 | H33: =H$2 -> 2025 | I33: =I$2 -> 2026 | J33: =J$2 -> 2027 | K33: =K$2 -> 2028 | L33: =L$2 -> 2029 | M33: =M$2 -> 2030
B34: =CONCATENATE("Model Running: ",INDEX(Input!$B$12:$B$14,Input!$D$6)," Drivers") -> Model Running: Base Case Drivers
B36: Operating | F36: =Model!F302 -> 15941 | G36: =Model!G302 -> 16675 | H36: =Model!H302 -> 15904 | I36: =Model!I302 -> 13733.402 | J36: =Model!J302 -> 14174.144 | K36: =Model!K302 -> 14255.556 | L36: =Model!L302 -> 14599.324 | M36: =Model!M302 -> 14942.689
B37: Investing | F37: =Model!F313 -> -6196 | G37: =Model!G313 -> -8624 | H37: =Model!H313 -> -4367 | I37: =Model!I313 -> -4766.6848 | J37: =Model!J313 -> -4746.8986 | K37: =Model!K313 -> -4770.6331 | L37: =Model!L313 -> -4819.2569 | M37: =Model!M313 -> -4954.1961
B38: Financing | F38: =Model!F324 -> -9758 | G38: =Model!G324 -> -7362 | H38: =Model!H324 -> -12065 | I38: =Model!I324 -> -9335.4442 | J38: =Model!J324 -> -8877.3407 | K38: =Model!K324 -> -8439.3522 | L38: =Model!L324 -> -8017.6604 | M38: =Model!M324 -> -10152.276
B42: BALANCE SHEET
B44: =Input!$B$131 -> All figures in CHF millions unless stated | F44: =F$2 -> 2023 | G44: =G$2 -> 2024 | H44: =H$2 -> 2025 | I44: =I$2 -> 2026 | J44: =J$2 -> 2027 | K44: =K$2 -> 2028 | L44: =L$2 -> 2029 | M44: =M$2 -> 2030
B45: =CONCATENATE("Model Running: ",INDEX(Input!$B$12:$B$14,Input!$D$6)," Drivers") -> Model Running: Base Case Drivers
B47: Cash & Equivalents | F47: =Model!F341 -> 4816 | G47: =Model!G341 -> 5556 | H47: =Model!H341 -> 4579 | I47: =Model!I341 -> 4210.2724 | J47: =Model!J341 -> 4760.1772 | K47: =Model!K341 -> 5805.748 | L47: =Model!L341 -> 7568.1546 | M47: =Model!M341 -> 7404.3711
B48: Trade Receivable | F48: =Model!F344 -> 10995 | G48: =Model!G344 -> 11251 | H48: =Model!H344 -> 10561 | I48: =Model!I344 -> 10595.371 | J48: =Model!J344 -> 10754.301 | K48: =Model!K344 -> 10682.398 | L48: =Model!L344 -> 10767.857 | M48: =Model!M344 -> 11069.357
B49: Inventory | F49: =Model!F343 -> 11896 | G49: =Model!G343 -> 13260 | H49: =Model!H343 -> 12813 | I49: =Model!I343 -> 12418.185 | J49: =Model!J343 -> 12378.849 | K49: =Model!K343 -> 12321.899 | L49: =Model!L343 -> 12407.284 | M49: =Model!M343 -> 12579.452
B50: Other Current Assets | F50: =Model!F342+Model!F345+Model!F346+Model!F347+Model!F348 -> 3150 | G50: =Model!G342+Model!G345+Model!G346+Model!G347+Model!G348 -> 5121 | H50: =Model!H342+Model!H345+Model!H346+Model!H347+Model!H348 -> 4016 | I50: =Model!I342+Model!I345+Model!I346+Model!I347+Model!I348 -> 4029.8079 | J50: =Model!J342+Model!J345+Model!J346+Model!J347+Model!J348 -> 4037.2001 | K50: =Model!K342+Model!K345+Model!K346+Model!K347+Model!K348 -> 4039.7011 | L50: =Model!L342+Model!L345+Model!L346+Model!L347+Model!L348 -> 4049.7551 | M50: =Model!M342+Model!M345+Model!M346+Model!M347+Model!M348 -> 4064.1122
B51: Total Current Assets | F51: =SUM(F47:F50) -> 30857 | G51: =SUM(G47:G50) -> 35188 | H51: =SUM(H47:H50) -> 31969 | I51: =SUM(I47:I50) -> 31253.637 | J51: =SUM(J47:J50) -> 31930.527 | K51: =SUM(K47:K50) -> 32849.746 | L51: =SUM(L47:L50) -> 34793.05 | M51: =SUM(M47:M50) -> 35117.293
B53: PPE | F53: =Model!F352 -> 30467 | G53: =Model!G352 -> 33706 | H53: =Model!H352 -> 32549 | I53: =Model!I352 -> 34027.226 | J53: =Model!J352 -> 35444.623 | K53: =Model!K352 -> 36854.096 | L53: =Model!L352 -> 38231.02 | M53: =Model!M352 -> 39659.058
B54: Other Non-Current Assets | F54: =SUM(Model!F353:F359) -> 65226 | G54: =SUM(Model!G353:G359) -> 70370 | H54: =SUM(Model!H353:H359) -> 62633 | I54: =SUM(Model!I353:I359) -> 61922.626 | J54: =SUM(Model!J353:J359) -> 61457.027 | K54: =SUM(Model!K353:K359) -> 61142.614 | L54: =SUM(Model!L353:L359) -> 61019.698 | M54: =SUM(Model!M353:M359) -> 60989.88
B55: Total Non-Current Assets | F55: =SUM(F53:F54) -> 95693 | G55: =SUM(G53:G54) -> 104076 | H55: =SUM(H53:H54) -> 95182 | I55: =SUM(I53:I54) -> 95949.852 | J55: =SUM(J53:J54) -> 96901.65 | K55: =SUM(K53:K54) -> 97996.71 | L55: =SUM(L53:L54) -> 99250.718 | M55: =SUM(M53:M54) -> 100648.94
B56: Total Assets | F56: =F51+F55 -> 126550 | G56: =G51+G55 -> 139264 | H56: =H51+H55 -> 127151 | I56: =I51+I55 -> 127203.49 | J56: =J51+J55 -> 128832.18 | K56: =K51+K55 -> 130846.46 | L56: =L51+L55 -> 134043.77 | M56: =M51+M55 -> 135766.23
B58: Trade Payable | F58: =Model!F366 -> 19204 | G58: =Model!G366 -> 21807 | H58: =Model!H366 -> 20023 | I58: =Model!I366 -> 20029.331 | J58: =Model!J366 -> 20404.696 | K58: =Model!K366 -> 20767.246 | L58: =Model!L366 -> 21148.779 | M58: =Model!M366 -> 21688.711
B59: Other Current Liabilities | F59: =SUM(Model!F364:F365)+SUM(Model!F367:F371) -> 17880 | G59: =SUM(Model!G364:G365)+SUM(Model!G367:G371) -> 21056 | H59: =SUM(Model!H364:H365)+SUM(Model!H367:H371) -> 20671 | I59: =SUM(Model!I364:I365)+SUM(Model!I367:I371) -> 20170.147 | J59: =SUM(Model!J364:J365)+SUM(Model!J367:J371) -> 20156.854 | K59: =SUM(Model!K364:K365)+SUM(Model!K367:K371) -> 20253.534 | L59: =SUM(Model!L364:L365)+SUM(Model!L367:L371) -> 20608.524 | M59: =SUM(Model!M364:M365)+SUM(Model!M367:M371) -> 20869.484
B60: Total Current Liabilities | F60: =SUM(F58:F59) -> 37084 | G60: =SUM(G58:G59) -> 42863 | H60: =SUM(H58:H59) -> 40694 | I60: =SUM(I58:I59) -> 40199.478 | J60: =SUM(J58:J59) -> 40561.55 | K60: =SUM(K58:K59) -> 41020.781 | L60: =SUM(L58:L59) -> 41757.303 | M60: =SUM(M58:M59) -> 42558.196
B62: Financial Debt | F62: =Model!F375 -> 45825 | G62: =Model!G375 -> 51697 | H62: =Model!H375 -> 46246 | I62: =Model!I375 -> 45355.968 | J62: =Model!J375 -> 44902.408 | K62: =Model!K375 -> 44902.408 | L62: =Model!L375 -> 45351.432 | M62: =Model!M375 -> 45804.947
B63: Other Non-Current Liabilities | F63: =SUM(Model!F376:F380) -> 7254 | G63: =SUM(Model!G376:G380) -> 8011 | H63: =SUM(Model!H376:H380) -> 7153 | I63: =SUM(Model!I376:I380) -> 7282.1138 | J63: =SUM(Model!J376:J380) -> 7415.8249 | K63: =SUM(Model!K376:K380) -> 7554.3354 | L63: =SUM(Model!L376:L380) -> 7697.8885 | M63: =SUM(Model!M376:M380) -> 7834.2021
B64: Total Non-Current Liabilities | F64: =SUM(F62:F63) -> 53079 | G64: =SUM(G62:G63) -> 59708 | H64: =SUM(H62:H63) -> 53399 | I64: =SUM(I62:I63) -> 52638.082 | J64: =SUM(J62:J63) -> 52318.233 | K64: =SUM(K62:K63) -> 52456.744 | L64: =SUM(L62:L63) -> 53049.321 | M64: =SUM(M62:M63) -> 53639.149
B65: Total Liabilities | F65: =F64+F60 -> 90163 | G65: =G64+G60 -> 102571 | H65: =H64+H60 -> 94093 | I65: =I64+I60 -> 92837.56 | J65: =J64+J60 -> 92879.783 | K65: =K64+K60 -> 93477.524 | L65: =L64+L60 -> 94806.624 | M65: =M64+M60 -> 96197.344
B67: Equity attributable to shareholders (Parent) | F67: =Model!F390 -> 35742 | G67: =Model!G390 -> 35917 | H67: =Model!H390 -> 32810 | I67: =Model!I390 -> 34058.638 | J67: =Model!J390 -> 35583.249 | K67: =Model!K390 -> 36938.188 | L67: =Model!L390 -> 38741.105 | M67: =Model!M390 -> 39003.779
B68: Non-controlling interests | F68: =Model!F391 -> 645 | G68: =Model!G391 -> 776 | H68: =Model!H391 -> 248 | I68: =Model!I391 -> 307.28958 | J68: =Model!J391 -> 369.14493 | K68: =Model!K391 -> 430.74425 | L68: =Model!L391 -> 496.03895 | M68: =Model!M391 -> 565.10715
B69: Total equity | F69: =SUM(F67:F68) -> 36387 | G69: =SUM(G67:G68) -> 36693 | H69: =SUM(H67:H68) -> 33058 | I69: =SUM(I67:I68) -> 34365.928 | J69: =SUM(J67:J68) -> 35952.394 | K69: =SUM(K67:K68) -> 37368.932 | L69: =SUM(L67:L68) -> 39237.144 | M69: =SUM(M67:M68) -> 39568.886
B70: Total liabilities and equity | F70: =F69+F65 -> 126550 | G70: =G69+G65 -> 139264 | H70: =H69+H65 -> 127151 | I70: =I69+I65 -> 127203.49 | J70: =J69+J65 -> 128832.18 | K70: =K69+K65 -> 130846.46 | L70: =L69+L65 -> 134043.77 | M70: =M69+M65 -> 135766.23
B74: Profitability & Return Ratio
B76: =Input!$B$131 -> All figures in CHF millions unless stated | F76: =F$2 -> 2023 | G76: =G$2 -> 2024 | H76: =H$2 -> 2025 | I76: =I$2 -> 2026 | J76: =J$2 -> 2027 | K76: =K$2 -> 2028 | L76: =L$2 -> 2029 | M76: =M$2 -> 2030
B77: =CONCATENATE("Model Running: ",INDEX(Input!$B$12:$B$14,Input!$D$6)," Drivers") -> Model Running: Base Case Drivers
B79: ROE | F79: =F24/F69 -> 0.31629428 | G79: =G24/G69 -> 0.30452675 | H79: =H24/H69 -> 0.27993224 | I79: =I24/I69 -> 0.27603888 | J79: =J24/J69 -> 0.27527672 | K79: =K24/K69 -> 0.26374556 | L79: =L24/L69 -> 0.2662567 | M79: =M24/M69 -> 0.27928286
B80: ROA | F80: =F24/F56 -> 0.090944291 | G80: =G24/G56 -> 0.080236098 | H80: =H24/H56 -> 0.072779608 | I80: =I24/I56 -> 0.074576039 | J80: =J24/J56 -> 0.076819763 | K80: =K24/K56 -> 0.075324088 | L80: =L24/L56 -> 0.077938368 | M80: =M24/M56 -> 0.081396615
B81: Return on Net Assets | F81: =F24/(F53+F48+F49-F58) -> 0.33697371 | G81: =G24/(G53+G48+G49-G58) -> 0.30689371 | H81: =H24/(H53+H48+H49-H58) -> 0.25777159 | I81: =I24/(I53+I48+I49-I58) -> 0.25630804 | J81: =J24/(J53+J48+J49-J58) -> 0.25926276 | K81: =K24/(K53+K48+K49-K58) -> 0.25212588 | L81: =L24/(L53+L48+L49-L58) -> 0.259509 | M81: =M24/(M53+M48+M49-M58) -> 0.26552465
B82: Return on Invested Capital | F82: =F17*(1-F101)/(F69+(F62+Model!F364+Model!F371)-F47) -> 0.13248468 | G82: =G17*(1-G101)/(G69+(G62+Model!G364+Model!G371)-G47) -> 0.11656413 | H82: =H17*(1-H101)/(H69+(H62+Model!H364+Model!H371)-H47) -> 0.10728797 | I82: =I17*(1-I101)/(I69+(I62+Model!I364+Model!I371)-I47) -> 0.10907626 | J82: =J17*(1-J101)/(J69+(J62+Model!J364+Model!J371)-J47) -> 0.11243851 | K82: =K17*(1-K101)/(K69+(K62+Model!K364+Model!K371)-K47) -> 0.11067382 | L82: =L17*(1-L101)/(L69+(L62+Model!L364+Model!L371)-L47) -> 0.11558303 | M82: =M17*(1-M101)/(M69+(M62+Model!M364+Model!M371)-M47) -> 0.11997637
B83: Gross Margin | F83: =F11/F9 -> 0.46087348 | G83: =G11/G9 -> 0.46936328 | H83: =H11/H9 -> 0.45826334 | I83: =I11/I9 -> 0.4603561 | J83: =J11/J9 -> 0.45842121 | K83: =K11/K9 -> 0.45154073 | L83: =L11/L9 -> 0.45247071 | M83: =M11/M9 -> 0.45384055
B84: SG&A % of Revenue | F84: =-(SUM(Model!F258:F262)+Model!F288)/F9 -> 0.2682885 | G84: =-(SUM(Model!G258:G262)+Model!G288)/G9 -> 0.27076973 | H84: =-(SUM(Model!H258:H262)+Model!H288)/H9 -> 0.27683151 | I84: =-(SUM(Model!I258:I262)+Model!I288)/I9 -> 0.28210476 | J84: =-(SUM(Model!J258:J262)+Model!J288)/J9 -> 0.27770224 | K84: =-(SUM(Model!K258:K262)+Model!K288)/K9 -> 0.27312941 | L84: =-(SUM(Model!L258:L262)+Model!L288)/L9 -> 0.27042684 | M84: =-(SUM(Model!M258:M262)+Model!M288)/M9 -> 0.26905956
B85: Other Operating Expenses % of Revenue | F85: =-SUM(Model!F265:F266)/F9 -> 0.0048955019 | G85: =-SUM(Model!G265:G266)/G9 -> -0.00099215002 | H85: =-SUM(Model!H265:H266)/H9 -> 0.0044278801 | I85: =-SUM(Model!I265:I266)/I9 -> 0.0029874527 | J85: =-SUM(Model!J265:J266)/J9 -> 0.0026884397 | K85: =-SUM(Model!K265:K266)/K9 -> 0.002489296 | L85: =-SUM(Model!L265:L266)/L9 -> 0.0021903624 | M85: =-SUM(Model!M265:M266)/M9 -> 0.0019910403
B86: EBITDA Margin | F86: =F14/F9 -> 0.18768947 | G86: =G14/G9 -> 0.1995857 | H86: =H14/H9 -> 0.17700395 | I86: =I14/I9 -> 0.17526389 | J86: =J14/J9 -> 0.17803053 | K86: =K14/K9 -> 0.17592203 | L86: =L14/L9 -> 0.17985351 | M86: =M14/M9 -> 0.18278995
B87: Check | F87: =ROUND(F83-F84-F85-F86,6) -> 0 | G87: =ROUND(G83-G84-G85-G86,6) -> 0 | H87: =ROUND(H83-H84-H85-H86,6) -> 0 | I87: =ROUND(I83-I84-I85-I86,6) -> 0 | J87: =ROUND(J83-J84-J85-J86,6) -> 0 | K87: =ROUND(K83-K84-K85-K86,6) -> 0 | L87: =ROUND(L83-L84-L85-L86,6) -> 0 | M87: =ROUND(M83-M84-M85-M86,6) -> 0
B89: Depreciation % of Revenue | F89: =-F16/F9 -> 0.037042988 | G89: =-G16/G9 -> 0.039053642 | H89: =-H16/H9 -> 0.040418312 | I89: =-I16/I9 -> 0.038150173 | J89: =-J16/J9 -> 0.038040067 | K89: =-K16/K9 -> 0.038231739 | L89: =-L16/L9 -> 0.037816885 | M89: =-M16/M9 -> 0.037660198
B90: EBIT Margin | F90: =F17/F9 -> 0.15064648 | G90: =G17/G9 -> 0.16053205 | H90: =H17/H9 -> 0.13658564 | I90: =I17/I9 -> 0.13711372 | J90: =J17/J9 -> 0.13999046 | K90: =K17/K9 -> 0.13769029 | L90: =L17/L9 -> 0.14203662 | M90: =M17/M9 -> 0.14512975
B91: Check | F91: =ROUND(F86-F89-F90,6) -> 0 | G91: =ROUND(G86-G89-G90,6) -> 0 | H91: =ROUND(H86-H89-H90,6) -> 0 | I91: =ROUND(I86-I89-I90,6) -> 0 | J91: =ROUND(J86-J89-J90,6) -> 0 | K91: =ROUND(K86-K89-K90,6) -> 0 | L91: =ROUND(L86-L89-L90,6) -> 0 | M91: =ROUND(M86-M89-M90,6) -> 0
B93: Other Non Operating Expense % of Revenue | F93: =-F19/F9 -> 0.014568671 | G93: =-G19/G9 -> 0.01619058 | H93: =-H19/H9 -> 0.016977249 | I93: =-I19/I9 -> 0.016851629 | J93: =-J19/J9 -> 0.016335489 | K93: =-K19/K9 -> 0.015926565 | L93: =-L19/L9 -> 0.015334616 | M93: =-M19/M9 -> 0.01462794
B94: EBT Margin | F94: =F20/F9 -> 0.13607781 | G94: =G20/G9 -> 0.14434147 | H94: =H20/H9 -> 0.11960839 | I94: =I20/I9 -> 0.12026209 | J94: =J20/J9 -> 0.12365497 | K94: =K20/K9 -> 0.12176372 | L94: =L20/L9 -> 0.12670201 | M94: =M20/M9 -> 0.13050181
B95: Check | F95: =ROUND(F90-F93-F94,6) -> 0 | G95: =ROUND(G90-G93-G94,6) -> 0 | H95: =ROUND(H90-H93-H94,6) -> 0 | I95: =ROUND(I90-I93-I94,6) -> 0 | J95: =ROUND(J90-J93-J94,6) -> 0 | K95: =ROUND(K90-K93-K94,6) -> 0 | L95: =ROUND(L90-L93-L94,6) -> 0 | M95: =ROUND(M90-M93-M94,6) -> 0
B97: Tax % of Revenue | F97: =-F22/F9 -> 0.024788165 | G97: =-G22/G9 -> 0.036131705 | H97: =-H22/H9 -> 0.029370863 | I97: =-I22/I9 -> 0.028261591 | J97: =-J22/J9 -> 0.029058918 | K97: =-K22/K9 -> 0.028614475 | L97: =-L22/L9 -> 0.029774971 | M97: =-M22/M9 -> 0.030667926
B98: Net Profit Margin | F98: =F24/F9 -> 0.12328738 | G98: =G24/G9 -> 0.1218273 | H98: =H24/H9 -> 0.10295377 | I98: =I24/I9 -> 0.10503585 | J98: =J24/J9 -> 0.10795114 | K98: =K24/K9 -> 0.10696944 | L98: =L24/L9 -> 0.11115228 | M98: =M24/M9 -> 0.11436212
B99: Check | F99: =ROUND(F94-F97+F23/F9-F98,6) -> 0 | G99: =ROUND(G94-G97+G23/G9-G98,6) -> 0 | H99: =ROUND(H94-H97+H23/H9-H98,6) -> 0 | I99: =ROUND(I94-I97+I23/I9-I98,6) -> 0 | J99: =ROUND(J94-J97+J23/J9-J98,6) -> 0 | K99: =ROUND(K94-K97+K23/K9-K98,6) -> 0 | L99: =ROUND(L94-L97+L23/L9-L98,6) -> 0 | M99: =ROUND(M94-M97+M23/M9-M98,6) -> 0
B101: Effective Tax Rate | F101: =-F22/F20 -> 0.18216169 | G101: =-G22/G20 -> 0.25032102 | H101: =-H22/H20 -> 0.24555855 | I101: =-I22/I20 -> 0.235 | J101: =-J22/J20 -> 0.235 | K101: =-K22/K20 -> 0.235 | L101: =-L22/L20 -> 0.235 | M101: =-M22/M20 -> 0.235
B102: Tax Burden | F102: =F24/F20 -> 0.90600646 | G102: =G24/G20 -> 0.84402145 | H102: =H24/H20 -> 0.86075714 | I102: =I24/I20 -> 0.87339117 | J102: =J24/J20 -> 0.87300283 | K102: =K24/K20 -> 0.87850006 | L102: =L24/L20 -> 0.87727328 | M102: =M24/M20 -> 0.87632592
B103: Effective Interest Rate | F103: =-Model!F270/(F62+Model!F364+Model!F371) -> 0.029760504 | G103: =-Model!G270/(G62+Model!G364+Model!G371) -> 0.028996224 | H103: =-Model!H270/(H62+Model!H364+Model!H371) -> 0.031563299 | I103: =-Model!I270/(I62+Model!I364+Model!I371) -> 0.029591837 | J103: =-Model!J270/(J62+Model!J364+Model!J371) -> 0.029292929 | K103: =-Model!K270/(K62+Model!K364+Model!K371) -> 0.029 | L103: =-Model!L270/(L62+Model!L364+Model!L371) -> 0.028712871 | M103: =-Model!M270/(M62+Model!M364+Model!M371) -> 0.028712871
B104: Interest Burden | F104: =F20/F17 -> 0.90329233 | G104: =G20/G17 -> 0.89914425 | H104: =H20/H17 -> 0.87570253 | I104: =I20/I17 -> 0.87709743 | J104: =J20/J17 -> 0.88330998 | K104: =K20/K17 -> 0.88433051 | L104: =L20/L17 -> 0.89203759 | M104: =M20/M17 -> 0.89920785
B108: Asset Utilization Ratios
B110: =Input!$B$131 -> All figures in CHF millions unless stated | F110: =F$2 -> 2023 | G110: =G$2 -> 2024 | H110: =H$2 -> 2025 | I110: =I$2 -> 2026 | J110: =J$2 -> 2027 | K110: =K$2 -> 2028 | L110: =L$2 -> 2029 | M110: =M$2 -> 2030
B111: =CONCATENATE("Model Running: ",INDEX(Input!$B$12:$B$14,Input!$D$6)," Drivers") -> Model Running: Base Case Drivers
B113: Asset Turnover | F113: =F9/F56 -> 0.737661 | G113: =G9/G56 -> 0.65860524 | H113: =H9/H56 -> 0.7069154 | I113: =I9/I56 -> 0.71000559 | J113: =J9/J56 -> 0.71161604 | K113: =K9/K56 -> 0.70416457 | L113: =L9/L56 -> 0.70118549 | M113: =M9/M56 -> 0.71174453
B114: PPE Turnover | F114: =F9/F53 -> 3.0640037 | G114: =G9/G53 -> 2.7211772 | H114: =H9/H53 -> 2.7615288 | I114: =I9/I53 -> 2.6542036 | J114: =J9/J53 -> 2.5865431 | K114: =K9/K53 -> 2.5000597 | L114: =L9/L53 -> 2.4584629 | M114: =M9/M53 -> 2.4365398
B115: Cash Turnover | F115: =F9/F47 -> 19.383513 | G115: =G9/G47 -> 16.508279 | H115: =H9/H47 -> 19.629832 | I115: =I9/I47 -> 21.451151 | J115: =J9/J47 -> 19.259586 | K115: =K9/K47 -> 15.870038 | L115: =L9/L47 -> 12.419084 | M115: =M9/M47 -> 13.050517
B116: Cash Days | F116: =F47*365/F9 -> 18.830436 | G116: =G47*365/G9 -> 22.110118 | H116: =H47*365/H9 -> 18.594148 | I116: =I47*365/I9 -> 17.015404 | J116: =J47*365/J9 -> 18.951601 | K116: =K47*365/K9 -> 22.999315 | L116: =L47*365/L9 -> 29.390252 | M116: =M47*365/M9 -> 27.96824
B117: A/R Turnover | F117: =F9/F48 -> 8.4903138 | G117: =G9/G48 -> 8.1521643 | H117: =H9/H48 -> 8.5110312 | I117: =I9/I48 -> 8.5240233 | J117: =J9/J48 -> 8.5248721 | K117: =K9/K48 -> 8.6251647 | L117: =L9/L48 -> 8.7287143 | M117: =M9/M48 -> 8.7295833
B118: A/R Days | F118: =F48*365/F9 -> 42.990166 | G118: =G48*365/G9 -> 44.773386 | H118: =H48*365/H9 -> 42.88552 | I118: =I48*365/I9 -> 42.820155 | J118: =J48*365/J9 -> 42.815892 | K118: =K48*365/K9 -> 42.318032 | L118: =L48*365/L9 -> 41.81601 | M118: =M48*365/M9 -> 41.811847
B119: Inventory Turnover | F119: =-F10/F49 -> 4.2306658 | G119: =-G10/G49 -> 3.6704374 | H119: =-H10/H49 -> 3.800359 | I119: =-I10/I49 -> 3.9247312 | J119: =-J10/J49 -> 4.010989 | K119: =-K10/K49 -> 4.1011236 | L119: =-L10/L49 -> 4.1477273 | M119: =-M10/M49 -> 4.1954023
B120: Inventory Days | F120: =-F49*365/F10 -> 86.274837 | G120: =-G49*365/G10 -> 99.443189 | H120: =-H49*365/H10 -> 96.043558 | I120: =-I49*365/I10 -> 93 | J120: =-J49*365/J10 -> 91 | K120: =-K49*365/K10 -> 89 | L120: =-L49*365/L10 -> 88 | M120: =-M49*365/M10 -> 87
B121: A/P Turnover | F121: =-F10/F58 -> 2.620704 | G121: =-G10/G58 -> 2.2318522 | H121: =-H10/H58 -> 2.4319033 | I121: =-I10/I58 -> 2.4333333 | J121: =-J10/J58 -> 2.4333333 | K121: =-K10/K58 -> 2.4333333 | L121: =-L10/L58 -> 2.4333333 | M121: =-M10/M58 -> 2.4333333
B122: A/P Days | F122: =-F58*365/F10 -> 139.27555 | G122: =-G58*365/G10 -> 163.5413 | H122: =-H58*365/H10 -> 150.0882 | I122: =-I58*365/I10 -> 150 | J122: =-J58*365/J10 -> 150 | K122: =-K58*365/K10 -> 150 | L122: =-L58*365/L10 -> 150 | M122: =-M58*365/M10 -> 150
B123: Cash Conversion Cycle / WC Funding Gap | F123: =F118+F120-F122 -> -10.010549 | G123: =G118+G120-G122 -> -19.324723 | H123: =H118+H120-H122 -> -11.159126 | I123: =I118+I120-I122 -> -14.179845 | J123: =J118+J120-J122 -> -16.184108 | K123: =K118+K120-K122 -> -18.681968 | L123: =L118+L120-L122 -> -20.18399 | M123: =M118+M120-M122 -> -21.188153
B127: Leverage Ratios
B129: =Input!$B$131 -> All figures in CHF millions unless stated | F129: =F$2 -> 2023 | G129: =G$2 -> 2024 | H129: =H$2 -> 2025 | I129: =I$2 -> 2026 | J129: =J$2 -> 2027 | K129: =K$2 -> 2028 | L129: =L$2 -> 2029 | M129: =M$2 -> 2030
B130: =CONCATENATE("Model Running: ",INDEX(Input!$B$12:$B$14,Input!$D$6)," Drivers") -> Model Running: Base Case Drivers
B132: Total Asset to Equity | F132: =F56/F69 -> 3.4778905 | G132: =G56/G69 -> 3.7953833 | H132: =H56/H69 -> 3.8463004 | I132: =I56/I69 -> 3.701442 | J132: =J56/J69 -> 3.5834102 | K132: =K56/K69 -> 3.501477 | L132: =L56/L69 -> 3.4162468 | M132: =M56/M69 -> 3.431136
B133: Total Liabilities to Equity | F133: =F65/F69 -> 2.4778905 | G133: =G65/G69 -> 2.7953833 | H133: =H65/H69 -> 2.8463004 | I133: =I65/I69 -> 2.701442 | J133: =J65/J69 -> 2.5834102 | K133: =K65/K69 -> 2.501477 | L133: =L65/L69 -> 2.4162468 | M133: =M65/M69 -> 2.431136
B134: Debt to Equity | F134: =(F62+Model!F364+Model!F371)/F69 -> 1.5181521 | G134: =(G62+Model!G364+Model!G371)/G69 -> 1.7322105 | H134: =(H62+Model!H364+Model!H371)/H69 -> 1.7500151 | I134: =(I62+Model!I364+Model!I371)/I69 -> 1.6497433 | J134: =(J62+Model!J364+Model!J371)/J69 -> 1.5611759 | K134: =(K62+Model!K364+Model!K371)/K69 -> 1.5019966 | L134: =(L62+Model!L364+Model!L371)/L69 -> 1.4447864 | M134: =(M62+Model!M364+Model!M371)/M69 -> 1.4470001
B135: Debt to EBITDA | F135: =(F62+Model!F364+Model!F371)/F14 -> 3.1528452 | G135: =(G62+Model!G364+Model!G371)/G14 -> 3.4720857 | H135: =(H62+Model!H364+Model!H371)/H14 -> 3.6362036 | I135: =(I62+Model!I364+Model!I371)/I14 -> 3.5817166 | J135: =(J62+Model!J364+Model!J371)/J14 -> 3.4388647 | K135: =(K62+Model!K364+Model!K371)/K14 -> 3.4627672 | L135: =(L62+Model!L364+Model!L371)/L14 -> 3.3535328 | M135: =(M62+Model!M364+Model!M371)/M14 -> 3.2415608
B136: Net Debt to EBITDA | F136: =((F62+Model!F364+Model!F371)-F47)/F14 -> 2.877975 | G136: =((G62+Model!G364+Model!G371)-G47)/G14 -> 3.1685786 | H136: =((H62+Model!H364+Model!H371)-H47)/H14 -> 3.3483972 | I136: =((I62+Model!I364+Model!I371)-I47)/I14 -> 3.3157317 | J136: =((J62+Model!J364+Model!J371)-J47)/J14 -> 3.147217 | K136: =((K62+Model!K364+Model!K371)-K47)/K14 -> 3.1045868 | L136: =((L62+Model!L364+Model!L371)-L47)/L14 -> 2.9058282 | M136: =((M62+Model!M364+Model!M371)-M47)/M14 -> 2.8223621
B140: Liquidity Ratios
B142: =Input!$B$131 -> All figures in CHF millions unless stated | F142: =F$2 -> 2023 | G142: =G$2 -> 2024 | H142: =H$2 -> 2025 | I142: =I$2 -> 2026 | J142: =J$2 -> 2027 | K142: =K$2 -> 2028 | L142: =L$2 -> 2029 | M142: =M$2 -> 2030
B143: =CONCATENATE("Model Running: ",INDEX(Input!$B$12:$B$14,Input!$D$6)," Drivers") -> Model Running: Base Case Drivers
B145: Current | F145: =F51/F60 -> 0.83208392 | G145: =G51/G60 -> 0.82094114 | H145: =H51/H60 -> 0.78559493 | I145: =I51/I60 -> 0.77746373 | J145: =J51/J60 -> 0.78721172 | K145: =K51/K60 -> 0.80080743 | L145: =L51/L60 -> 0.83322072 | M145: =M51/M60 -> 0.82515934
B146: Quick | F146: =(F51-F49)/F60 -> 0.51129867 | G146: =(G51-G49)/G60 -> 0.51158342 | H146: =(H51-H49)/H60 -> 0.47073279 | I146: =(I51-I49)/I60 -> 0.46854964 | J146: =(J51-J49)/J60 -> 0.48202494 | K146: =(K51-K49)/K60 -> 0.50042555 | L146: =(L51-L49)/L60 -> 0.53609224 | M146: =(M51-M49)/M60 -> 0.52957697
B147: Interest Coverage | F147: =F14/(-Model!F270) -> 10.657543 | G147: =G14/(-Model!G270) -> 9.9327184 | H147: =H14/(-Model!H270) -> 8.713034 | I147: =I14/(-Model!I270) -> 9.4348905 | J147: =J14/(-Model!J270) -> 9.9270933 | K147: =K14/(-Model!K270) -> 9.958151 | L147: =L14/(-Model!L270) -> 10.385342 | M147: =M14/(-Model!M270) -> 10.744079
...

Sheet Input
B2: ="Nestlé S.A. | CHF millions | Scenario: "&INDEX(Input!$B$12:$B$14,Input!$D$6) -> Nestlé S.A. | CHF millions | Scenario: Base Case | I2: =F173 -> 2026 | J2: =I2+1 -> 2027 | K2: =J2+1 -> 2028 | L2: =K2+1 -> 2029 | M2: =L2+1 -> 2030 | O2: Justification / basis of assumption
B4: Growth & Margin Drivers
C6: Model Running: | D6: =Dashboard!$F$2 -> 2
B8: All figures in CHF millions unless stated | I8: =I$2 -> 2026 | J8: =J$2 -> 2027 | K8: =K$2 -> 2028 | L8: =L$2 -> 2029 | M8: =M$2 -> 2030
B10: Sales growth, % YoY | I10: =INDEX(I12:I14,$D$6) -> 0.005 | J10: =INDEX(J12:J14,$D$6) -> 0.015 | K10: =INDEX(K12:K14,$D$6) -> 0.005 | L10: =INDEX(L12:L14,$D$6) -> 0.02 | M10: =INDEX(M12:M14,$D$6) -> 0.028
B12: Best Case | I12: 0.025 | J12: 0.035 | K12: 0.04 | L12: 0.045 | M12: 0.05 | O12: Best Case: reported sales growth converges toward the organic growth guidance (3–4% for 2026) as the c.3% FX headwind from a strong CHF and the 2025–26 portfolio exits (Waters JV, VMS, ice cream) roll off, building to 5% by 2030. Source: Nestlé H1 2026 results and FY2026 guidance.
B13: Base Case | I13: 0.005 | J13: 0.015 | K13: 0.005 | L13: 0.02 | M13: 0.028 | O13: Base Case: 2026 +0.5% = organic growth guidance of 3–4% less a c.3% FX headwind at spot rates (H1 2026 guidance); 2027 +1.5% as FX normalises; 2028 slows under an assumed mild global slowdown; 2029–30 returns toward the organic trend (2.0–2.8%). The Waters deconsolidation into the Peranel JV (FY2025 sales CHF 3.5bn, closing H1 2027) is not modelled separately and would lower 2027 reported sales by up to c.4pp.
B14: Worst Case | I14: -0.015 | J14: -0.01 | K14: -0.055 | L14: -0.03 | M14: 0.005 | O14: Worst Case: a demand and macro shock in 2028–29 (–5.5% and –3.0%), sized on the roughly ten-year cadence of past global stress events (1998, 2008, 2020). Consumer staples are assumed to decline less than cyclical sectors, with stabilisation in 2030.
B17: Other revenue, % of sales | I17: =INDEX(I19:I21,$D$6) -> 0.0042 | J17: =INDEX(J19:J21,$D$6) -> 0.0043 | K17: =INDEX(K19:K21,$D$6) -> 0.0043 | L17: =INDEX(L19:L21,$D$6) -> 0.0044 | M17: =INDEX(M19:M21,$D$6) -> 0.0045
B19: 1 | I19: 0.0042 | J19: 0.0044 | K19: 0.0046 | L19: 0.0048 | M19: 0.005 | O19: Other revenue (royalty and licensing-type income) as % of sales. FY23–25 range 0.38–0.44%; the Best Case trends gently upward with stronger sales momentum.
B20: 2 | I20: 0.0042 | J20: 0.0043 | K20: 0.0043 | L20: 0.0044 | M20: 0.0045 | O20: Held at 0.42–0.45% of sales, close to the FY2025 level (0.44%) and slightly above the FY23–25 average (0.41%).
B21: 3 | I21: 0.0038 | J21: 0.0035 | K21: 0.003 | L21: 0.0033 | M21: 0.0036 | O21: Compressed during the 2028–29 downturn on lower royalty and licensing volumes, recovering partially by 2030.
B24: COGS | I24: =INDEX(I26:I28,$D$6) -> 0.00090441985 | J24: =INDEX(J26:J28,$D$6) -> 0.018740719 | K24: =INDEX(K26:K28,$D$6) -> 0.017768006 | L24: =INDEX(L26:L28,$D$6) -> 0.018371853 | M24: =INDEX(M26:M28,$D$6) -> 0.025530179
B26: Best Case | I26: 0.015082154 | J26: 0.028739312 | K26: 0.030626201 | L26: 0.034982241 | M26: 0.035676958 | O26: COGS is projected as a growth rate on the prior year and is the main lever for the gross-margin path. In the Best Case COGS grows slower than sales, supported by 'Fuel for Growth' procurement savings (CHF 3bn gross savings target by end-2027) and easing cocoa and coffee costs.
B27: Base Case | I27: 0.00090441985 | J27: 0.018740719 | K27: 0.017768006 | L27: 0.018371853 | M27: 0.025530179 | O27: Calibrated so that the EBITDA margin moves from 17.5% (2026) to 18.3% (2030), recovering above the FY2025 level (17.7%) but staying below FY2024 (20.0%), as coffee and cocoa cost relief and 'Fuel for Growth' savings are partly reinvested.
B28: Worst Case | I28: -0.010364991 | J28: 0.00033932446 | K28: -0.052572217 | L28: -0.0018388641 | M28: -5.4555294e-05 | O28: In the 2028 shock year COGS falls less than sales (–5.3% vs –5.5%): input costs and FX stay elevated while volumes soften, the typical operating-deleverage pattern for consumer staples in a downturn.
B31: Distribution expenses | I31: =INDEX(I33:I35,$D$6) -> 0.081 | J31: =INDEX(J33:J35,$D$6) -> 0.0805 | K31: =INDEX(K33:K35,$D$6) -> 0.08 | L31: =INDEX(L33:L35,$D$6) -> 0.0795 | M31: =INDEX(M33:M35,$D$6) -> 0.079
B33: Best Case | I33: 0.08 | J33: 0.0785 | K33: 0.077 | L33: 0.0755 | M33: 0.074 | O33: Distribution costs as % of sales continue the FY23–25 decline (8.3% to 8.2%) through logistics and network efficiencies, reaching 7.4% by 2030.
B34: Base Case | I34: 0.081 | J34: 0.0805 | K34: 0.08 | L34: 0.0795 | M34: 0.079 | O34: Gradual improvement from the FY2025 level (8.2%) to 7.9% by 2030 from ongoing logistics and network efficiency.
B35: Worst Case | I35: 0.083 | J35: 0.085 | K35: 0.09 | L35: 0.087 | M35: 0.084 | O35: Rises to 9.0% in 2028 as freight costs increase and lower volumes absorb fixed distribution costs, then partially normalises.
B38: Marketing & administration expenses | I38: =INDEX(I40:I42,$D$6) -> 0.2 | J38: =INDEX(J40:J42,$D$6) -> 0.201 | K38: =INDEX(K40:K42,$D$6) -> 0.201 | L38: =INDEX(L40:L42,$D$6) -> 0.202 | M38: =INDEX(M40:M42,$D$6) -> 0.203
B40: Best Case | I40: 0.201 | J40: 0.203 | K40: 0.205 | L40: 0.206 | M40: 0.208 | O40: Includes a deliberate step-up in advertising and promotion, in line with management's stated intent to lift A&P toward c.9% of sales, within a Marketing & Administration total that has run at 19–20% of sales; reaches 20.8% by 2030.
B41: Base Case | I41: 0.2 | J41: 0.201 | K41: 0.201 | L41: 0.202 | M41: 0.203 | O41: Modest reinvestment from 20.0% to 20.3% of sales, broadly in line with the FY2025 level (20.0%).
B42: Worst Case | I42: 0.197 | J42: 0.202 | K42: 0.213 | L42: 0.205 | M42: 0.199 | O42: Rises to 21.3% in 2028: overheads are less flexible than marketing spend, so the ratio increases even as A&P is reduced; it partially normalises thereafter.
B45: Other trading income | I45: =INDEX(I47:I49,$D$6) -> 0.0014 | J45: =INDEX(J47:J49,$D$6) -> 0.0014 | K45: =INDEX(K47:K49,$D$6) -> 0.0013 | L45: =INDEX(L47:L49,$D$6) -> 0.0014 | M45: =INDEX(M47:M49,$D$6) -> 0.0014
B47: Best Case | I47: 0.0016 | J47: 0.0017 | K47: 0.0017 | L47: 0.0018 | M47: 0.0018 | O47: Small and historically volatile line (FY23–25: 0.14–0.15% of sales); the Best Case is slightly higher.
B48: Base Case | I48: 0.0014 | J48: 0.0014 | K48: 0.0013 | L48: 0.0014 | M48: 0.0014 | O48: Held near the FY23–25 average.
B49: Worst Case | I49: 0.0008 | J49: 0.0006 | K49: 0.0005 | L49: 0.0007 | M49: 0.0009 | O49: Compressed during the 2028–29 downturn.
B52: Other trading expenses | I52: =INDEX(I54:I56,$D$6) -> 0.024 | J52: =INDEX(J54:J56,$D$6) -> 0.019 | K52: =INDEX(K54:K56,$D$6) -> 0.015 | L52: =INDEX(L54:L56,$D$6) -> 0.0115 | M52: =INDEX(M54:M56,$D$6) -> 0.0095
B54: Best Case | I54: 0.022 | J54: 0.017 | K54: 0.013 | L54: 0.01 | M54: 0.0085 | O54: Elevated in 2026–27 by 'Fuel for Growth' restructuring and impairment-type charges (c.16,000 role reductions by end-2027, announced in Q4 2025), fading from 2028 as the programme completes; the Best Case assumes faster execution.
B55: Base Case | I55: 0.024 | J55: 0.019 | K55: 0.015 | L55: 0.0115 | M55: 0.0095 | O55: H1 2026 other trading expenses ran at 1.9% of sales (restructuring and net other trading items CHF 0.8bn vs CHF 0.4bn in H1 2025) as 'Fuel for Growth' restructuring accelerated; 2.4% for the full year allows for H2 phasing, declining to 0.95% of sales by 2030 as the programme completes.
B56: Worst Case | I56: 0.027 | J56: 0.025 | K56: 0.034 | L56: 0.021 | M56: 0.016 | O56: Adds further impairment and restructuring charges in the 2028 shock year (3.4% of sales) on top of the ongoing programme, before receding.
B59: Other operating income | I59: =INDEX(I61:I63,$D$6) -> 0.003 | J59: =INDEX(J61:J63,$D$6) -> 0.0028 | K59: =INDEX(K61:K63,$D$6) -> 0.0027 | L59: =INDEX(L61:L63,$D$6) -> 0.0028 | M59: =INDEX(M61:M63,$D$6) -> 0.0028
B61: Best Case | I61: 0.0035 | J61: 0.0035 | K61: 0.0035 | L61: 0.0034 | M61: 0.0034 | O61: Historically volatile, disposal-gain-type line (FY23–25: 0.28–0.52% of sales); the Best Case assumes slightly more portfolio gains.
B62: Base Case | I62: 0.003 | J62: 0.0028 | K62: 0.0027 | L62: 0.0028 | M62: 0.0028 | O62: Held near the FY2025 level (0.28% of sales), below the FY23–25 average (0.37%), which included higher disposal gains in 2024.
B63: Worst Case | I63: 0.0015 | J63: 0.0012 | K63: 0.001 | L63: 0.0012 | M63: 0.0015 | O63: Compressed in the downturn as fewer disposal gains are realised.
B66: Other operating expenses | I66: =INDEX(I68:I70,$D$6) -> 0.006 | J66: =INDEX(J68:J70,$D$6) -> 0.0055 | K66: =INDEX(K68:K70,$D$6) -> 0.0052 | L66: =INDEX(L68:L70,$D$6) -> 0.005 | M66: =INDEX(M68:M70,$D$6) -> 0.0048
B68: Best Case | I68: 0.005 | J68: 0.0045 | K68: 0.0042 | L68: 0.004 | M68: 0.0038 | O68: Historically 0.42–0.81% of sales (FY23–25); the Best Case trends lower.
B69: Base Case | I69: 0.006 | J69: 0.0055 | K69: 0.0052 | L69: 0.005 | M69: 0.0048 | O69: 0.60% of sales in 2026 easing to 0.48% by 2030, below FY2025 (0.73%, incl. infant-formula inventory write-offs). Excludes the CHF 1.3bn one-off non-cash write-down on assets held for sale booked in H1 2026, so reported 2026 net profit will be lower than modelled; the non-cash share of this line is added back in the cash flow via row 168.
B70: Worst Case | I70: 0.0085 | J70: 0.01 | K70: 0.0135 | L70: 0.0105 | M70: 0.0085 | O70: Rises to 1.35% of sales in the 2028 trough, then recedes.
B73: Income from associates & JV, growth % YoY | I73: =INDEX(I75:I77,$D$6) -> 0.03 | J73: =INDEX(J75:J77,$D$6) -> 0.04 | K73: =INDEX(K75:K77,$D$6) -> 0.04 | L73: =INDEX(L75:L77,$D$6) -> 0.05 | M73: =INDEX(M75:M77,$D$6) -> 0.05
B75: Best Case | I75: 0.06 | J75: 0.06 | K75: 0.07 | L75: 0.07 | M75: 0.07 | O75: Year-on-year growth in income from associates & JV (mainly the L'Oréal stake); the Best Case assumes 6–7% growth.
B76: Base Case | I76: 0.03 | J76: 0.04 | K76: 0.04 | L76: 0.05 | M76: 0.05 | O76: Modest recovery (3–5% a year) after the FY2025 decline (–8.5%).
B77: Worst Case | I77: -0.1 | J77: -0.05 | K77: -0.15 | L77: -0.05 | M77: 0.03 | O77: Declines with the equity-market and consumer downturn in 2026–29, then recovers slightly in 2030.
B81: Working Capital Drivers
B83: All figures in CHF millions unless stated | I83: =I$2 -> 2026 | J83: =J$2 -> 2027 | K83: =K$2 -> 2028 | L83: =L$2 -> 2029 | M83: =M$2 -> 2030
B86: DSO | F86: (Days) | I86: =INDEX(I88:I90,$D$6) -> 43 | J86: =INDEX(J88:J90,$D$6) -> 43 | K86: =INDEX(K88:K90,$D$6) -> 42.5 | L86: =INDEX(L88:L90,$D$6) -> 42 | M86: =INDEX(M88:M90,$D$6) -> 42
B88: Best Case | I88: 42.5 | J88: 42 | K88: 41.5 | L88: 41 | M88: 40.5 | O88: Best Case: DSO improves c.0.5 day a year to 40.5 days by 2030 as receivables processing moves into expanded shared services with tighter escalation and governance (FY2025 strategic update).
B89: Base Case | I89: 43 | J89: 43 | K89: 42.5 | L89: 42 | M89: 42 | O89: Base Case: starts from the FY2025 actual (43.1 days) and eases to 42 days by 2030, supported by tighter receivables governance and the expansion of shared services (FY2023–25 range: 43–45 days).
B90: Worst Case | I90: 45 | J90: 46 | K90: 48 | L90: 47 | M90: 46 | O90: Worst Case: customers and distributors stretch payment terms in the 2028 downturn (48 days, above the FY2024 peak of 45 days), normalising partially to 46 days by 2030.
B93: DSI | F93: (Days) | I93: =INDEX(I95:I97,$D$6) -> 93 | J93: =INDEX(J95:J97,$D$6) -> 91 | K93: =INDEX(K95:K97,$D$6) -> 89 | L93: =INDEX(L95:L97,$D$6) -> 88 | M93: =INDEX(M95:M97,$D$6) -> 87
B95: Best Case | I95: 92 | J95: 88 | K95: 86 | L95: 85 | M95: 84 | O95: Best Case: inventory days fall back below the FY2023 level (86 days) to 84 days by 2030 as lower coffee and cocoa costs flow through and data-driven inventory resets (finished goods, raw & packaging, spare parts) are fully embedded.
B96: Base Case | I96: 93 | J96: 91 | K96: 89 | L96: 88 | M96: 87 | O96: Base Case: gradual normalisation from the commodity-inflated FY2024–25 level (96–99 days) to 87 days by 2030, close to FY2023 (86 days); 2026 (93 days) reflects the working-capital improvement reported in H1 2026, partly from lower coffee and cocoa costs.
B97: Worst Case | I97: 98 | J97: 100 | K97: 104 | L97: 100 | M97: 97 | O97: Worst Case: renewed commodity inflation combined with a volume shortfall builds inventory to 104 days in 2028 (above the FY2024 peak of 99 days), before partial correction to 97 days by 2030.
B100: DPO | F100: (Days) | I100: =INDEX(I102:I104,$D$6) -> 150 | J100: =INDEX(J102:J104,$D$6) -> 150 | K100: =INDEX(K102:K104,$D$6) -> 150 | L100: =INDEX(L102:L104,$D$6) -> 150 | M100: =INDEX(M102:M104,$D$6) -> 150
B102: Best Case | I102: 152 | J102: 153 | K102: 154 | L102: 155 | M102: 155 | O102: Best Case: further extension of supplier terms and supply-chain-finance coverage, rising to 155 days by 2030 (the previous Base Case path).
B103: Base Case | I103: 150 | J103: 150 | K103: 150 | L103: 150 | M103: 150 | O103: Base Case: held flat at 150 days, the FY2025 level and close to the FY2023–25 average (151 days). Payable days are already high for the sector; lower commodity prices reduce payable balances, and further extension would rely on supplier-finance programmes.
B104: Worst Case | I104: 148 | J104: 145 | K104: 140 | L104: 142 | M104: 144 | O104: Worst Case: suppliers tighten terms and lower purchase volumes reduce payables in the downturn, falling to 140 days in 2028 (FY2023 level: 139 days) and recovering to 144 days by 2030.
B107: Prepayments | F107: (Days) | I107: 2 | J107: 2 | K107: 2 | L107: 2 | M107: 2 | O107: prepayments are c.CHF 0.5bn (c.2 days of sales, stable over FY2023–25); scenario impact on cash is immaterial, so a single input applies to all scenarios.
B108: Accruals | F108: (Days) | I108: 40 | J108: 40 | K108: 40 | L108: 41 | M108: 41 | O108: accruals held at 40–41 days of COGS, in line with FY2024–25 (41–42 days); a single input applies to all scenarios.
B111: Capex, D&A & Fixed Asset Drivers
B113: All figures in CHF millions unless stated | I113: =I$2 -> 2026 | J113: =J$2 -> 2027 | K113: =K$2 -> 2028 | L113: =L$2 -> 2029 | M113: =M$2 -> 2030
B116: Capex | F116: % Sales | I116: =INDEX(I118:I120,$D$6) -> 0.049 | J116: =INDEX(J118:J120,$D$6) -> 0.048 | K116: =INDEX(K118:K120,$D$6) -> 0.048 | L116: =INDEX(L118:L120,$D$6) -> 0.047 | M116: =INDEX(M118:M120,$D$6) -> 0.047
B118: Best Case | I118: 0.046 | J118: 0.045 | K118: 0.044 | L118: 0.044 | M118: 0.044 | O118: Best Case: capex at the lower end of management's 4-5% of sales range (4.4-4.6% on this model's basis), reflecting tighter business-case scrutiny and the end of the 2022-24 capacity build-out; absolute capex still rises with sales.
B119: Base Case | I119: 0.049 | J119: 0.048 | K119: 0.048 | L119: 0.047 | M119: 0.047 | O119: Base Case: 4.9% of sales in 2026 easing to 4.7% by 2030. Management guides capex to normalise within 4–5% of sales (FY2025: 4.8% on Nestlé's definition vs 5.1% on this model's cash-flow PP&E basis), and lower capex already supported H1 2026 free cash flow. Source: FY2025 results call (19 Feb 2026); H1 2026 results.
B120: Worst Case | I120: 0.05 | J120: 0.05 | K120: 0.053 | L120: 0.052 | M120: 0.05 | O120: Worst Case: absolute capex is sticky (committed projects; safety and quality spend non-negotiable) at c.CHF 4.4-4.8bn while sales fall, lifting the ratio to 5.3% in 2028; trimmed back to 5.0% by 2030.
B123: Expenditure on intangible assets | F123: % Sales | I123: 0.004 | J123: 0.004 | K123: 0.004 | L123: 0.0045 | M123: 0.0045 | O123: intangible expenditure (mainly IT/software) ran at 0.36–0.53% of sales over FY2023–25 (cash-flow basis) and is immaterial to group cash flow; a single input applies to all scenarios.
B124: Combined D&A | F124: % Opening | I124: 0.07 | J124: 0.069 | K124: 0.068 | L124: 0.067 | M124: 0.067 | O124: the D&A rate is an accounting estimate on the opening asset base (FY2024–25: 6.9–7.4%). Capex scenarios already flow into D&A through the asset base; a single input applies to all scenarios.
B125: D&A allocated to PP&E | I125: 0.85 | J125: 0.85 | K125: 0.85 | L125: 0.85 | M125: 0.85 | O125: c.85% of D&A relates to PP&E (incl. right-of-use assets), the remainder to intangibles; a structural split, not scenario-dependent.
B129: Equity & Dividend Drivers
B131: All figures in CHF millions unless stated | I131: =I$2 -> 2026 | J131: =J$2 -> 2027 | K131: =K$2 -> 2028 | L131: =L$2 -> 2029 | M131: =M$2 -> 2030
B134: Dividend payout ratio | F134: % Net Profit | I134: =INDEX(I136:I138,$D$6) -> 0.865 | J134: =INDEX(J136:J138,$D$6) -> 0.842 | K134: =INDEX(K136:K138,$D$6) -> 0.859 | L134: =INDEX(L136:L138,$D$6) -> 0.823 | M134: =INDEX(M136:M138,$D$6) -> 0.79
B136: Best Case | I136: 0.806 | J136: 0.751 | K136: 0.697 | L136: 0.647 | M136: 0.602 | O136: Best Case: dividend per share rises CHF 0.10 a year from 2027 (CHF 3.10 paid in April 2026 = c.CHF 8.0bn cash), funded by stronger profit and cash flow. Payout back-solved from Best Case net profit.
B137: Base Case | I137: 0.865 | J137: 0.842 | K137: 0.859 | L137: 0.823 | M137: 0.79 | O137: Base Case: reflects the progressive dividend – CHF 3.10/share paid April 2026 (c.CHF 8.0bn, already paid), then +CHF 0.05/share a year, in line with the FY2025 increase. Payout (79–87% of reported net profit) is back-solved from Base Case net profit and should be re-checked if margin inputs change.
B138: Worst Case | I138: 0.982 | J138: 0.7 | K138: 0.7 | L138: 0.7 | M138: 0.7 | O138: Worst Case: 2026 fixed at the CHF 8.0bn already paid. From 2027 the payout input is set at 70%, so the dividend floor holds the prior-year dividend, capped at 100% of net profit (cell F186).
B141: Treasury share purchases | I141: =INDEX(I143:I145,$D$6) -> 0 | J141: =INDEX(J143:J145,$D$6) -> 0 | K141: =INDEX(K143:K145,$D$6) -> 1000 | L141: =INDEX(L143:L145,$D$6) -> 1500 | M141: =INDEX(M143:M145,$D$6) -> 2000
B143: Best Case | I143: 0 | J143: 1000 | K143: 2500 | L143: 3500 | M143: 4000 | O143: Best Case: buybacks resume from 2027 and scale to CHF 4bn a year as leverage reaches the middle of the 2–3x target range (Nestlé bought back CHF 4.7–5.2bn a year in 2023–24). Executed only when prior-year leverage is within the ceiling (F185).
B144: Base Case | I144: 0 | J144: 0 | K144: 1000 | L144: 1500 | M144: 2000 | O144: Base Case: nil in 2026–27 (no programme in place; management prioritises the dividend and net debt reduction, with buybacks only from excess cash), then CHF 1.0–2.0bn a year. Leverage-gated (F185): Base Case model leverage falls below the 3.0x ceiling in 2029 (c.2.9x), so the first buyback (CHF 2.0bn) is executed in 2030.
B145: Worst Case | I145: 0 | J145: 0 | K145: 0 | L145: 0 | M145: 0 | O145: Worst Case: no buybacks; all surplus cash goes to protecting the dividend and the balance sheet.
B148: Dividends received from associates & JV | F148: % Opening | I148: =INDEX(I150:I152,$D$6) -> 0.065 | J148: =INDEX(J150:J152,$D$6) -> 0.06 | K148: =INDEX(K150:K152,$D$6) -> 0.06 | L148: =INDEX(L150:L152,$D$6) -> 0.06 | M148: =INDEX(M150:M152,$D$6) -> 0.06
B150: Best Case | I150: 0.065 | J150: 0.065 | K150: 0.065 | L150: 0.065 | M150: 0.065 | O150: Best Case: 6.5% of the opening balance throughout, supported by a progressive L'Oreal dividend and distributions from the new waters JV (Peranel) once established.
B151: Base Case | I151: 0.065 | J151: 0.06 | K151: 0.06 | L151: 0.06 | M151: 0.06 | O151: Base Case: ordinary distributions ran at 5.3-5.8% of the opening balance in FY2024-25, excluding the CHF 2.0bn extraordinary Froneri distribution in 2025; the lower 2026 opening base lifts the ratio to c.6%.
B152: Worst Case | I152: 0.06 | J152: 0.05 | K152: 0.045 | L152: 0.045 | M152: 0.05 | O152: Worst Case: 2026 close to Base (main dividends received in H1); associates cut distributions to 4.5-5.0% in the 2027-29 downturn.
B155: Dividends to NCI | F155: % NCI Profit | I155: 0.75 | J155: 0.75 | K155: 0.75 | L155: 0.75 | M155: 0.75 | O155: dividends to NCI are small (c.CHF 0.2bn) and follow subsidiary policy; held at 75% of NCI profit, within the FY2023-25 range (60-108%).
B159: Other Inputs
B161: All figures in CHF millions unless stated | I161: =I$2 -> 2026 | J161: =J$2 -> 2027 | K161: =K$2 -> 2028 | L161: =L$2 -> 2029 | M161: =M$2 -> 2030
B164: Other Annual Inputs
B166: Financial Debt | F166: Increase / (Decrease) | I166: -0.02 | J166: -0.01 | K166: 0 | L166: 0.01 | M166: 0.01 | O166: Year-on-year change in total financial debt: modest deleveraging in 2026–27 (FY2025: –9.0%), stable in 2028 and modest growth from 2029 in line with the business. Any short-term funding need is met by the revolving credit line. The c.CHF 2.8bn Peranel JV proceeds expected in H1 2027 are not modelled and would accelerate deleveraging.
B167: Current Portion | F167: % Financial Debt | I167: 0.2 | J167: 0.2 | K167: 0.2 | L167: 0.2 | M167: 0.2 | O167: Share of financial debt maturing within one year, held at 20%: the FY2025 level and the top of the FY2023–25 range (17–20%). Affects only the current/non-current split and liquidity ratios, not cash.
B168: Non-cash charges | F168: % Other Exp. | I168: 0.35 | J168: 0.35 | K168: 0.35 | L168: 0.35 | M168: 0.35 | O168: Share of other trading and other operating expenses that is non-cash (impairments, write-downs), added back in the cash flow and written off against goodwill. Impairments were 27%, 37% and 37% of these expenses in FY2023–25; 35% applied. Restructuring is treated as cash.
C172: Dates | I172: Taxes
C173: First Year of Forecast | E173: (YYYY) | F173: 2026 | I173: Tax Rate | M173: 0.235 | O173: Effective tax rate on profit before tax, associates and JV. 23.5% sits between the underlying rate (22.1% FY2025; 22.3% H1 2026) and the reported rate (24.6% FY2025), allowing for recurring non-deductible items and the OECD Pillar Two 15% minimum tax. Cash taxes come from the tax depreciation schedule; the timing difference is recorded in deferred tax liabilities.
C174: Days in Period | E174: (Days) | F174: 365 | I174: First Year Tax Depreciation | M174: 0.15 | O174: Share of current-year capex added to the tax depreciation base in the year of spend (partial-year convention); the full amount enters the base from the following year.
I175: Blended Tax Depreciation Rate | M175: 0.08 | O175: Blended tax depreciation rate on the tax basis (8%), slightly above the book D&A rate (c.7%), reflecting moderately accelerated tax allowances; the resulting timing difference builds a deferred tax liability.
I176: Tax Basis for Assets | M176: 49222 | O176: Opening tax basis of depreciable assets, proxied to the FY2025 net book value of PP&E and intangible assets (CHF 49,222m), as the tax basis is not disclosed. Both PP&E and intangible capex and D&A flow through the tax schedule, consistent with this base.
I177: Tax Losses | M177: 0 | O177: Opening tax loss carryforwards assumed nil, given the Group's consistent consolidated profitability (not disclosed).
C180: Other Single Inputs | I180: Interest Rates
I181: Cash & ST Investment | M181: 0.025 | O181: Interest rate earned on cash and short-term investments, applied to opening balances. Set below the FY2025 implied yield (3.8%; FY2024: 6.1%) to reflect lower CHF and EUR short-term rates.
C182: Non-controlling interests, % of profit | F182: 0.025 | I182: Financial Debt | M182: 0.029 | O182: F182 – NCI share of profit, held near the FY23–25 average (2.4–2.6%). | M182 – Interest rate on opening financial debt (2.9%): FY2025 financial expense equalled 2.9% of opening debt, and Nestlé reports an average cost of net debt of 2.5–2.6% (FY2025, H1 2026); the small cushion covers refinancing of maturing low-coupon debt.
C183: R&D Cost | F183: 0.018 | I183: Revolving Credit Line | M183: 0.042 | O183: F183 – R&D cost, held at the FY23–25 average (1.8% of sales). | M183 – Interest rate on the revolving credit line (4.2%), priced at a spread above term debt in line with typical committed-facility pricing.
...

Sheet Model
B2: =Input!$B$2 -> Nestlé S.A. | CHF millions | Scenario: Base Case | F2: =G2-1 -> 2023 | G2: =H2-1 -> 2024 | H2: =I2-1 -> 2025 | I2: =Input!$I$2 -> 2026 | J2: =I2+1 -> 2027 | K2: =J2+1 -> 2028 | L2: =K2+1 -> 2029 | M2: =L2+1 -> 2030
B4: Growth & Margin Drivers
B6: =Input!$B$131 -> All figures in CHF millions unless stated | F6: =F$2 -> 2023 | G6: =G$2 -> 2024 | H6: =H$2 -> 2025 | I6: =I$2 -> 2026 | J6: =J$2 -> 2027 | K6: =K$2 -> 2028 | L6: =L$2 -> 2029 | M6: =M$2 -> 2030
B7: =CONCATENATE("Model Running: ",INDEX(Input!$B$12:$B$14,Input!$D$6)," Drivers") -> Model Running: Base Case Drivers
B9: Sales growth | G9: -0.0176778 | H9: -0.020404142 | I9: =Input!I$10 -> 0.005 | J9: =Input!J$10 -> 0.015 | K9: =Input!K$10 -> 0.005 | L9: =Input!L$10 -> 0.02 | M9: =Input!M$10 -> 0.028
B10: Other revenue | F10: 0.0037957806 | G10: 0.0040063927 | H10: 0.004413901 | I10: =Input!I$17 -> 0.0042 | J10: =Input!J$17 -> 0.0043 | K10: =Input!K$17 -> 0.0043 | L10: =Input!L$17 -> 0.0044 | M10: =Input!M$17 -> 0.0045
B11: Cost of goods sold | G11: -0.032943888 | H11: 0.00049311691 | I11: =Input!I$24 -> 0.00090441985 | J11: =Input!J$24 -> 0.018740719 | K11: =Input!K$24 -> 0.017768006 | L11: =Input!L$24 -> 0.018371853 | M11: =Input!M$24 -> 0.025530179
B12: Distribution expenses | F12: 0.083496419 | G12: 0.082831622 | H12: 0.081640407 | I12: =Input!I$31 -> 0.081 | J12: =Input!J$31 -> 0.0805 | K12: =Input!K$31 -> 0.08 | L12: =Input!L$31 -> 0.0795 | M12: =Input!M$31 -> 0.079
B13: Marketing & administration expenses | F13: 0.18870298 | G13: 0.19826171 | H13: 0.19983238 | I13: =Input!I$38 -> 0.2 | J13: =Input!J$38 -> 0.201 | K13: =Input!K$38 -> 0.201 | L13: =Input!L$38 -> 0.202 | M13: =Input!M$38 -> 0.203
B14: R&D costs | F14: 0.017806835 | G14: 0.018247696 | H14: 0.01802436 | I14: =Input!$F$183 -> 0.018 | J14: =Input!$F$183 -> 0.018 | K14: =Input!$F$183 -> 0.018 | L14: =Input!$F$183 -> 0.018 | M14: =Input!$F$183 -> 0.018
B15: Other trading income | F15: 0.0014193854 | G15: 0.0013573571 | H15: 0.0015085484 | I15: =Input!I$45 -> 0.0014 | J15: =Input!J$45 -> 0.0014 | K15: =Input!K$45 -> 0.0013 | L15: =Input!L$45 -> 0.0014 | M15: =Input!M$45 -> 0.0014
B16: Other trading expenses | F16: 0.017903611 | G16: 0.013080982 | H16: 0.020661526 | I16: =Input!I$52 -> 0.024 | J16: =Input!J$52 -> 0.019 | K16: =Input!K$52 -> 0.015 | L16: =Input!L$52 -> 0.0115 | M16: =Input!M$52 -> 0.0095
B17: Other operating income | F17: 0.00320437 | G17: 0.005188607 | H17: 0.0028271315 | I17: =Input!I$59 -> 0.003 | J17: =Input!J$59 -> 0.0028 | K17: =Input!K$59 -> 0.0027 | L17: =Input!L$59 -> 0.0028 | M17: =Input!M$59 -> 0.0028
B18: Other operating expenses | F18: 0.0081184542 | G18: 0.004192482 | H18: 0.0072745558 | I18: =Input!I$66 -> 0.006 | J18: =Input!J$66 -> 0.0055 | K18: =Input!K$66 -> 0.0052 | L18: =Input!L$66 -> 0.005 | M18: =Input!M$66 -> 0.0048
B19: Effective tax rate | F19: 0.18216169 | G19: 0.25032102 | H19: 0.24555855 | I19: =Input!$M$173 -> 0.235 | J19: =Input!$M$173 -> 0.235 | K19: =Input!$M$173 -> 0.235 | L19: =Input!$M$173 -> 0.235 | M19: =Input!$M$173 -> 0.235
B20: Income from associates & JV | G20: 0.11517857 | H20: -0.084867894 | I20: =Input!I$73 -> 0.03 | J20: =Input!J$73 -> 0.04 | K20: =Input!K$73 -> 0.04 | L20: =Input!L$73 -> 0.05 | M20: =Input!M$73 -> 0.05
B21: Non-controlling interests | F21: 0.026066557 | G21: 0.025953105 | H21: 0.023881565 | I21: =Input!$F$182 -> 0.025 | J21: =Input!$F$182 -> 0.025 | K21: =Input!$F$182 -> 0.025 | L21: =Input!$F$182 -> 0.025 | M21: =Input!$F$182 -> 0.025
B22: Non-cash share of other trading & operating expenses | F22: =IFERROR(F289/-(F262+F266),0) -> 0.26735537 | G22: =IFERROR(G289/-(G262+G266),0) -> 0.36755387 | H22: =IFERROR(H289/-(H262+H266),0) -> 0.3692 | I22: =Input!I$168 -> 0.35 | J22: =Input!J$168 -> 0.35 | K22: =Input!K$168 -> 0.35 | L22: =Input!L$168 -> 0.35 | M22: =Input!M$168 -> 0.35
B25: Equity & Dividend Drivers
B27: =Input!$B$131 -> All figures in CHF millions unless stated | F27: =F$2 -> 2023 | G27: =G$2 -> 2024 | H27: =H$2 -> 2025 | I27: =I$2 -> 2026 | J27: =J$2 -> 2027 | K27: =K$2 -> 2028 | L27: =L$2 -> 2029 | M27: =M$2 -> 2030
B28: =CONCATENATE("Model Running: ",INDEX(Input!$B$12:$B$14,Input!$D$6)," Drivers") -> Model Running: Base Case Drivers
B30: Dividend payout ratio, % of net profit (parent) | F30: 0.6984566 | G30: 0.71811834 | H30: 0.86892505 | I30: =Input!I$134 -> 0.865 | J30: =Input!J$134 -> 0.842 | K30: =Input!K$134 -> 0.859 | L30: =Input!L$134 -> 0.823 | M30: =Input!M$134 -> 0.79
B31: Dividends to NCI, % of NCI profit | F31: 1.0766667 | G31: 0.6 | H31: 0.77828054 | I31: =Input!I$155 -> 0.75 | J31: =Input!J$155 -> 0.75 | K31: =Input!K$155 -> 0.75 | L31: =Input!L$155 -> 0.75 | M31: =Input!M$155 -> 0.75
B32: Treasury share purchases, CHF mm/year | F32: 5234 | G32: 4678 | H32: 213 | I32: =IF((H364+H375+H371-H341)/(H267+H288)>Input!$F$185,0,Input!I$141) -> 0 | J32: =IF((I364+I375+I371-I341)/(I267+I288)>Input!$F$185,0,Input!J$141) -> 0 | K32: =IF((J364+J375+J371-J341)/(J267+J288)>Input!$F$185,0,Input!K$141) -> 0 | L32: =IF((K364+K375+K371-K341)/(K267+K288)>Input!$F$185,0,Input!L$141) -> 0 | M32: =IF((L364+L375+L371-L341)/(L267+L288)>Input!$F$185,0,Input!M$141) -> 2000
B33: Dividends received from associates & JV, % of opening balance | G33: 0.057992054 | H33: 0.19223789 | I33: =Input!I$148 -> 0.065 | J33: =Input!J$148 -> 0.06 | K33: =Input!K$148 -> 0.06 | L33: =Input!L$148 -> 0.06 | M33: =Input!M$148 -> 0.06
B36: Working Capital Schedule
B38: =Input!$B$131 -> All figures in CHF millions unless stated | F38: =F$2 -> 2023 | G38: =G$2 -> 2024 | H38: =H$2 -> 2025 | I38: =I$2 -> 2026 | J38: =J$2 -> 2027 | K38: =K$2 -> 2028 | L38: =L$2 -> 2029 | M38: =M$2 -> 2030
B39: =CONCATENATE("Model Running: ",INDEX(Input!$B$12:$B$14,Input!$D$6)," Drivers") -> Model Running: Base Case Drivers
B41: Days in Period | F41: =Input!$F$174 -> 365 | G41: =Input!$F$174 -> 365 | H41: =Input!$F$174 -> 365 | I41: =Input!$F$174 -> 365 | J41: =Input!$F$174 -> 365 | K41: =Input!$F$174 -> 365 | L41: =Input!$F$174 -> 365 | M41: =Input!$F$174 -> 365
B42: Revenue | F42: =F255 -> 92998 | G42: =G255 -> 91354 | H42: =H255 -> 89490 | I42: =I255 -> 89937.45 | J42: =J255 -> 91286.512 | K42: =K255 -> 91742.944 | L42: =L255 -> 93577.803 | M42: =M255 -> 96197.982
B43: COGS | F43: =-F257 -> 50328 | G43: =-G257 -> 48670 | H43: =-H257 -> 48694 | I43: =-I257 -> 48738.04 | J43: =-J257 -> 49651.426 | K43: =-K257 -> 50533.633 | L43: =-L257 -> 51462.029 | M43: =-M257 -> 52775.864
B45: AMOUNTS PER DAY
B46: Accounts Receivable (Days) | F46: =(F53/F42)*F41 -> 43.153347 | G46: =(G53/G42)*G41 -> 44.952766 | H46: =(H53/H42)*H41 -> 43.074813 | I46: =Input!I86 -> 43 | J46: =Input!J86 -> 43 | K46: =Input!K86 -> 42.5 | L46: =Input!L86 -> 42 | M46: =Input!M86 -> 42
B47: Inventory (Days) | F47: =(F54/F43)*F41 -> 86.274837 | G47: =(G54/G43)*G41 -> 99.443189 | H47: =(H54/H43)*H41 -> 96.043558 | I47: =Input!I93 -> 93 | J47: =Input!J93 -> 91 | K47: =Input!K93 -> 89 | L47: =Input!L93 -> 88 | M47: =Input!M93 -> 87
B48: Accounts Payable (Days) | F48: =(F55/F43)*F41 -> 139.27555 | G48: =(G55/G43)*G41 -> 163.5413 | H48: =(H55/H43)*H41 -> 150.0882 | I48: =Input!I100 -> 150 | J48: =Input!J100 -> 150 | K48: =Input!K100 -> 150 | L48: =Input!L100 -> 150 | M48: =Input!M100 -> 150
B49: Prepayments (Days) | F49: =(F56/F42)*F41 -> 2.0448289 | G49: =(G56/G42)*G41 -> 2.1695273 | H49: =(H56/H42)*H41 -> 1.953682 | I49: =Input!I107 -> 2 | J49: =Input!J107 -> 2 | K49: =Input!K107 -> 2 | L49: =Input!L107 -> 2 | M49: =Input!M107 -> 2
B50: Accruals (Days) | F50: =(F57/F43)*F41 -> 37.074392 | G50: =(G57/G43)*G41 -> 40.992192 | H50: =(H57/H43)*H41 -> 41.789029 | I50: =Input!I108 -> 40 | J50: =Input!J108 -> 40 | K50: =Input!K108 -> 40 | L50: =Input!L108 -> 41 | M50: =Input!M108 -> 41
B52: TOTAL AMOUNTS
B53: Accounts Receivable | F53: 10995 | G53: 11251 | H53: 10561 | I53: =(I46/I41)*I42 -> 10595.371 | J53: =(J46/J41)*J42 -> 10754.301 | K53: =(K46/K41)*K42 -> 10682.398 | L53: =(L46/L41)*L42 -> 10767.857 | M53: =(M46/M41)*M42 -> 11069.357
B54: Inventory | F54: 11896 | G54: 13260 | H54: 12813 | I54: =(I47/I41)*I43 -> 12418.185 | J54: =(J47/J41)*J43 -> 12378.849 | K54: =(K47/K41)*K43 -> 12321.899 | L54: =(L47/L41)*L43 -> 12407.284 | M54: =(M47/M41)*M43 -> 12579.452
B55: Accounts Payable | F55: 19204 | G55: 21807 | H55: 20023 | I55: =(I48/I41)*I43 -> 20029.331 | J55: =(J48/J41)*J43 -> 20404.696 | K55: =(K48/K41)*K43 -> 20767.246 | L55: =(L48/L41)*L43 -> 21148.779 | M55: =(M48/M41)*M43 -> 21688.711
B56: Prepayments | F56: 521 | G56: 543 | H56: 479 | I56: =(I49/I41)*I42 -> 492.80795 | J56: =(J49/J41)*J42 -> 500.20006 | K56: =(K49/K41)*K42 -> 502.70106 | L56: =(L49/L41)*L42 -> 512.75509 | M56: =(M49/M41)*M42 -> 527.11223
B57: Accruals | F57: 5112 | G57: 5466 | H57: 5575 | I57: =(I50/I41)*I43 -> 5341.155 | J57: =(J50/J41)*J43 -> 5441.2521 | K57: =(K50/K41)*K43 -> 5537.9323 | L57: =(L50/L41)*L43 -> 5780.6663 | M57: =(M50/M41)*M43 -> 5928.2477
B60: CASH CHANGES
B61: Accounts Receivable | G61: =F53-G53 -> -256 | H61: =G53-H53 -> 690 | I61: =H53-I53 -> -34.370822 | J61: =I53-J53 -> -158.93056 | K61: =J53-K53 -> 71.903759 | L61: =K53-L53 -> -85.459181 | M61: =L53-M53 -> -301.49999
B62: Inventory | G62: =F54-G54 -> -1364 | H62: =G54-H54 -> 447 | I62: =H54-I54 -> 394.81451 | J62: =I54-J54 -> 39.33688 | K62: =J54-K54 -> 56.949166 | L62: =K54-L54 -> -85.384261 | M62: =L54-M54 -> -172.16876
B63: Prepayments | G63: =F56-G56 -> -22 | H63: =G56-H56 -> 64 | I63: =H56-I56 -> -13.807945 | J63: =I56-J56 -> -7.3921192 | K63: =J56-K56 -> -2.5010003 | L63: =K56-L56 -> -10.054021 | M63: =L56-M56 -> -14.357142
B64: Accounts Payable | G64: =G55-F55 -> 2603 | H64: =H55-G55 -> -1784 | I64: =I55-H55 -> 6.3314329 | J64: =J55-I55 -> 375.36408 | K64: =K55-J55 -> 362.55074 | L64: =L55-K55 -> 381.53279 | M64: =M55-L55 -> 539.93211
B65: Accruals | G65: =G57-F57 -> 354 | H65: =H57-G57 -> 109 | I65: =I57-H57 -> -233.84495 | J65: =J57-I57 -> 100.09709 | K65: =K57-J57 -> 96.680198 | L65: =L57-K57 -> 242.73394 | M65: =M57-L57 -> 147.58144
B66: Cash from Working Capital Items | G66: =G61+G62+G63+G64+G65 -> 1315 | H66: =H61+H62+H63+H64+H65 -> -474 | I66: =I61+I62+I63+I64+I65 -> 119.12223 | J66: =J61+J62+J63+J64+J65 -> 348.47536 | K66: =K61+K62+K63+K64+K65 -> 585.58287 | L66: =L61+L62+L63+L64+L65 -> 443.36926 | M66: =M61+M62+M63+M64+M65 -> 199.48765
B69: Asset Schedule
B71: =Input!$B$131 -> All figures in CHF millions unless stated | F71: =F$2 -> 2023 | G71: =G$2 -> 2024 | H71: =H$2 -> 2025 | I71: =I$2 -> 2026 | J71: =J$2 -> 2027 | K71: =K$2 -> 2028 | L71: =L$2 -> 2029 | M71: =M$2 -> 2030
B72: =CONCATENATE("Model Running: ",INDEX(Input!$B$12:$B$14,Input!$D$6)," Drivers") -> Model Running: Base Case Drivers
B74: Capital Expenditure
B75: Capex, % of sales | F75: =-F305/F255 -> 0.061442182 | G75: =-G305/G255 -> 0.061715962 | H75: =-H305/H255 -> 0.050586658 | I75: =Input!I116 -> 0.049 | J75: =Input!J116 -> 0.048 | K75: =Input!K116 -> 0.048 | L75: =Input!L116 -> 0.047 | M75: =Input!M116 -> 0.047
B76: Capital Expenditure — PP&E | F76: =-F255*F75 -> -5714 | G76: =-G255*G75 -> -5638 | H76: =-H255*H75 -> -4527 | I76: =-I255*I75 -> -4406.9351 | J76: =-J255*J75 -> -4381.7526 | K76: =-K255*K75 -> -4403.6613 | L76: =-L255*L75 -> -4398.1568 | M76: =-M255*M75 -> -4521.3051
B78: Intangible capex, % of sales | F78: =-F306/F255 -> 0.0052581776 | G78: =-G306/G255 -> 0.0035575892 | H78: =-H306/H255 -> 0.0042909822 | I78: =Input!I123 -> 0.004 | J78: =Input!J123 -> 0.004 | K78: =Input!K123 -> 0.004 | L78: =Input!L123 -> 0.0045 | M78: =Input!M123 -> 0.0045
B79: Capital Expenditure — Intangible assets | F79: =-F255*F78 -> -489 | G79: =-G255*G78 -> -325 | H79: =-H255*H78 -> -384 | I79: =-I255*I78 -> -359.7498 | J79: =-J255*J78 -> -365.14605 | K79: =-K255*K78 -> -366.97178 | L79: =-L255*L78 -> -421.10011 | M79: =-M255*M78 -> -432.89092
B81: TOTAL DEPRECIATION & AMORTIZATION
B82: Combined D&A rate, % of opening PP&E + intangibles | G82: 0.073564446 | H82: 0.068610602 | I82: =Input!I124 -> 0.07 | J82: =Input!J124 -> 0.069 | K82: =Input!K124 -> 0.068 | L82: =Input!L124 -> 0.067 | M82: =Input!M124 -> 0.067
B83: D&A allocated to PP&E (remainder to intangibles), % | F83: 0.85 | G83: 0.85 | H83: 0.85 | I83: =Input!I125 -> 0.85 | J83: =Input!J125 -> 0.85 | K83: =Input!K125 -> 0.85 | L83: =Input!L125 -> 0.85 | M83: =Input!M125 -> 0.85
B84: Property, plant and equipment | F84: =F352 -> 30467 | G84: =G352 -> 33706 | H84: =H352 -> 32549 | I84: =I352 -> 34027.226 | J84: =J352 -> 35444.623 | K84: =K352 -> 36854.096 | L84: =L352 -> 38231.02 | M84: =M352 -> 39659.058
B85: Intangible assets | F85: =F354 -> 18225 | G85: =G354 -> 19245 | H85: =H354 -> 16673 | I85: =I354 -> 16515.919 | J85: =J354 -> 16357.943 | K85: =K354 -> 16196.529 | L85: =L354 -> 16084.47 | M85: =M354 -> 15971.49
B87: Total Depreciation & Amortization | G87: =G82*(F84+F85) -> 3582 | H87: =H82*(G84+G85) -> 3633 | I87: =I82*(H84+H85) -> 3445.54 | J87: =J82*(I84+I85) -> 3487.477 | K87: =K82*(J84+J85) -> 3522.5745 | L87: =L82*(K84+K85) -> 3554.3919 | M87: =M82*(L84+L85) -> 3639.1378
B88: Depreciation — PP&E | G88: =G83*G87 -> 3044.7 | H88: =H83*H87 -> 3088.05 | I88: =I83*I87 -> 2928.709 | J88: =J83*J87 -> 2964.3554 | K88: =K83*K87 -> 2994.1883 | L88: =L83*L87 -> 3021.2331 | M88: =M83*M87 -> 3093.2672
B89: Amortization — Intangible assets | G89: =G87-G88 -> 537.3 | H89: =H87-H88 -> 544.95 | I89: =I87-I88 -> 516.831 | J89: =J87-J88 -> 523.12155 | K89: =K87-K88 -> 528.38618 | L89: =L87-L88 -> 533.15878 | M89: =M87-M88 -> 545.87067
B92: PROPERTY, PLANT & EQUIPMENT
B93: Beginning | G93: =F97 -> 30467 | H93: =G97 -> 33706 | I93: =H97 -> 32549 | J93: =I97 -> 34027.226 | K93: =J97 -> 35444.623 | L93: =K97 -> 36854.096 | M93: =L97 -> 38231.02
B94: Capital Expenditure | G94: =-G76 -> 5638 | H94: =-H76 -> 4527 | I94: =-I76 -> 4406.9351 | J94: =-J76 -> 4381.7526 | K94: =-K76 -> 4403.6613 | L94: =-L76 -> 4398.1568 | M94: =-M76 -> 4521.3051
B95: Depreciation | G95: =-G88 -> -3044.7 | H95: =-H88 -> -3088.05 | I95: =-I88 -> -2928.709 | J95: =-J88 -> -2964.3554 | K95: =-K88 -> -2994.1883 | L95: =-L88 -> -3021.2331 | M95: =-M88 -> -3093.2672
B96: Other movements (FX, leases, impairments, disposals) | G96: =G352-SUM(G93:G95) -> 645.7 | H96: =H352-SUM(H93:H95) -> -2595.95 | I96: 0 | J96: 0 | K96: 0 | L96: 0 | M96: 0
B97: Ending | F97: =F352 -> 30467 | G97: =SUM(G93:G96) -> 33706 | H97: =SUM(H93:H96) -> 32549 | I97: =SUM(I93:I96) -> 34027.226 | J97: =SUM(J93:J96) -> 35444.623 | K97: =SUM(K93:K96) -> 36854.096 | L97: =SUM(L93:L96) -> 38231.02 | M97: =SUM(M93:M96) -> 39659.058
B99: INTANGIBLE ASSETS
B100: Beginning | G100: =F104 -> 18225 | H100: =G104 -> 19245 | I100: =H104 -> 16673 | J100: =I104 -> 16515.919 | K100: =J104 -> 16357.943 | L100: =K104 -> 16196.529 | M100: =L104 -> 16084.47
B101: Capital Expenditure | G101: =-G79 -> 325 | H101: =-H79 -> 384 | I101: =-I79 -> 359.7498 | J101: =-J79 -> 365.14605 | K101: =-K79 -> 366.97178 | L101: =-L79 -> 421.10011 | M101: =-M79 -> 432.89092
B102: Amortization | G102: =-G89 -> -537.3 | H102: =-H89 -> -544.95 | I102: =-I89 -> -516.831 | J102: =-J89 -> -523.12155 | K102: =-K89 -> -528.38618 | L102: =-L89 -> -533.15878 | M102: =-M89 -> -545.87067
B103: Other movements (FX, acquisitions, impairments, disposals) | G103: =G354-SUM(G100:G102) -> 1232.3 | H103: =H354-SUM(H100:H102) -> -2411.05 | I103: 0 | J103: 0 | K103: 0 | L103: 0 | M103: 0
B104: Ending | F104: =F354 -> 18225 | G104: =SUM(G100:G103) -> 19245 | H104: =SUM(H100:H103) -> 16673 | I104: =SUM(I100:I103) -> 16515.919 | J104: =SUM(J100:J103) -> 16357.943 | K104: =SUM(K100:K103) -> 16196.529 | L104: =SUM(L100:L103) -> 16084.47 | M104: =SUM(M100:M103) -> 15971.49
C107: First Year Tax Depreciation | D107: =Input!M174 -> 0.15
C108: Blended Tax Depreciation Rate | D108: =Input!M175 -> 0.08
B110: TAX BASIS
B111: Beginning | I111: =H114 -> 49222 | J111: =I114 -> 49993.725 | K111: =J114 -> 50684.162 | L111: =K114 -> 51342.815 | M111: =L114 -> 51996.816
B112: Capital Expenditure | I112: =I94+I101 -> 4766.6848 | J112: =J94+J101 -> 4746.8986 | K112: =K94+K101 -> 4770.6331 | L112: =L94+L101 -> 4819.2569 | M112: =M94+M101 -> 4954.1961
B113: Tax Depreciation | I113: =-(I111+I112*$D$107)*$D$108 -> -3994.9602 | J113: =-(J111+J112*$D$107)*$D$108 -> -4056.4608 | K113: =-(K111+K112*$D$107)*$D$108 -> -4111.9806 | L113: =-(L111+L112*$D$107)*$D$108 -> -4165.2563 | M113: =-(M111+M112*$D$107)*$D$108 -> -4219.1956
B114: Ending | H114: =Input!M176 -> 49222 | I114: =I111+I112+I113 -> 49993.725 | J114: =J111+J112+J113 -> 50684.162 | K114: =K111+K112+K113 -> 51342.815 | L114: =L111+L112+L113 -> 51996.816 | M114: =M111+M112+M113 -> 52731.816
B116: Model uses a blended D&A rate on opening net book value , consistent with the level of disclosure in Nestlé's consolidated statements. All PP&E and intangible capex is depreciated/amortized on this blended basis;
B117: Historical 'Other movements' reconcile the PP&E and intangibles roll-forwards to reported balances (FX, leases, impairments, disposals); the forecast assumes none, so the asset base moves only with capex and D&A.
B119: Income Tax Schedule
B121: =Input!$B$131 -> All figures in CHF millions unless stated | F121: =F$2 -> 2023 | G121: =G$2 -> 2024 | H121: =H$2 -> 2025 | I121: =I$2 -> 2026 | J121: =J$2 -> 2027 | K121: =K$2 -> 2028 | L121: =L$2 -> 2029 | M121: =M$2 -> 2030
B122: =CONCATENATE("Model Running: ",INDEX(Input!$B$12:$B$14,Input!$D$6)," Drivers") -> Model Running: Base Case Drivers
C124: EBT | I124: =I271 -> 10861.493 | J124: =J271 -> 11336.57 | K124: =K271 -> 11218.998 | L124: =L271 -> 11908.664 | M124: =M271 -> 12610.504
C125: Profitable Before Tax? | I125: =IF(I134>0,1,0) -> 1 | J125: =IF(J134>0,1,0) -> 1 | K125: =IF(K134>0,1,0) -> 1 | L125: =IF(L134>0,1,0) -> 1 | M125: =IF(M134>0,1,0) -> 1
C127: Tax Rate | D127: =Input!$M$173 -> 0.235
C128: Unused Tax Loss Remaining | D128: =IF(M145=0,0,1) -> 0
B130: ADJUSTMENT FOR DEPRECIATION
B131: EBT | I131: =I124 -> 10861.493 | J131: =J124 -> 11336.57 | K131: =K124 -> 11218.998 | L131: =L124 -> 11908.664 | M131: =M124 -> 12610.504
B132: Add: Accounting Depreciation | I132: =I87 -> 3445.54 | J132: =J87 -> 3487.477 | K132: =K87 -> 3522.5745 | L132: =L87 -> 3554.3919 | M132: =M87 -> 3639.1378
B133: Less: Tax Depreciation | I133: =I113 -> -3994.9602 | J133: =J113 -> -4056.4608 | K133: =K113 -> -4111.9806 | L133: =L113 -> -4165.2563 | M133: =M113 -> -4219.1956
B134: EBT After Adjustment | I134: =SUM(I131:I133) -> 10312.073 | J134: =SUM(J131:J133) -> 10767.586 | K134: =SUM(K131:K133) -> 10629.591 | L134: =SUM(L131:L133) -> 11297.799 | M134: =SUM(M131:M133) -> 12030.446
B136: ADJUSTMENT FOR TAX LOSSES 1
...
